Workbook
Name _1枚目: #REF!
Name _1枚目: #REF!
Name _1枚目: [2]納入先!#REF!
Name _1枚目: [3]納入先!#REF!
Name _1枚目: #REF!
Name _2枚目: #REF!
Name _2枚目: #REF!
Name _2枚目: [4]UMG受領資料_注文!#REF!
Name _2枚目: #REF!
Name _2枚目: #REF!
Name _3枚目: #REF!
Name _3枚目: #REF!
Name _3枚目: [2]注文確認!#REF!
Name _3枚目: [3]注文確認!#REF!
Name _3枚目: #REF!
Name _4枚目: #REF!
Name _4枚目: #REF!
Name _4枚目: #REF!
Name _4枚目: #REF!
Name _4枚目: #REF!
Name a: #REF!
Name a: #REF!
Name a: #REF!
Name AA: #REF!
Name AA: #REF!
Name AA: #REF!
Name AA: #REF!
Name AA: #REF!
Name b: #REF!
Name b: #REF!
Name b: #REF!
Name B_下: #REF!
Name B_下: #REF!
Name B_下: '[10]営業系PG管理表 (テストフェーズ別)'!#REF!
Name B_下: '[10]営業系PG管理表 (テストフェーズ別)'!#REF!
Name B_下: #REF!
Name B_上: #REF!
Name B_上: #REF!
Name B_上: '[10]営業系PG管理表 (テストフェーズ別)'!#REF!
Name B_上: '[10]営業系PG管理表 (テストフェーズ別)'!#REF!
Name B_上: #REF!
Name CSV項目編集仕様: #REF!
Name CSV項目編集仕様: #REF!
Name dd: #REF!
Name dd: #REF!
Name dd: #REF!
Name DS_下: #REF!
Name DS_下: #REF!
Name DS_下: '[10]営業系PG管理表 (テストフェーズ別)'!#REF!
Name DS_下: '[10]営業系PG管理表 (テストフェーズ別)'!#REF!
Name DS_下: #REF!
Name DS_上: #REF!
Name DS_上: #REF!
Name DS_上: '[10]営業系PG管理表 (テストフェーズ別)'!#REF!
Name DS_上: '[10]営業系PG管理表 (テストフェーズ別)'!#REF!
Name DS_上: #REF!
Name ＤＳ担当: #REF!
Name ＤＳ担当: #REF!
Name GUI名称: #REF!
Name GUI名称: #REF!

Sheet  cover
C2: Inabata & Co., Ltd.
A8: EDI system
A10: Batch processing design document
A13: Techno UMG_Payment and payment details
A17: - Ver.2.00 -
A22: 45842
A24: Fujitsu Limited
V28: approval | AA28: create
AA29: 45842
AA30: FJ) Kunimitsu

Sheet  Change history
A1: Inabata & Co., Ltd. | F1: Batch processing design document | T1: Account Name | AH1: Customer abbreviation ID | AS1: Category Name | BB1: Author | BF1: Creation date | BJ1: Updated by | BN1: Update date
T3: Techno UMG | AH3: TUG | AS3: Payment and payment details | BB3: FJ) Kunimitsu | BF3: 45842
B7: No. | D7: Version | H7: Change Date | L7: Changed by | O7: classification | Q7: Change Control Number | U7: Changes | AF7: Changes | AY7: remarks
B8: =ROW()-7 -> 1 | D8: 2.00 | H8: 45842 | L8: FJ Kunimitsu | O8: New | Q8: R60795 | AF8: Create New | AY8: EDI middleware migration support
B9: =ROW()-7 -> 2
B10: =ROW()-7 -> 3
B11: =ROW()-7 -> 4
B12: =ROW()-7 -> 5
B13: =ROW()-7 -> 6
B14: =ROW()-7 -> 7
B15: =ROW()-7 -> 8
B16: =ROW()-7 -> 9
B17: =ROW()-7 -> 10
B18: =ROW()-7 -> 11
B19: =ROW()-7 -> 12
B20: =ROW()-7 -> 13
... B52: =ROW()-7 -> 45

Sheet  1. Transmission and reception information
A1: Inabata & Co., Ltd. | E1: Batch processing design document | O1: Account Name | X1: Customer abbreviation ID | AC1: Category Name | AG1: Author | AJ1: Creation date | AM1: Updated by | AP1: Update date
O3: =Change history!T3 -> Techno UMG | X3: =Change history!AH3 -> TUG | AC3: =Change history!AS3 -> Payment and payment details | AG3: =Change history!BB3 -> FJ) Kunimitsu | AJ3: =Change history!BF3 -> 45842
B6: ① List of sent and received files
K7: S: Start, H: Header, B: Body, T: Trailer, E: End
C8: No. | D8: category | K8: Format Type | R8: File structure | W8: 0Data transmission status
C9: 1 | D9: Payment details | K9: JPCA | R9: Heart, Body, and Teeth | W9: Nothing
B11: ②How to read the data
C12: Payment details data | V12: H: Header | AD12: *
C13: B: Body | V13: B: Body
C14: B: Body | V14: B: Body
C15: B: Body | V15: B: Body
V16: T: Trailer | AD16: *
Q18: File structure | V18: First record: Header, Body, Last record: Trailer
B19: ③Extraction conditions | V19: (*Added by NTS processing)
C21: Please refer to the "2. Function" sheet.
B23: 4. Header/trailer editing
C24: Granted in batches when converting to CII.
B26: ⑤0 data transmission specifications
C28: none

Sheet  2. Function
A1: Inabata & Co., Ltd. | E1: Batch processing design document | O1: Account Name | X1: Customer abbreviation ID | AC1: Category Name | AG1: Author | AJ1: Creation date | AM1: Updated by | AP1: Update date
O3: =Change history!T3 -> Techno UMG | X3: =Change history!AH3 -> TUG | AC3: =Change history!AS3 -> Payment and payment details | AG3: =Change history!BB3 -> FJ) Kunimitsu | AJ3: =Change history!BF3 -> 45842
B6: ①Purpose
C8: ・In Common Process_EDI Send_Payment_Data Extraction, import the linked file (TUGA140S02001) and create a payment details file for Techno UMG.
B10: ② Functionality overview
C12: ・Import the linked file, extract the data to be sent, and check the number of items.
C13: ・If the number of data items to be sent is not 0, create a file to send to the business partner.
C14: - Call mplt_CMN_EDI sending DB_payment update 2 and update the EDI sending status type and processing receipt number of EDI sending DB_payment.
B17: ③ Input/output information
C19: [input]
C20: Table name or file name | M20: Extraction conditions | AE20: Purpose of use
C21: Linked files | M21: EDI server: /PRD/Temp/TUGA140S02001 (created by common processing) | AE21: Extracting data to be sent
C22: 3. INPUT file layout (B)
C25: [output]
C26: Table name or file name | M26: Update conditions, extraction conditions | AE26: Purpose of use
C27: Sending file (payment details) | M27: Created based on the following extraction conditions. | AE27: Creating files to send to business partners
C28: (4. OUTPUT file layout (B)) | M28: Linked file.Delete category = "0" (enabled) and
M29: Linked file.Transmission data deletion category = "0" (transmission target) and
M30: Linked file.EDI_Current payment amount<>0
M32: The summary key for the sending file (payment) is as follows:
N33: Linked file. Supplier code (top 6)
N34: Linked file.Denomination
N35: Linked file. Head office/branch code
N36: Linked file. Supplier code (bottom 4)
N37: Linked file.Payment date
C39: EDI Send DB_Payment | M39: Updated based on the following renewal conditions: | AE39: Set the processed flag
M40: Send Sequence No. = Linked File.Send Sequence No. | AE40: EDI_Transmission status type="3" (Processed)
AE41: Processing receipt number = Linked file.Processing receipt number
B45: ④Function details
C47: (1) Importing linked files
D49: Import the linked file "TUGA140S02001" created in the common process.
D50: →File path: /EDI Server/PRD/Temp/TUGA140S02001
C53: (2) Creating data to be sent
D55: ① Obtain the data to be sent from the linked file.
D57: Extraction conditions:
E58: ・Linked file.Delete category = "0" (enabled)
E59: ・Linked file.Transmission data deletion classification = "0" (transmission target)
E60: ・Linked file.Payment・EDI_Current payment amount<>0
D62: ②If there is data to be sent, create a file to send to the business partner.
E63: 1 | F63: Editing data by recipient
F64: The recipient-specific data in the linked file obtained from ① is divided into the number of digits in "6. Recipient-specific data layout" and mapped to each item.
E66: 2 | F66: Sort in ascending order by the following sort key:
G67: Sort by:
H68: ・Linked file. Supplier code (top 6)
H69: ・Linked file. Denomination
H70: ・Linked file. Head office/branch code
H71: ・Linked file. Supplier code (bottom 4)
H72: ・Linked file.Payment date
E74: 3 | F74: Edit and output payment details files
F76: Map to the items in the sending file according to "7. Item Transfer (Payment Details Data Sending File)".
E78: 4 | F78: Create a file to send to a business partner
F79: For the output format, refer to the "4. OUTPUT file layout (B)" sheet.
G80: Location: EDI Server\PRD\Temp\
G81: Filename:
J82: Sending file (payment details) → TUGA14001
C84: (3) EDI Send DB_Payment Status Update (Common Process Call)
D86: Call mplt_CMN_EDI Send DB_Payment Update 2 and perform the following process.
E88: UPDATE EDI Send DB_Payment to EDI_Send Status Type="3" (Processed), Processing Receipt Number = Linked File.Processing Receipt Number.
E89: *Transmission sequence number = Linked file.Transmission sequence number

Sheet  3. INPUT file layout (B)
A6: ■ | B6: INPUT file layout | E6: Record length | G6: =SUM(G10:G37) -> 4241 | H6: Character encoding | J6: SJIS
A7: [Body Record]
B8: item | H8: decimal | I8: decimal point | J8: PAC/ | K8: Shift presence/absence | L8: start
A9: No. | B9: group | C9: Item name (Japanese name) | D9: Item name (English name) | E9: Character encoding | F9: Type | G9: number of digits | H9: number of digits | I9: presence or absence | J9: UNPAC | L9: position | M9: remarks
A10: =ROW()-9 -> 1 | C10: Transmission Sequence No. | D10: SND_SEQ_NO | F10: Half-width alphanumeric characters | G10: 10 | L10: 1
A11: =ROW()-9 -> 2 | C11: Data Exchange ID | D11: DATA_KOKAN_ID | F11: Half-width alphanumeric characters | G11: 6 | L11: =L10+G10 -> 11
A12: =ROW()-9 -> 3 | C12: EDI_Function Category Code | D12: EDI_KINO_CATEGORY_CD | F12: Half-width alphanumeric characters | G12: 4 | L12: =L11+G11 -> 17
A13: =ROW()-9 -> 4 | C13: Supplier Code | D13: SUP_CD | F13: Half-width numbers | G13: 14 | L13: =L12+G12 -> 21
A14: =ROW()-9 -> 5 | C14: Sales area | D14: HAN_KBN | F14: Half-width alphanumeric characters | G14: 3 | L14: =L13+G13 -> 35
A15: =ROW()-9 -> 6 | C15: Starting date | D15: KISAN_D | F15: Half-width alphanumeric characters | G15: 8 | L15: =L14+G14 -> 38
A16: =ROW()-9 -> 7 | C16: denomination | D16: KINSHU | F16: Half-width English characters | G16: 1 | L16: =L15+G15 -> 46
A17: =ROW()-9 -> 8 | C17: Head office/branch code | D17: HONSHITEN_CD | F17: Half-width numbers | G17: 1 | L17: =L16+G16 -> 47
A18: =ROW()-9 -> 9 | C18: Deadline | D18: SHIMEKIRI_YMD | F18: Date (year, month, day) | G18: 8 | L18: =L17+G17 -> 48
A19: =ROW()-9 -> 10 | C19: Maturity Date | D19: MANKI_D | F19: Half-width alphanumeric characters | G19: 8 | L19: =L18+G18 -> 56
A20: =ROW()-9 -> 11 | C20: Bank Code | D20: BANK_CD | F20: Half-width numbers | G20: 4 | L20: =L19+G19 -> 64
A21: =ROW()-9 -> 12 | C21: Branch code | D21: SHITEN_CD | F21: Half-width numbers | G21: 3 | L21: =L20+G20 -> 68
A22: =ROW()-9 -> 13 | C22: Bank name (kana) | D22: BANK_NMK | F22: Half-width characters | G22: 40 | L22: =L21+G21 -> 71
... A25: =ROW()-9 -> 16 | C25: Transfer account number | D25: FURIKOMI_KOZA_NO | F25: Half-width alphanumeric characters | G25: 7 | L25: =L24+G24 -> 152
A26: =ROW()-9 -> 17 | C26: EDI_Current payment amount | D26: EDI_KONKAI_PAY_GAKU | F26: Number | G26: 13 | H26: 0 | L26: =L25+G25 -> 159
A27: =ROW()-9 -> 18 | C27: Payment date | D27: PAY_YMD | F27: Date (year, month, day) | G27: 8 | L27: =L26+G26 -> 172
A28: =ROW()-9 -> 19 | C28: Transmission data deletion category | D28: SND_DATA_DEL_KBN | F28: Half-width numbers | G28: 1 | L28: =L27+G27 -> 180
A29: =ROW()-9 -> 20 | C29: Receive Sequence No. | D29: RCV_SEQ_NO | F29: Half-width alphanumeric characters | G29: 10 | L29: =L28+G28 -> 181
A30: =ROW()-9 -> 21 | C30: Processing receipt number | D30: FUNC_UKETSUKE_NO | F30: Number | G30: 10 | L30: =L29+G29 -> 191
A31: =ROW()-9 -> 22 | C31: Deletion category | D31: DEL_KBN | F31: Half-width numbers | G31: 1 | L31: =L30+G30 -> 201
A32: =ROW()-9 -> 23 | C32: Receive sequence No. 2 | D32: RCV_SEQ_NO_2 | F32: Half-width characters | G32: 10 | L32: =L31+G31 -> 202
A33: =ROW()-9 -> 24 | C33: Confirmed Purchase Responsible Organization Code (old) | D33: CONFIRM_SIR_SKNIN_SSHK_CD_OLD | F33: Half-width alphanumeric characters | G33: 5 | L33: =L32+G32 -> 212
A34: =ROW()-9 -> 25 | C34: JPCA_EDI billed amount | D34: JPCA_EDI_SEIKYU_GAKU | F34: Number | G34: 13 | H34: 0 | L34: =L33+G33 -> 217
A35: =ROW()-9 -> 26 | C35: Data by counterparty | D35: AITE_SAKI_BETSU_DATA | F35: Mixed half-width characters | G35: 4000 | L35: =L34+G34 -> 230
A36: =ROW()-9 -> 27 | C36: Processing receipt number | D36: FUNC_UKETSUKE_NO | F36: Number | G36: 10 | H36: 0 | L36: =L35+G35 -> 4230
A37: =ROW()-9 -> 28 | C37: FILLER | D37: FILLER | F37: Half-width characters | G37: 2 | L37: =L36+G36 -> 4240 | M37: Line feed code (2 bytes)

Sheet  4. OUTPUT file layout (B)
A6: ■ | B6: OUTPUT file layout | E6: Record length | G6: =SUM(G10:G142) -> 1900 | H6: Character encoding | J6: SJIS
A7: [Body Record]
B8: item | H8: decimal | I8: decimal point | J8: PAC/ | K8: Shift presence/absence | L8: start
A9: No. | B9: group | C9: Item name (Japanese name) | D9: Item name (English name) | E9: Character encoding | F9: Type | G9: number of digits | H9: number of digits | I9: presence or absence | J9: UNPAC | L9: position | M9: remarks
A10: =ROW()-9 -> 1 | C10: Reserve | D10: RESERVE | F10: character | G10: 1 | L10: 1
A11: =ROW()-9 -> 2 | C11: BPID | D11: BPID | F11: character | G11: 8 | L11: =L10+G10 -> 2
A12: =ROW()-9 -> 3 | C12: Sending and receiving | D12: SND_RCV | F12: character | G12: 1 | L12: =L11+G11 -> 10
A13: =ROW()-9 -> 4 | C13: Information classification | D13: INF_KBN | F13: character | G13: 4 | L13: =L12+G12 -> 11
A14: =ROW()-9 -> 5 | C14: Company code | D14: JISHA_CD | F14: character | G14: 12 | L14: =L13+G13 -> 15
A15: =ROW()-9 -> 6 | C15: Recipient Code | D15: AITE_SAKI_CD | F15: character | G15: 12 | L15: =L14+G14 -> 27
A16: =ROW()-9 -> 7 | C16: Data Type | D16: DATA_SBT | F16: character | G16: 4 | L16: =L15+G15 -> 39
A17: =ROW()-9 -> 8 | C17: Processing classification | D17: FUNC_KBN | F17: character | G17: 1 | L17: =L16+G16 -> 43
A18: =ROW()-9 -> 9 | C18: Processing date | D18: FUNC_YMD | F18: character | G18: 6 | L18: =L17+G17 -> 44
A19: =ROW()-9 -> 10 | C19: Processing time | D19: FUNC_TM | F19: character | G19: 6 | L19: =L18+G18 -> 50
A20: =ROW()-9 -> 11 | C20: Red and Black Division | D20: AKAKURO_KBN | F20: character | G20: 1 | L20: =L19+G19 -> 56
A21: =ROW()-9 -> 12 | C21: Ordering company code | D21: HACSHA_KIGYO_CD | F21: character | G21: 6 | L21: =L20+G20 -> 57
A22: =ROW()-9 -> 13 | C22: Ordering department code | D22: HACSHA_BMN_CD | F22: character | G22: 6 | L22: =L21+G21 -> 63
... A24: =ROW()-9 -> 15 | C24: New purchaser department code | D24: NEW_HACSHA_BMN_CD | F24: character | G24: 6 | L24: =L23+G23 -> 75
A25: =ROW()-9 -> 16 | C25: Contractor company code | D25: JUC_KIGYO_CD | F25: character | G25: 6 | L25: =L22+G22 -> 69
A26: =ROW()-9 -> 17 | C26: Order recipient department code | D26: JUC_BMN_CD | F26: character | G26: 6 | L26: =L25+G25 -> 75
A27: =ROW()-9 -> 18 | C27: Claimant company code | D27: SEIKYU_KIGYO_CD | F27: character | G27: 6 | L27: =L26+G26 -> 81
A28: =ROW()-9 -> 19 | C28: Claimant department code | D28: SEIKYU_BMN_CD | F28: character | G28: 6 | L28: =L27+G27 -> 87
A29: =ROW()-9 -> 20 | C29: Payer company code | D29: PAY_KIGYO_CD | F29: character | G29: 6 | L29: =L28+G28 -> 93
A30: =ROW()-9 -> 21 | C30: Payer Department Code | D30: PAY_BMN_CD | F30: character | G30: 6 | L30: =L29+G29 -> 99
A31: =ROW()-9 -> 22 | C31: Contract number | D31: KEIYAKU_NO | F31: character | G31: 10 | L31: =L30+G30 -> 105
A32: =ROW()-9 -> 23 | C32: Implementation date | D32: JISSHI_YMD | F32: character | G32: 6 | L32: =L31+G31 -> 115
A33: =ROW()-9 -> 24 | C33: Order number | D33: CHUMON_NO | F33: character | G33: 10 | L33: =L32+G32 -> 121
A34: =ROW()-9 -> 25 | C34: Orderer and order date | D34: HACSHA_CHUMON_D | F34: character | G34: 6 | L34: =L33+G33 -> 131
A35: =ROW()-9 -> 26 | C35: Orderer and order time | D35: HACSHA_CHUMON_TM | F35: character | G35: 4 | L35: =L34+G34 -> 137
A36: =ROW()-9 -> 27 | C36: Order Class | D36: ORDER_KBN | F36: character | G36: 1 | L36: =L35+G35 -> 141
A37: =ROW()-9 -> 28 | C37: Contact necessity classification | D37: RENRAKU_YN_KBN | F37: character | G37: 1 | L37: =L36+G36 -> 142
... A71: =ROW()-9 -> 62 | C71: Quantity confirmation indicator | D71: SURYO_CONFIRM_KBN | F71: character | G71: 1 | L71: =L70+G70 -> 737
A72: =ROW()-9 -> 63 | C72: Sales price | D72: HAN_TANK | F72: Number | G72: 13 | H72: 3 | I72: Yes | J72: PAC | L72: =L71+G71 -> 738
A73: =ROW()-9 -> 64 | C73: Unit price | D73: TANK_UNIT | F73: character | G73: 3 | L73: =L72+G72 -> 751
A74: =ROW()-9 -> 65 | C74: Unit price category | D74: TANK_KBN | F74: character | G74: 1 | L74: =L73+G73 -> 754
A75: =ROW()-9 -> 66 | C75: Payment classification | D75: KOSEN_KBN | F75: character | G75: 1 | L75: =L74+G74 -> 755
A76: =ROW()-9 -> 67 | C76: Commission unit price | D76: KOSEN_TANK | F76: Number | G76: 13 | H76: 3 | I76: Yes | J76: PAC | L76: =L75+G75 -> 756
A77: =ROW()-9 -> 68 | C77: commission | D77: KOSEN | F77: Number | G77: 13 | H77: 0 | J77: PAC | L77: =L76+G76 -> 769
A78: =ROW()-9 -> 69 | C78: Secondary store payment classification | D78: NIJITEN_KOSEN_KBN | F78: character | G78: 1 | L78: =L77+G77 -> 782
A79: =ROW()-9 -> 70 | C79: Secondary store commission unit price | D79: NIJITEN_KOSEN_TANK | F79: Number | G79: 13 | H79: 3 | I79: Yes | J79: PAC | L79: =L78+G78 -> 783
A80: =ROW()-9 -> 71 | C80: Secondary store commission | D80: NIJITEN_KOSEN | F80: Number | G80: 13 | H80: 0 | J80: PAC | L80: =L79+G79 -> 796
A81: =ROW()-9 -> 72 | C81: Delivery company code | D81: NNY_KIGYO_CD | F81: character | G81: 6 | L81: =L80+G80 -> 809
A82: =ROW()-9 -> 73 | C82: Delivery department code | D82: NNY_BMN_CD | F82: character | G82: 6 | L82: =L81+G81 -> 815
A83: =ROW()-9 -> 74 | C83: Delivery destination name (kana) | D83: NNY_NM_KANA | F83: character | G83: 40 | L83: =L82+G82 -> 821
A84: =ROW()-9 -> 75 | C84: Delivery destination name (kanji) | D84: NNY_NM_KANJI | F84: character | G84: 40 | L84: =L83+G83 -> 861
A85: =ROW()-9 -> 76 | C85: Delivery Terms | D85: UKEWATASHI_JOKEN | F85: character | G85: 2 | L85: =L84+G84 -> 901
A86: =ROW()-9 -> 77 | C86: Delivery address (kana) | D86: UKEWATASHI_BASHO_ADDRK | F86: character | G86: 74 | L86: =L85+G85 -> 903
A87: =ROW()-9 -> 78 | C87: Delivery address (kanji) | D87: UKEWATASHI_BASHO_ADDR | F87: character | G87: 74 | L87: =L86+G86 -> 977
A88: =ROW()-9 -> 79 | C88: District Code | D88: CHIKU_CD | F88: character | G88: 11 | L88: =L87+G87 -> 1051
A89: =ROW()-9 -> 80 | C89: post code | D89: ZIP | F89: character | G89: 7 | L89: =L88+G88 -> 1062
A90: =ROW()-9 -> 81 | C90: telephone number | D90: TEL | F90: character | G90: 12 | L90: =L89+G89 -> 1069
A91: =ROW()-9 -> 82 | C91: Fax Phone Number | D91: FAX_TEL | F91: character | G91: 12 | L91: =L90+G90 -> 1081
A92: =ROW()-9 -> 83 | C92: Desired delivery date | D92: KIBO_NONYU_YMD | F92: character | G92: 6 | L92: =L91+G91 -> 1093
... A97: =ROW()-9 -> 88 | C97: Delivery requirements (Kanji) | D97: NONYU_YOKEN_KANJI | F97: character | G97: 44 | L97: =L96+G96 -> 1163
A98: =ROW()-9 -> 89 | C98: Payment amount | D98: PAY_GAKU | F98: Number | G98: 13 | H98: 0 | J98: PAC | L98: =L97+G97 -> 1207
A99: =ROW()-9 -> 90 | C99: Payment reference number | D99: PAY_SEIRI_NO | F99: character | G99: 12 | L99: =L98+G98 -> 1220
A100: =ROW()-9 -> 91 | C100: Bill number (check number) | D100: TEGATA_NO_KOGITTE | F100: character | G100: 12 | L100: =L99+G99 -> 1232
A101: =ROW()-9 -> 92 | C101: Issuing bank (code) | D101: ISSUE_BANK_CD | F101: character | G101: 7 | L101: =L100+G100 -> 1244
A102: =ROW()-9 -> 93 | C102: Issuing bank (name) | D102: ISSUE_BANK_NM | F102: character | G102: 30 | L102: =L101+G101 -> 1251
A103: =ROW()-9 -> 94 | C103: Transfer bank (code) | D103: FURIKOMI_BANK_CD | F103: character | G103: 7 | L103: =L102+G102 -> 1281
A104: =ROW()-9 -> 95 | C104: Transfer bank (name) | D104: FURIKOMI_BANK_NM | F104: character | G104: 30 | L104: =L103+G103 -> 1288
A105: =ROW()-9 -> 96 | C105: Account number | D105: KOZA_NO | F105: character | G105: 7 | L105: =L104+G104 -> 1318
A106: =ROW()-9 -> 97 | C106: Payment Requirements | D106: PAY_YOKEN | F106: character | G106: 10 | L106: =L105+G105 -> 1325
A107: =ROW()-9 -> 98 | C107: Order Quantity | D107: CHUMON_SURYO | F107: Number | G107: 13 | H107: 3 | I107: Yes | J107: PAC | L107: =L106+G106 -> 1335
A108: =ROW()-9 -> 99 | C108: Order/sales quantity | D108: CHUMON_HAN_KOSU | F108: Number | G108: 13 | H108: 3 | I108: Yes | J108: PAC | L108: =L107+G107 -> 1348
A109: =ROW()-9 -> 100 | C109: Order Quantity Unit | D109: CHUMON_SURYO_UNIT | F109: character | G109: 3 | L109: =L108+G108 -> 1361
A110: =ROW()-9 -> 101 | C110: Sales volume | D110: HAN_SURYO | F110: Number | G110: 13 | H110: 3 | I110: Yes | J110: PAC | L110: =L109+G109 -> 1364
A111: =ROW()-9 -> 102 | C111: Amount calculation quantity | D111: GAKU_CLC_SURYO | F111: Number | G111: 13 | H111: 3 | I111: Yes | J111: PAC | L111: =L110+G110 -> 1377
A112: =ROW()-9 -> 103 | C112: Packaging | D112: NISUGATA | F112: character | G112: 10 | L112: =L111+G111 -> 1390
A113: =ROW()-9 -> 104 | C113: capacity | D113: YORYO | F113: Number | G113: 13 | H113: 3 | I113: Yes | J113: PAC | L113: =L112+G112 -> 1400
A114: =ROW()-9 -> 105 | C114: Sales price | D114: HAN_GAKU | F114: Number | G114: 13 | H114: 0 | J114: PAC | L114: =L113+G113 -> 1413
A115: =ROW()-9 -> 106 | C115: Invoice amount | D115: SEIKYU_GAKU | F115: Number | G115: 13 | H115: 0 | J115: PAC | L115: =L114+G114 -> 1426
A116: =ROW()-9 -> 107 | C116: Consumption tax amount | D116: SHOHIZEI_GAKU | F116: Number | G116: 13 | H116: 0 | J116: PAC | L116: =L115+G115 -> 1439
A117: =ROW()-9 -> 108 | C117: Invoice amount including tax | D117: ZEIKOMI_SEIKYU_GAKU | F117: Number | G117: 13 | H117: 0 | J117: PAC | L117: =L116+G116 -> 1452
A118: =ROW()-9 -> 109 | C118: Unit price amount category | D118: TANK_GAKU_KBN | F118: character | G118: 1 | L118: =L117+G117 -> 1465
A119: =ROW()-9 -> 110 | C119: Transaction Classification | D119: TORIHIKI_KBN | F119: character | G119: 1 | L119: =L118+G118 -> 1466
A120: =ROW()-9 -> 111 | C120: Retroactive classification | D120: SOKYU_KBN | F120: character | G120: 1 | L120: =L119+G119 -> 1467
A121: =ROW()-9 -> 112 | C121: Shipping and billing category | D121: SHUKKA_SEIKYU_KBN | F121: character | G121: 1 | L121: =L120+G120 -> 1468
A122: =ROW()-9 -> 113 | C122: Taxation category | D122: KAZEI_KBN | F122: character | G122: 2 | L122: =L121+G121 -> 1469
A123: =ROW()-9 -> 114 | C123: Backorder Classification | D123: BACK_ORDER_KBN | F123: character | G123: 1 | L123: =L122+G122 -> 1471
A124: =ROW()-9 -> 115 | C124: Recording date | D124: KEIJO_YM | F124: character | G124: 4 | L124: =L123+G123 -> 1472
A125: =ROW()-9 -> 116 | C125: Shipping date (planned) | D125: SHUKKA_YMD_YOTEI | F125: character | G125: 6 | L125: =L124+G124 -> 1476
A126: =ROW()-9 -> 117 | C126: Shipping Report Number | D126: SHUKKA_HOKOKU_NO | F126: character | G126: 25 | L126: =L125+G125 -> 1482
A127: =ROW()-9 -> 118 | C127: Shipping Invoice Number | D127: SHUKKA_SEIKYU_NO | F127: character | G127: 10 | L127: =L126+G126 -> 1507
A128: =ROW()-9 -> 119 | C128: Shipping location | D128: SHUKKA_BASHO | F128: character | G128: 5 | L128: =L127+G127 -> 1517
A129: =ROW()-9 -> 120 | C129: Shipping instruction comment (kana) | D129: SHUKKA_SASHIZU_COMMENT_KANA | F129: character | G129: 44 | L129: =L128+G128 -> 1522
... A142: =ROW()-9 -> 133 | C142: FILLER | D142: FILLER | F142: character | G142: 67 | L142: =L141+G141 -> 1822

Sheet  5. Item transfer (EDI sending DB_payment)_update
A6: ■ | B6: EDI Outbound DB_Payment Mapping Specifications
A7: EDI Outbound DB_Payment Mapping | H7: Setting value
A8: No. | B8: Item Group | C8: Item name (Japanese name) | D8: Item name (English name) | E8: Type | F8: number of digits | G8: Number of decimal places | H8: Simple transfer | I8: Editing content
A9: =ROW()-8 -> 1 | C9: Transmission Sequence No. | D9: SND_SEQ_NO | E9: Half-width alphanumeric characters | F9: 10
A10: =ROW()-8 -> 2 | C10: Data Exchange ID | D10: DATA_KOKAN_ID | E10: Half-width alphanumeric characters | F10: 6
A11: =ROW()-8 -> 3 | C11: EDI_Function Category Code | D11: EDI_KINO_CATEGORY_CD | E11: Half-width alphanumeric characters | F11: 4
A12: =ROW()-8 -> 4 | C12: Supplier Code | D12: SUP_CD | E12: Half-width numbers | F12: 10
A13: =ROW()-8 -> 5 | C13: Sales area | D13: HAN_KBN | E13: Half-width alphanumeric characters | F13: 3
A14: =ROW()-8 -> 6 | C14: Starting date | D14: KISAN_D | E14: Half-width alphanumeric characters | F14: 8
A15: =ROW()-8 -> 7 | C15: denomination | D15: KINSHU | E15: Half-width English characters | F15: 1
A16: =ROW()-8 -> 8 | C16: Head office/branch code | D16: HONSHITEN_CD | E16: Half-width numbers | F16: 1
A17: =ROW()-8 -> 9 | C17: Deadline | D17: SHIMEKIRI_YMD | E17: Date (year, month, day) | F17: 8
A18: =ROW()-8 -> 10 | C18: Maturity Date | D18: MANKI_D | E18: Half-width alphanumeric characters | F18: 8
A19: =ROW()-8 -> 11 | C19: Bank Code | D19: BANK_CD | E19: Half-width numbers | F19: 4
A20: =ROW()-8 -> 12 | C20: Branch code | D20: SHITEN_CD | E20: Half-width numbers | F20: 3
... A24: =ROW()-8 -> 16 | C24: Transfer account number | D24: FURIKOMI_KOZA_NO | E24: Half-width alphanumeric characters | F24: 7
A25: =ROW()-8 -> 17 | C25: EDI_Current payment amount | D25: EDI_KONKAI_PAY_GAKU | E25: Decimal numbers | F25: 13 | G25: 0
A26: =ROW()-8 -> 18 | C26: Payment date | D26: PAY_YMD | E26: Date (year, month, day) | F26: 8
A27: =ROW()-8 -> 19 | C27: EDI_Transmission Status Type | D27: EDI_SND_JOKYO_SBT | E27: Half-width alphanumeric characters | F27: 1 | I27: "3" (Processed)
A28: =ROW()-8 -> 20 | C28: Date and time of sending | D28: SND_DT | E28: Full-byte mixed characters | F28: 19
A29: =ROW()-8 -> 21 | C29: Transmission data deletion category | D29: SND_DATA_DEL_KBN | E29: Half-width numbers | F29: 1
A30: =ROW()-8 -> 22 | C30: Receive Sequence No. | D30: RCV_SEQ_NO | E30: Half-width alphanumeric characters | F30: 10
A31: =ROW()-8 -> 23 | C31: Processing receipt number | D31: FUNC_UKETSUKE_NO | E31: Decimal numbers | F31: 10 | G31: 0 | H31: [Processing receipt number]
A32: =ROW()-8 -> 24 | C32: Deletion category | D32: DEL_KBN | E32: Half-width numbers | F32: 1
A33: =ROW()-8 -> 25 | C33: Creation date | D33: CREATE_DT | E33: Full-byte mixed characters | F33: 19
A34: =ROW()-8 -> 26 | C34: Created by | D34: CREATE_USR | E34: Half-width alphanumeric characters | F34: 20
A35: =ROW()-8 -> 27 | C35: Creation Process | D35: CREATE_FUNC | E35: Full-byte mixed characters | F35: 64
A36: =ROW()-8 -> 28 | C36: Latest update date and time | D36: NEW_UPDATE_DT | E36: Full-byte mixed characters | F36: 19 | I36: System date and time (YYYY/MM/DD HH:MI:SS)
A37: =ROW()-8 -> 29 | C37: Latest Updated User | D37: NEW_UPDATE_USR | E37: Half-width alphanumeric characters | F37: 20 | I37: "EDI"
A38: =ROW()-8 -> 30 | C38: Latest update processing | D38: NEW_UPDATE_FUNC | E38: Full-byte mixed characters | F38: 64 | I38: "m_TUG_Payment_Payment_Details_Data_Edit_010"
A39: =ROW()-8 -> 31 | C39: Number of updates | D39: UPDATE_CNT | E39: Decimal numbers | F39: 9 | G39: 0 | I39: [Update count] +1

Sheet  6. Data layout by destination
E6: Record length | F6: =SUM(G10:G140) -> 4000
A7: ■ | B7: Data layout by destination
B8: change | C8: item | H8: decimal | I8: decimal point | J8: start
A9: No. | B9: part | C9: group | D9: Item name (Japanese name) | E9: Item name (English name) | F9: Type | G9: number of digits | H9: number of digits | I9: presence or absence | J9: position | K9: remarks
A10: =ROW()-9 -> 1 | D10: Reserve | E10: RESERVE | F10: character | G10: 1 | J10: 1
A11: =ROW()-9 -> 2 | D11: BPID | E11: BPID | F11: character | G11: 8 | J11: =J10+G10 -> 2
A12: =ROW()-9 -> 3 | D12: Sending and receiving | E12: SND_RCV | F12: character | G12: 1 | J12: =J11+G11 -> 10
A13: =ROW()-9 -> 4 | D13: Information classification | E13: INF_KBN | F13: character | G13: 4 | J13: =J12+G12 -> 11
A14: =ROW()-9 -> 5 | D14: Company code | E14: JISHA_CD | F14: character | G14: 12 | J14: =J13+G13 -> 15
A15: =ROW()-9 -> 6 | D15: Recipient Code | E15: AITE_SAKI_CD | F15: character | G15: 12 | J15: =J14+G14 -> 27
A16: =ROW()-9 -> 7 | D16: Data Type | E16: DATA_SBT | F16: character | G16: 4 | J16: =J15+G15 -> 39
A17: =ROW()-9 -> 8 | D17: Processing classification | E17: FUNC_KBN | F17: character | G17: 1 | J17: =J16+G16 -> 43
A18: =ROW()-9 -> 9 | D18: Processing date | E18: FUNC_YMD | F18: character | G18: 6 | J18: =J17+G17 -> 44
A19: =ROW()-9 -> 10 | D19: Processing time | E19: FUNC_TM | F19: character | G19: 6 | J19: =J18+G18 -> 50
A20: =ROW()-9 -> 11 | D20: Red and Black Division | E20: AKAKURO_KBN | F20: character | G20: 1 | J20: =J19+G19 -> 56
A21: =ROW()-9 -> 12 | D21: Ordering company code | E21: HACSHA_KIGYO_CD | F21: character | G21: 6 | J21: =J20+G20 -> 57
A22: =ROW()-9 -> 13 | D22: Ordering department code | E22: HACSHA_BMN_CD | F22: character | G22: 6 | J22: =J21+G21 -> 63
... A51: =ROW()-9 -> 42 | D51: Lot No. | E51: LOT_NO | F51: character | G51: 10 | J51: =J50+G50 -> 418
A52: =ROW()-9 -> 43 | D52: Customer company code | E52: JUYOKA_KIGYO_CD | F52: character | G52: 6 | J52: =J49+G49 -> 417
A53: =ROW()-9 -> 44 | D53: Customer sector code | E53: JUYOKA_BMN_CD | F53: character | G53: 6 | J53: =J50+G50 -> 418
A54: =ROW()-9 -> 45 | D54: Customer name (kana) | E54: JUYOKA_NM_KANA | F54: character | G54: 40 | J54: =J51+G51 -> 428
A55: =ROW()-9 -> 46 | D55: Consumer name (kanji) | E55: JUYOKA_NM_KANJI | F55: character | G55: 40 | J55: =J52+G52 -> 423
A56: =ROW()-9 -> 47 | D56: Customer order number | E56: JUYOKA_CHUMON_NO | F56: character | G56: 10 | J56: =J53+G53 -> 424
A57: =ROW()-9 -> 48 | D57: Secondary store company code | E57: NIJITEN_KIGYO_CD | F57: character | G57: 6 | J57: =J53+G53 -> 424
A58: =ROW()-9 -> 49 | D58: Secondary store department code | E58: NIJITEN_BMN_CD | F58: character | G58: 6 | J58: =J54+G54 -> 468
A59: =ROW()-9 -> 50 | D59: Secondary store name (kana) | E59: NIJITEN_NM_KANA | F59: character | G59: 40 | J59: =J55+G55 -> 463
A60: =ROW()-9 -> 51 | D60: Secondary store name (kanji) | E60: NIJITEN_NM_KANJI | F60: character | G60: 40 | J60: =J56+G56 -> 434
A61: =ROW()-9 -> 52 | D61: Third-tier store code | E61: SANJITEN_CD | F61: character | G61: 92 | J61: =J58+G58 -> 474
A62: =ROW()-9 -> 53 | D62: Payment terms deadline | E62: KESSAI_JOKEN_SHIMEKIRI_D | F62: character | G62: 6 | J62: =J59+G59 -> 503
A63: =ROW()-9 -> 54 | D63: Payment terms start date | E63: KESSAI_JOKEN_KISAN_D | F63: character | G63: 6 | J63: =J60+G60 -> 474
A64: =ROW()-9 -> 55 | D64: Payment terms and means | E64: KESSAI_JOKEN_SHUDAN | F64: character | G64: 1 | J64: =J61+G61 -> 566
A65: =ROW()-9 -> 56 | D65: Payment terms maturity date | E65: KESSAI_JOKEN_MANKI_D | F65: character | G65: 6 | J65: =J62+G62 -> 509
A66: =ROW()-9 -> 57 | D66: Payment terms criteria | E66: KESSAI_JOKEN_KIJUN | F66: character | G66: 1 | J66: =J63+G63 -> 480
A67: =ROW()-9 -> 58 | D67: Payment Terms | E67: KESSAI_JOKEN | F67: character | G67: 15 | J67: =J64+G64 -> 567
A68: =ROW()-9 -> 59 | D68: Quantity confirmation indicator | E68: SURYO_CONFIRM_KBN | F68: character | G68: 1 | J68: =J65+G65 -> 515
A69: =ROW()-9 -> 60 | B69: ● | D69: Sales price | E69: HAN_TANK | F69: Number | G69: 13 | H69: 3 | I69: Nothing | J69: =J66+G66 -> 481 | K69: Unpack numeric strings and use them as numbers
A70: =ROW()-9 -> 61 | D70: Unit price | E70: TANK_UNIT | F70: character | G70: 3 | J70: =J67+G67 -> 582
A71: =ROW()-9 -> 62 | D71: Unit price category | E71: TANK_KBN | F71: character | G71: 1 | J71: =J68+G68 -> 516
A72: =ROW()-9 -> 63 | D72: Payment classification | E72: KOSEN_KBN | F72: character | G72: 1 | J72: =J69+G69 -> 494
A73: =ROW()-9 -> 64 | B73: ● | D73: Commission unit price | E73: KOSEN_TANK | F73: Number | G73: 13 | H73: 3 | I73: Nothing | J73: =J70+G70 -> 585 | K73: Unpack numeric strings and use them as numbers
A74: =ROW()-9 -> 65 | B74: ● | D74: amount of money | E74: KOSEN_GAKU | F74: Number | G74: 13 | H74: 0 | J74: =J71+G71 -> 517 | K74: Unpack numeric strings and use them as numbers
A75: =ROW()-9 -> 66 | D75: Secondary store payment classification | E75: NIJITEN_KOSEN_KBN | F75: character | G75: 1 | J75: =J72+G72 -> 495
A76: =ROW()-9 -> 67 | B76: ● | D76: Secondary store commission unit price | E76: NIJITEN_KOSEN_TANK | F76: Number | G76: 13 | H76: 3 | I76: Nothing | J76: =J73+G73 -> 598 | K76: Unpack numeric strings and use them as numbers
A77: =ROW()-9 -> 68 | B77: ● | D77: 2nd store account amount | E77: NIJITEN_KOSEN_GAKU | F77: Number | G77: 13 | H77: 0 | J77: =J74+G74 -> 530 | K77: Unpack numeric strings and use them as numbers
A78: =ROW()-9 -> 69 | D78: Delivery company code | E78: NNY_KIGYO_CD | F78: character | G78: 6 | J78: =J74+G74 -> 530
A79: =ROW()-9 -> 70 | D79: Delivery department code | E79: NNY_BMN_CD | F79: character | G79: 6 | J79: =J75+G75 -> 496
A80: =ROW()-9 -> 71 | D80: Delivery destination name (kana) | E80: NNY_NM_KANA | F80: character | G80: 40 | J80: =J76+G76 -> 611
A81: =ROW()-9 -> 72 | D81: Delivery destination name (Kanji) | E81: NNY_NM_KANJI | F81: character | G81: 40 | J81: =J77+G77 -> 543
A82: =ROW()-9 -> 73 | D82: Delivery Terms | E82: UKEWATASHI_JOKEN | F82: character | G82: 2 | J82: =J79+G79 -> 502
A83: =ROW()-9 -> 74 | D83: Delivery address (kana) | E83: UKEWATASHI_BASHO_ADDRK | F83: character | G83: 74 | J83: =J80+G80 -> 651
A84: =ROW()-9 -> 75 | D84: Delivery address (Kanji) | E84: UKEWATASHI_BASHO_ADDR | F84: character | G84: 74 | J84: =J81+G81 -> 583
A85: =ROW()-9 -> 76 | D85: District Code | E85: CHIKU_CD | F85: character | G85: 11 | J85: =J82+G82 -> 504
A86: =ROW()-9 -> 77 | D86: post code | E86: ZIP | F86: character | G86: 7 | J86: =J83+G83 -> 725
A87: =ROW()-9 -> 78 | D87: telephone number | E87: TEL | F87: character | G87: 12 | J87: =J84+G84 -> 657
A88: =ROW()-9 -> 79 | D88: Fax number | E88: FAX | F88: character | G88: 12 | J88: =J85+G85 -> 515
A89: =ROW()-9 -> 80 | D89: Desired delivery date | E89: KIBO_NONYU_D | F89: character | G89: 6 | J89: =J86+G86 -> 732
A90: =ROW()-9 -> 81 | D90: Desired delivery time | E90: KIBO_NONYU_TM | F90: character | G90: 4 | J90: =J87+G87 -> 669
A91: =ROW()-9 -> 82 | D91: Desired delivery comment | E91: KIBO_NONYU_COMMENT | F91: character | G91: 10 | J91: =J88+G88 -> 527
A92: =ROW()-9 -> 83 | D92: Delivery date | E92: NONYU_YMD | F92: character | G92: 6 | J92: =J89+G89 -> 738
A93: =ROW()-9 -> 84 | D93: Delivery requirements (kana) | E93: NONYU_YOKEN_KANA | F93: character | G93: 44 | J93: =J90+G90 -> 673
A94: =ROW()-9 -> 85 | D94: Delivery requirements (Kanji) | E94: NONYU_YOKEN_KANJI | F94: character | G94: 44 | J94: =J91+G91 -> 537
A95: =ROW()-9 -> 86 | B95: ● | D95: Payment amount | E95: PAY_GAKU | F95: Number | G95: 13 | H95: 0 | J95: =J92+G92 -> 744 | K95: Unpack numeric strings and use them as numbers
A96: =ROW()-9 -> 87 | D96: Payment reference number | E96: PAY_SEIRI_NO | F96: character | G96: 12 | J96: =J93+G93 -> 717
A97: =ROW()-9 -> 88 | D97: Bill number (check number) | E97: TEGATA_NO_KOGITTE | F97: character | G97: 12 | J97: =J94+G94 -> 581
A98: =ROW()-9 -> 89 | D98: Issuing bank (code) | E98: ISSUE_BANK_CD | F98: character | G98: 7 | J98: =J95+G95 -> 757
A99: =ROW()-9 -> 90 | D99: Issuing bank (name) | E99: ISSUE_BANK_NM | F99: character | G99: 30 | J99: =J96+G96 -> 729
A100: =ROW()-9 -> 91 | D100: Transfer bank (code) | E100: FURIKOMI_BANK_CD | F100: character | G100: 7 | J100: =J97+G97 -> 593
A101: =ROW()-9 -> 92 | D101: Transfer bank (name) | E101: FURIKOMI_BANK_NM | F101: character | G101: 30 | J101: =J98+G98 -> 764
A102: =ROW()-9 -> 93 | D102: Account number | E102: KOZA_NO | F102: character | G102: 7 | J102: =J99+G99 -> 759
A103: =ROW()-9 -> 94 | D103: Payment Requirements | E103: PAY_YOKEN | F103: character | G103: 10 | J103: =J100+G100 -> 600
A104: =ROW()-9 -> 95 | B104: ● | D104: Order Quantity | E104: CHUMON_SURYO | F104: Number | G104: 13 | H104: 3 | I104: Nothing | J104: =J101+G101 -> 794 | K104: Unpack numeric strings and use them as numbers
A105: =ROW()-9 -> 96 | B105: ● | D105: Order/sales quantity | E105: CHUMON_HAN_KOSU | F105: Number | G105: 13 | H105: 3 | I105: Nothing | J105: =J102+G102 -> 766 | K105: Unpack numeric strings and use them as numbers
A106: =ROW()-9 -> 97 | D106: Order Quantity Unit | E106: CHUMON_SURYO_UNIT | F106: character | G106: 3 | J106: =J103+G103 -> 610
A107: =ROW()-9 -> 98 | B107: ● | D107: Sales quantity | E107: HAN_KOSU | F107: Number | G107: 13 | H107: 3 | I107: Nothing | J107: =J104+G104 -> 807 | K107: Unpack numeric strings and use them as numbers
A108: =ROW()-9 -> 99 | B108: ● | D108: Amount calculation quantity | E108: GAKU_CLC_SURYO | F108: Number | G108: 13 | H108: 3 | I108: Nothing | J108: =J105+G105 -> 779 | K108: Unpack numeric strings and use them as numbers
A109: =ROW()-9 -> 100 | D109: Packaging | E109: NISUGATA | F109: character | G109: 10 | J109: =J106+G106 -> 613
A110: =ROW()-9 -> 101 | B110: ● | D110: capacity | E110: YORYO | F110: Number | G110: 13 | H110: 3 | I110: Nothing | J110: =J107+G107 -> 820 | K110: Unpack numeric strings and use them as numbers
A111: =ROW()-9 -> 102 | B111: ● | D111: Sales price | E111: HAN_GAKU | F111: Number | G111: 13 | H111: 0 | J111: =J108+G108 -> 792 | K111: Unpack numeric strings and use them as numbers
A112: =ROW()-9 -> 103 | B112: ● | D112: Invoice amount | E112: SEIKYU_GAKU | F112: Number | G112: 13 | H112: 0 | J112: =J109+G109 -> 623 | K112: Unpack numeric strings and use them as numbers
A113: =ROW()-9 -> 104 | B113: ● | D113: Consumption tax amount | E113: SHOHIZEI_GAKU | F113: Number | G113: 13 | H113: 0 | J113: =J110+G110 -> 833 | K113: Unpack numeric strings and use them as numbers
A114: =ROW()-9 -> 105 | B114: ● | D114: Invoice amount including tax | E114: ZEIKOMI_SEIKYU_GAKU | F114: Number | G114: 13 | H114: 0 | J114: =J111+G111 -> 805 | K114: Unpack numeric strings and use them as numbers
A115: =ROW()-9 -> 106 | D115: Unit price/amount classification | E115: TANK_GAKU_KBN | F115: character | G115: 1 | J115: =J112+G112 -> 636
A116: =ROW()-9 -> 107 | D116: Transaction Classification | E116: TORIHIKI_KBN | F116: character | G116: 1 | J116: =J113+G113 -> 846
A117: =ROW()-9 -> 108 | D117: Retroactive classification | E117: SOKYU_KBN | F117: character | G117: 1 | J117: =J114+G114 -> 818
A118: =ROW()-9 -> 109 | D118: Shipping and billing category | E118: SHUKKA_SEIKYU_KBN | F118: character | G118: 1 | J118: =J115+G115 -> 637
A119: =ROW()-9 -> 110 | D119: Taxation category | E119: KAZEI_KBN | F119: character | G119: 2 | J119: =J116+G116 -> 847
A120: =ROW()-9 -> 111 | D120: Backorder Classification | E120: BACK_ORDER_KBN | F120: character | G120: 1 | J120: =J117+G117 -> 819
A121: =ROW()-9 -> 112 | D121: Recording date | E121: KEIJO_YM | F121: character | G121: 4 | J121: =J118+G118 -> 638
A122: =ROW()-9 -> 113 | D122: Shipping date (planned) | E122: SHUKKA_YMD_YOTEI | F122: character | G122: 6 | J122: =J119+G119 -> 849
A123: =ROW()-9 -> 114 | D123: Shipping Report Number | E123: SHUKKA_HOKOKU_NO | F123: character | G123: 25 | J123: =J120+G120 -> 820
A124: =ROW()-9 -> 115 | D124: Shipping Invoice Number | E124: SHUKKA_SEIKYU_NO | F124: character | G124: 10 | J124: =J121+G121 -> 642
A125: =ROW()-9 -> 116 | D125: Shipping location | E125: SHUKKA_BASHO | F125: character | G125: 5 | J125: =J122+G122 -> 855
A126: =ROW()-9 -> 117 | D126: Shipping Instruction Comments (Kana) | E126: SHUKKA_SASHIZU_COMMENT_KANA | F126: character | G126: 44 | J126: =J123+G123 -> 845
... A140: =ROW()-9 -> 131 | D140: Column 1 | E140: COLUMN_1 | F140: character | G140: 2100 | J140: =J137+G137 -> 956

Sheet  7. Item transfer (payment details data transmission file)
A6: ■ | B6: Payment details data transmission file mapping specifications | D6: [ ]: 6. Data layout by destination | E6: △: Half-width space, □: Full-width space
A7: Payment details data sending file mapping | D7: Setting value
A8: No. | B8: Item name (Japanese name) | C8: Item name (English name) | D8: Simple transfer | E8: Editing content
A9: =ROW()-8 -> 1 | B9: Reserve | C9: RESERVE | E9: "△"
A10: =ROW()-8 -> 2 | B10: BPID | C10: BPID | E10: "JPCA0102"
A11: =ROW()-8 -> 3 | B11: Sending Type | C11: SND_RCV | E11: "S"
A12: =ROW()-8 -> 4 | B12: Information classification | C12: INF_KBN | E12: "1810"
A13: =ROW()-8 -> 5 | B13: Company code | C13: JISHA_CD | E13: "101913000110"
A14: =ROW()-8 -> 6 | B14: Recipient Code | C14: AITE_SAKI_CD | E14: "504832000001"
A15: =ROW()-8 -> 7 | B15: Data Type | C15: DATA_SBT | E15: "1810"
A16: =ROW()-8 -> 8 | B16: Processing classification | C16: FUNC_KBN | D16: [Processing category]
A17: =ROW()-8 -> 9 | B17: Processing date | C17: FUNC_YMD | E17: yymmdd (system date)
A18: =ROW()-8 -> 10 | B18: Processing time | C18: FUNC_TM | E18: HHMMSS (system time)
A19: =ROW()-8 -> 11 | B19: Red and Black Division | C19: AKAKURO_KBN | D19: [Red and black division]
A20: =ROW()-8 -> 12 | B20: Ordering company code | C20: HACSHA_KIGYO_CD | D20: [Orderer company code]
A21: =ROW()-8 -> 13 | B21: Ordering department code | C21: HACSHA_BMN_CD | D21: [Orderer department code]
A22: =ROW()-8 -> 14 | B22: New purchaser company code | C22: NEW_HACSHA_KIGYO_CD | E22: △*6
A23: =ROW()-8 -> 15 | B23: New purchaser department code | C23: NEW_HACSHA_BMN_CD | E23: △*6
A24: =ROW()-8 -> 16 | B24: Contractor company code | C24: JUC_KIGYO_CD | D24: [Contractor company code]
A25: =ROW()-8 -> 17 | B25: Order recipient department code | C25: JUC_BMN_CD | D25: [Orderer department code]
A26: =ROW()-8 -> 18 | B26: Claimant company code | C26: SEIKYU_KIGYO_CD | D26: [Claimer company code]
A27: =ROW()-8 -> 19 | B27: Claimant department code | C27: SEIKYU_BMN_CD | D27: [Claimer department code]
A28: =ROW()-8 -> 20 | B28: Payer company code | C28: PAY_KIGYO_CD | D28: [Payer company code]
A29: =ROW()-8 -> 21 | B29: Payer Department Code | C29: PAY_BMN_CD | D29: [Payer department code]
A30: =ROW()-8 -> 22 | B30: Contract number | C30: KEIYAKU_NO | D30: [Contract number]
A31: =ROW()-8 -> 23 | B31: Implementation date | C31: JISSHI_YMD | D31: [Date]
A32: =ROW()-8 -> 24 | B32: Order number | C32: CHUMON_NO | D32: [Order number]
A33: =ROW()-8 -> 25 | B33: Orderer and order date | C33: HACSHA_CHUMON_D | D33: [Order date by purchaser]
A34: =ROW()-8 -> 26 | B34: Orderer and order time | C34: HACSHA_CHUMON_TM | E34: "0000"
A35: =ROW()-8 -> 27 | B35: Order Class | C35: ORDER_KBN | E35: "△"
A36: =ROW()-8 -> 28 | B36: Contact necessity classification | C36: RENRAKU_YN_KBN | E36: "△"
A37: =ROW()-8 -> 29 | B37: Quantity specification category | C37: SURYO_SHITEI_KBN | E37: "△"
A38: =ROW()-8 -> 30 | B38: Order comment (kana) | C38: HAC_COMMENT_KANA | E38: △*44
A39: =ROW()-8 -> 31 | B39: Order comment (Kanji) | C39: HAC_COMMENT_KANJI | E39: □*22
A40: =ROW()-8 -> 32 | B40: Order number | C40: JUC_NO | D40: [Order number]
A41: =ROW()-8 -> 33 | B41: Order acceptance date | C41: JUC_CHUMON_UKETSUKE_DT | E41: "000000"
A42: =ROW()-8 -> 34 | B42: Order acceptance time | C42: JUC_CHUMON_UKETSUKE_TM | E42: "0000"
A43: =ROW()-8 -> 35 | B43: Order confirmation date | C43: JUC_CHUMON_CONFIRM_D | E43: "000000"
A44: =ROW()-8 -> 36 | B44: Installment payment categories | C44: BUNNO_KBN | D44: [Installment payment category]
A45: =ROW()-8 -> 37 | B45: Order processing category | C45: JUC_FUNC_KBN | E45: "△"
A46: =ROW()-8 -> 38 | B46: Product Name Group | C46: HINMEI_GROUP | E46: △*5
A47: =ROW()-8 -> 39 | B47: Product name (kana) | C47: HINMEI_KANA | D47: [Product name (kana)]
A48: =ROW()-8 -> 40 | B48: Product name (kanji) | C48: HINMEI_KANJI | E48: □*35
A49: =ROW()-8 -> 41 | B49: Lot number designation category | C49: LOT_NO_SHITEI_KBN | D49: [Lot No. Designation Category]
A50: =ROW()-8 -> 42 | B50: Lot number | C50: LOT_NO | D50: [Lot No.]
A51: =ROW()-8 -> 43 | B51: Customer company code | C51: JUYOKA_KIGYO_CD | D51: [Customer company code]
A52: =ROW()-8 -> 44 | B52: Customer sector code | C52: JUYOKA_BMN_CD | D52: [Customer sector code]
A53: =ROW()-8 -> 45 | B53: Customer name (kana) | C53: JUYOKA_NM_KANA | E53: △*40
A54: =ROW()-8 -> 46 | B54: Consumer name (kanji) | C54: JUYOKA_NM_KANJI | D54: [Customer name (Kanji)]
A55: =ROW()-8 -> 47 | B55: Customer order number | C55: JUYOKA_CHUMON_NO | D55: [Customer order number]
A56: =ROW()-8 -> 48 | B56: Secondary store company code | C56: NIJITEN_KIGYO_CD | D56: [Secondary store company code]
A57: =ROW()-8 -> 49 | B57: Secondary store department code | C57: NIJITEN_BMN_CD | D57: [Secondary store department code]
A58: =ROW()-8 -> 50 | B58: Secondary store name (kana) | C58: NIJITEN_NM_KANA | E58: △*40
A59: =ROW()-8 -> 51 | B59: Secondary store name (kanji) | C59: NIJITEN_NM_KANJI | D59: [Secondary store name (Kanji)]
A60: =ROW()-8 -> 52 | B60: Third-tier store company code | C60: SANJITEN_KIGYO_CD | E60: △*6
A61: =ROW()-8 -> 53 | B61: Third-tier store department code | C61: SANJITEN_BMN_CD | E61: △*6
A62: =ROW()-8 -> 54 | B62: Third store name (kana) | C62: SANJITEN_NM_KANA | E62: △*40
A63: =ROW()-8 -> 55 | B63: Tertiary store name (kanji) | C63: SANJITEN_NM_KANJI | E63: □*20
A64: =ROW()-8 -> 56 | B64: Payment terms deadline | C64: KESSAI_JOKEN_SHIMEKIRI_D | D64: [Payment terms deadline]
A65: =ROW()-8 -> 57 | B65: Payment terms start date | C65: KESSAI_JOKEN_KISAN_D | D65: [Payment terms start date]
A66: =ROW()-8 -> 58 | B66: Payment terms and means | C66: KESSAI_JOKEN_SHUDAN | D66: [Payment terms and methods]
A67: =ROW()-8 -> 59 | B67: Payment terms maturity date | C67: KESSAI_JOKEN_MANKI_D | D67: [Payment terms maturity date]
A68: =ROW()-8 -> 60 | B68: Payment terms criteria | C68: KESSAI_JOKEN_KIJUN | D68: [Payment conditions criteria]
A69: =ROW()-8 -> 61 | B69: Payment Terms | C69: KESSAI_JOKEN | D69: [Payment terms]
A70: =ROW()-8 -> 62 | B70: Quantity confirmation indicator | C70: SURYO_CONFIRM_KBN | D70: [Quantity confirmation category]
A71: =ROW()-8 -> 63 | B71: Sales price | C71: HAN_TANK | D71: [Sales price]
A72: =ROW()-8 -> 64 | B72: Unit price | C72: TANK_UNIT | D72: [Unit price]
A73: =ROW()-8 -> 65 | B73: Unit price category | C73: TANK_KBN | D73: [Unit price category]
A74: =ROW()-8 -> 66 | B74: Payment classification | C74: KOSEN_KBN | E74: "△"
A75: =ROW()-8 -> 67 | B75: Commission unit price | C75: KOSEN_TANK | E75: 0
A76: =ROW()-8 -> 68 | B76: commission | C76: KOSEN | E76: 0
A77: =ROW()-8 -> 69 | B77: Secondary store payment classification | C77: NIJITEN_KOSEN_KBN | E77: "△"
A78: =ROW()-8 -> 70 | B78: Secondary store commission unit price | C78: NIJITEN_KOSEN_TANK | E78: 0
A79: =ROW()-8 -> 71 | B79: Secondary store commission | C79: NIJITEN_KOSEN | E79: 0
A80: =ROW()-8 -> 72 | B80: Delivery company code | C80: NNY_KIGYO_CD | D80: [Delivery company code]
A81: =ROW()-8 -> 73 | B81: Delivery department code | C81: NNY_BMN_CD | D81: [Delivery department code]
A82: =ROW()-8 -> 74 | B82: Delivery destination name (kana) | C82: NNY_NM_KANA | E82: △*40
A83: =ROW()-8 -> 75 | B83: Delivery destination name (kanji) | C83: NNY_NM_KANJI | D83: [Delivery destination name (Kanji)]
A84: =ROW()-8 -> 76 | B84: Delivery Terms | C84: UKEWATASHI_JOKEN | E84: △*2
A85: =ROW()-8 -> 77 | B85: Delivery address (kana) | C85: UKEWATASHI_BASHO_ADDRK | E85: △*74
A86: =ROW()-8 -> 78 | B86: Delivery address (kanji) | C86: UKEWATASHI_BASHO_ADDR | D86: [Delivery address (Kanji)]
A87: =ROW()-8 -> 79 | B87: District Code | C87: CHIKU_CD | E87: △*11
A88: =ROW()-8 -> 80 | B88: post code | C88: ZIP | D88: [post code]
A89: =ROW()-8 -> 81 | B89: telephone number | C89: TEL | D89: [telephone number]
A90: =ROW()-8 -> 82 | B90: Fax Phone Number | C90: FAX_TEL | D90: [Fax number]
A91: =ROW()-8 -> 83 | B91: Desired delivery date | C91: KIBO_NONYU_YMD | E91: "000000"
A92: =ROW()-8 -> 84 | B92: Desired delivery time | C92: KIBO_NONYU_TM | E92: "0000"
A93: =ROW()-8 -> 85 | B93: Desired delivery comment | C93: KIBO_NONYU_COMMENT | E93: △*10
A94: =ROW()-8 -> 86 | B94: Delivery date (planned) | C94: NONYU_YMD_YOTEI | D94: [Delivery date]
A95: =ROW()-8 -> 87 | B95: Delivery requirements (kana) | C95: NONYU_YOKEN_KANA | E95: △*44
A96: =ROW()-8 -> 88 | B96: Delivery requirements (Kanji) | C96: NONYU_YOKEN_KANJI | E96: □*22
A97: =ROW()-8 -> 89 | B97: Payment amount | C97: PAY_GAKU | D97: Linked file.EDI_Current payment amount
A98: =ROW()-8 -> 90 | B98: Payment reference number | C98: PAY_SEIRI_NO | E98: △*12
A99: =ROW()-8 -> 91 | B99: Bill number (check number) | C99: TEGATA_NO_KOGITTE | E99: △*12
A100: =ROW()-8 -> 92 | B100: Issuing bank (code) | C100: ISSUE_BANK_CD | E100: △*7
A101: =ROW()-8 -> 93 | B101: Issuing bank (name) | C101: ISSUE_BANK_NM | E101: △*30
A102: =ROW()-8 -> 94 | B102: Transfer bank (code) | C102: FURIKOMI_BANK_CD | E102: Linked file.Bank code + Linked file.Branch code If the combined value is less than 7 bytes, add a △ at the end
A103: =ROW()-8 -> 95 | B103: Transfer bank (name) | C103: FURIKOMI_BANK_NM | E103: Linked file.Bank name (kana) Right trim + △ + Linked file.Branch name (kana) Right trim If the combined file is less than 30 bytes, add △ to the end
A104: =ROW()-8 -> 96 | B104: Account number | C104: KOZA_NO | D104: Linked file.Transfer account number
A105: =ROW()-8 -> 97 | B105: Payment Requirements | C105: PAY_YOKEN | E105: △*10
...

Sheet  8. [Reference] Basic design
A1: Inabata & Co., Ltd. | G1: Basic design | R1: System Name | AW1: Subsystem name | BD1: Feature ID
R3: Techno UMG (payment details data) | AW3: EDI | BD3: -
B7: 1. | C7: Business flow explanation
C8: ① Send the payment details data created based on the "shipping invoice data" that is the subject of EDI payment.
B10: 2. | C10: specification
C11: ① Extraction of data to be sent
D12: ・DB (EDI Send DB_Payment) extraction conditions
D13: Data Exchange ID="000086"
D14: and EDI_Function Category Code="A140"
D15: And EDI_SendStatusType="0" (Unprocessed)
D17: ・DB (EDI receiving DB_Supplier) extraction conditions
D18: Data Exchange ID="000086"
D19: and EDI_Function Category Code="A100"
D21: ・DB (EDI sending DB_Payment) and DB (EDI receiving DB_Supplier) are linked by the receiving sequence number.
C23: ②If there is no target data
D24: - After outputting the message "0 items", the process will terminate abnormally.
D25: Unless a transaction is suspended, the number of payments will never be zero, so it is an irregular situation for the number of items to be sent to be zero.
D26: To detect that there are 0 targets, the process will be terminated abnormally, and once it has been confirmed that there are no operational issues, the job net will be recovered (perform the "Confirm" operation).
B28: 3. | C28: Sending item design
C30: ・Created based on the data in "EDI Send DB_Payment"
C31: For payment details data file layout and editing specifications, refer to the "Transmission Item Table (Payment Details)" sheet.

Sheet  9. [Reference] Sending Item List (Payment Details)
H6: [ ]: EDI receiving DB_Supplier " ": EDI sending DB_Payment
H7: △: Half-width space, □: Full-width space *n (n: number of repetitions)
B8: No. | C8: Item name | D8: Item character type | E8: Number of digits (bytes) | F8: Decimal places | G8: Required Optional Not used | H8: edit | I8: remarks
B9: 1 | C9: Reserve | D9: character | E9: 1 | G9: - | H9: △*1 | I9: In the NTS conversion process, this item is deleted.
B10: =B9+1 -> 2 | C10: BPID | D10: character | E10: 8 | G10: - | H10: "JPCA0102" | I10: In the NTS conversion process, this item is deleted.
B11: =B10+1 -> 3 | C11: Sending and receiving | D11: character | E11: 1 | G11: - | H11: "S" | I11: In the NTS conversion process, this item is deleted.
B12: =B11+1 -> 4 | C12: Information classification | D12: character | E12: 4 | G12: - | H12: "1810" [Payment details] | I12: In the NTS conversion process, this item is deleted.
B13: =B12+1 -> 5 | C13: Company code | D13: character | E13: 12 | G13: - | H13: "101913000110" | I13: In the NTS conversion process, this item is deleted.
B14: =B13+1 -> 6 | C14: Recipient Code | D14: character | E14: 12 | G14: - | H14: "504832000001" | I14: In the NTS conversion process, this item is deleted.
B15: =B14+1 -> 7 | C15: Data Type | D15: character | E15: 4 | G15: Required | H15: "1810" [Payment details] | L15: mixed string
B16: =B15+1 -> 8 | C16: Processing classification | D16: character | E16: 1 | G16: Required | H16: byte from 43rd byte of [Destination Data] | I16: Shipping billing turnaround | L16: mixed string
B17: =B16+1 -> 9 | C17: Processing date | D17: character | E17: 6 | G17: Required | H17: Job execution date: "YYMMDD" | L17: mixed string
B18: =B17+1 -> 10 | C18: Processing time | D18: character | E18: 6 | G18: Required | H18: Job execution time: "HHMMSS" | L18: mixed string
B19: =B18+1 -> 11 | C19: Red and Black Division | D19: character | E19: 1 | G19: Required | H19: 1 byte from the 56th byte of [Destination Data] | I19: Shipping billing turnaround | L19: mixed string
B20: =B19+1 -> 12 | C20: Ordering company code | D20: character | E20: 6 | G20: Required | H20: 6 bytes from byte 57 of [Destination Data] | I20: Shipping billing turnaround | L20: mixed string
B21: =B20+1 -> 13 | C21: Ordering department code | D21: character | E21: 6 | G21: Required | H21: 6 bytes from the 63rd byte of [Destination Data] | I21: Shipping billing turnaround | L21: mixed string
B22: =B21+1 -> 14 | C22: New purchaser company code | D22: character | E22: 6 | G22: - | H22: △*6 | I22: In the NTS conversion process, this item is deleted.
B23: =B22+1 -> 15 | C23: New purchaser department code | D23: character | E23: 6 | G23: - | H23: △*6 | I23: In the NTS conversion process, this item is deleted.
B24: =B23+1 -> 16 | C24: Contractor company code | D24: character | E24: 6 | G24: Required | H24: 6 bytes from byte 81 of [Destination Data] | I24: Shipping billing turnaround | L24: mixed string
B25: =B24+1 -> 17 | C25: Order recipient department code | D25: character | E25: 6 | G25: Required | H25: 6 bytes from byte 87 of [Destination Data] | I25: Shipping billing turnaround | L25: mixed string
B26: =B25+1 -> 18 | C26: Claimant company code | D26: character | E26: 6 | G26: Required | H26: bytes from byte 93 of [Destination Data] | I26: Shipping billing turnaround | L26: mixed string
B27: =B26+1 -> 19 | C27: Claimant department code | D27: character | E27: 6 | G27: Required | H27: 6 bytes from the 99th byte of [Destination Data] | I27: Shipping billing turnaround | L27: mixed string
B28: =B27+1 -> 20 | C28: Payer company code | D28: character | E28: 6 | G28: Required | H28: 6 bytes from byte 105 of [Destination Data] | I28: Shipping billing turnaround | L28: mixed string
B29: =B28+1 -> 21 | C29: Payer Department Code | D29: character | E29: 6 | G29: Required | H29: 6 bytes from byte 111 of [Destination Data] | I29: Shipping billing turnaround | L29: mixed string
B30: =B29+1 -> 22 | C30: Contract number | D30: character | E30: 10 | G30: Required | H30: 10 bytes from byte 117 of [Destination Data] | I30: Shipping billing turnaround | L30: mixed string
B31: =B30+1 -> 23 | C31: Implementation date | D31: character | E31: 6 | G31: Unused | H31: "000000" | L31: mixed string
B32: =B31+1 -> 24 | C32: Order number | D32: character | E32: 10 | G32: Required | H32: 10 bytes from byte 133 of [Destination Data] | I32: Shipping billing turnaround | L32: mixed string
B33: =B32+1 -> 25 | C33: Orderer and order date | D33: character | E33: 6 | G33: Required | H33: 6 bytes from byte 143 of [Destination Data] | I33: Shipping billing turnaround | L33: mixed string
B34: =B33+1 -> 26 | C34: Orderer and order time | D34: character | E34: 4 | G34: Unused | H34: "0000" | L34: mixed string
B35: =B34+1 -> 27 | C35: Order Class | D35: character | E35: 1 | G35: Unused | H35: △*1 | L35: mixed string
B36: =B35+1 -> 28 | C36: Contact necessity classification | D36: character | E36: 1 | G36: Unused | H36: △*1 | L36: mixed string
B37: =B36+1 -> 29 | C37: Quantity specification category | D37: character | E37: 1 | G37: Unused | H37: △*1 | L37: mixed string
B38: =B37+1 -> 30 | C38: Order comment (kana) | D38: character | E38: 44 | G38: Unused | H38: △*44 | L38: mixed string
B39: =B38+1 -> 31 | C39: Order comment (Kanji) | D39: character | E39: 44 | G39: Unused | H39: □*22 | L39: Kanji
B40: =B39+1 -> 32 | C40: Order number | D40: character | E40: 10 | G40: Required | H40: 10 bytes from byte 244 of [Destination Data] | I40: Shipping billing turnaround | L40: mixed string
B41: =B40+1 -> 33 | C41: Order acceptance date | D41: character | E41: 6 | G41: Unused | H41: "000000" | L41: mixed string
B42: =B41+1 -> 34 | C42: Order acceptance time | D42: character | E42: 4 | G42: Unused | H42: "0000" | L42: mixed string
B43: =B42+1 -> 35 | C43: Order confirmation date | D43: character | E43: 6 | G43: Unused | H43: "000000" | L43: mixed string
B44: =B43+1 -> 36 | C44: Installment payment categories | D44: character | E44: 1 | G44: Required | H44: 1 byte from byte 270 of [Destination Data] | I44: Shipping billing turnaround | L44: mixed string
B45: =B44+1 -> 37 | C45: Order processing category | D45: character | E45: 1 | G45: Unused | H45: △*1 | L45: mixed string
B46: =B45+1 -> 38 | C46: Product Name Group | D46: character | E46: 5 | G46: Unused | H46: △*5 | L46: mixed string
B47: =B46+1 -> 39 | C47: Product name (kana) | D47: character | E47: 70 | G47: Required | H47: 70 bytes from byte 277 of [Destination Data] | I47: Shipping billing turnaround | L47: mixed string
B48: =B47+1 -> 40 | C48: Product name (kanji) | D48: character | E48: 70 | G48: Unused | H48: □*35 | L48: Kanji
B49: =B48+1 -> 41 | C49: Lot number designation category | D49: character | E49: 1 | G49: Unused | H49: △*1 | L49: mixed string
B50: =B49+1 -> 42 | C50: Lot number | D50: character | E50: 10 | G50: Required | H50: 10 bytes from byte 418 of [Destination Data] | I50: Shipping billing turnaround | L50: mixed string
B51: =B50+1 -> 43 | C51: Customer company code | D51: character | E51: 6 | G51: Required | H51: 6 bytes from byte 428 of [Destination Data] | I51: Shipping billing turnaround | L51: mixed string
B52: =B51+1 -> 44 | C52: Customer sector code | D52: character | E52: 6 | G52: any | H52: 6 bytes from byte 434 of [Destination Data] | I52: Shipping billing turnaround | L52: mixed string | M52: Unused items in shipping invoice
B53: =B52+1 -> 45 | C53: Customer name (kana) | D53: character | E53: 40 | G53: Unused | H53: △*40 | L53: mixed string
B54: =B53+1 -> 46 | C54: Consumer name (kanji) | D54: character | E54: 40 | G54: Required | H54: 40 bytes from byte 480 of [Destination Data] | I54: Shipping billing turnaround | L54: Kanji
B55: =B54+1 -> 47 | C55: Customer order number | D55: character | E55: 10 | G55: any | H55: 10 bytes from byte 520 of [Destination Data] | I55: Shipping billing turnaround | L55: mixed string | M55: Unused items in shipping invoice
B56: =B55+1 -> 48 | C56: Secondary store company code | D56: character | E56: 6 | G56: any | H56: 6 bytes from byte 530 of [Destination Data] | I56: Shipping billing turnaround | L56: mixed string
B57: =B56+1 -> 49 | C57: Secondary store department code | D57: character | E57: 6 | G57: any | H57: 6 bytes from byte 536 of [Destination Data] | I57: Shipping billing turnaround | L57: mixed string | M57: Unused items in shipping invoice
B58: =B57+1 -> 50 | C58: Secondary store name (kana) | D58: character | E58: 40 | G58: Unused | H58: △*40 | L58: mixed string
B59: =B58+1 -> 51 | C59: Secondary store name (kanji) | D59: character | E59: 40 | G59: any | H59: 40 bytes from byte 582 of [Destination Data] | I59: Shipping billing turnaround | L59: Kanji
B60: =B59+1 -> 52 | C60: Third-tier store company code | D60: character | E60: 6 | G60: Unused | H60: △*6 | L60: mixed string
B61: =B60+1 -> 53 | C61: Third-tier store department code | D61: character | E61: 6 | G61: Unused | H61: △*6 | L61: mixed string
B62: =B61+1 -> 54 | C62: Third store name (kana) | D62: character | E62: 40 | G62: Unused | H62: △*40 | L62: mixed string
B63: =B62+1 -> 55 | C63: Tertiary store name (kanji) | D63: character | E63: 40 | G63: Unused | H63: □*20 | L63: Kanji
B64: =B63+1 -> 56 | C64: Payment terms deadline | D64: character | E64: 6 | G64: Required | H64: 6 bytes from byte 714 of [Destination Data] | I64: Shipping billing turnaround | L64: mixed string
B65: =B64+1 -> 57 | C65: Payment terms start date | D65: character | E65: 6 | G65: Required | H65: 6 bytes from byte 720 of [Destination Data] | I65: Shipping billing turnaround | L65: mixed string
B66: =B65+1 -> 58 | C66: Payment terms and means | D66: character | E66: 1 | G66: Required | H66: 1 byte from 726th byte of [Destination Data] | I66: Shipping billing turnaround | L66: mixed string
B67: =B66+1 -> 59 | C67: Payment terms maturity date | D67: character | E67: 6 | G67: Required | H67: 6 bytes from byte 727 of [Destination Data] | I67: Shipping billing turnaround | L67: mixed string
B68: =B67+1 -> 60 | C68: Payment terms criteria | D68: character | E68: 1 | G68: Required | H68: 1 byte from 733rd byte of [Destination Data] | I68: Shipping billing turnaround | L68: mixed string
B69: =B68+1 -> 61 | C69: Payment Terms | D69: character | E69: 15 | G69: Required | H69: 15 bytes from 734th byte of [Destination Data] | I69: Shipping billing turnaround | L69: mixed string
B70: =B69+1 -> 62 | C70: Quantity confirmation indicator | D70: character | E70: 1 | G70: Required | H70: 1 byte from 749th byte of [Destination Data] | I70: Shipping billing turnaround | L70: mixed string
B71: =B70+1 -> 63 | C71: Sales price | D71: Unpacking Numbers | E71: 13 | F71: 3 | G71: Required | H71: 13 bytes from byte 750 of [Destination Data] | I71: Shipping billing turnaround | L71: real number
B72: =B71+1 -> 64 | C72: Unit price | D72: character | E72: 3 | G72: Required | H72: 3 bytes from byte 763 of [Destination Data] | I72: Shipping billing turnaround | L72: mixed string
B73: =B72+1 -> 65 | C73: Unit price category | D73: character | E73: 1 | G73: Required | H73: 1 byte from 766th byte of [Destination Data] | I73: Shipping billing turnaround | L73: mixed string
B74: =B73+1 -> 66 | C74: Payment classification | D74: character | E74: 1 | G74: Unused | H74: △*1 | L74: mixed string
B75: =B74+1 -> 67 | C75: Commission unit price | D75: Unpacking Numbers | E75: 13 | F75: 3 | G75: Unused | H75: 0000000000000 | L75: real number
B76: =B75+1 -> 68 | C76: commission | D76: Unpacking Numbers | E76: 13 | F76: 0 | G76: Unused | H76: 0000000000000 | L76: real number
B77: =B76+1 -> 69 | C77: Secondary store payment classification | D77: character | E77: 1 | G77: Unused | H77: △*1 | L77: mixed string
B78: =B77+1 -> 70 | C78: Secondary store commission unit price | D78: Unpacking Numbers | E78: 13 | F78: 3 | G78: Unused | H78: 0000000000000 | L78: real number
B79: =B78+1 -> 71 | C79: Secondary store commission | D79: Unpacking Numbers | E79: 13 | F79: 0 | G79: Unused | H79: 0000000000000 | L79: real number
B80: =B79+1 -> 72 | C80: Delivery company code | D80: character | E80: 6 | G80: any | H80: 6 bytes from 821st byte of [Destination Data] | I80: Shipping billing turnaround | L80: mixed string
B81: =B80+1 -> 73 | C81: Delivery department code | D81: character | E81: 6 | G81: any | H81: bytes from 827th byte of [Destination Data] | I81: Shipping billing turnaround | L81: mixed string | M81: Unused items in shipping invoice
B82: =B81+1 -> 74 | C82: Delivery destination name (kana) | D82: character | E82: 40 | G82: Unused | H82: △*40 | L82: mixed string
B83: =B82+1 -> 75 | C83: Delivery destination name (kanji) | D83: character | E83: 40 | G83: any | H83: 40 bytes from 873rd byte of [Destination Data] | I83: Shipping billing turnaround | L83: Kanji
B84: =B83+1 -> 76 | C84: Delivery Terms | D84: character | E84: 2 | G84: Unused | H84: △*2 | L84: mixed string
B85: =B84+1 -> 77 | C85: Delivery address (kana) | D85: character | E85: 74 | G85: Unused | H85: △*74 | L85: mixed string
B86: =B85+1 -> 78 | C86: Delivery address (kanji) | D86: character | E86: 74 | G86: any | H86: 74 bytes from 989th byte of [Destination Data] | I86: Shipping billing turnaround | L86: Kanji
B87: =B86+1 -> 79 | C87: District Code | D87: character | E87: 11 | G87: Unused | H87: △*11 | L87: mixed string
B88: =B87+1 -> 80 | C88: post code | D88: character | E88: 7 | G88: any | H88: 7 bytes from 1074th byte of [Destination Data] | I88: Shipping billing turnaround | L88: mixed string
B89: =B88+1 -> 81 | C89: telephone number | D89: character | E89: 12 | G89: any | H89: 12 bytes from byte 1081 of [Destination Data] | I89: Shipping billing turnaround | L89: mixed string
B90: =B89+1 -> 82 | C90: Fax Phone Number | D90: character | E90: 12 | G90: any | H90: 12 bytes from byte 1093 of [Destination Data] | I90: Shipping billing turnaround | L90: mixed string | M90: Unused items in shipping invoice
B91: =B90+1 -> 83 | C91: Desired delivery date | D91: character | E91: 6 | G91: Unused | H91: △*6 | L91: mixed string
B92: =B91+1 -> 84 | C92: Desired delivery time | D92: character | E92: 4 | G92: Unused | H92: △*4 | L92: mixed string
B93: =B92+1 -> 85 | C93: Desired delivery comment | D93: character | E93: 10 | G93: Unused | H93: △*10 | L93: mixed string
B94: =B93+1 -> 86 | C94: Delivery date (planned) | D94: character | E94: 6 | G94: Required | H94: 6 bytes from byte 1125 of [Destination Data] | I94: Shipping billing turnaround | L94: mixed string
B95: =B94+1 -> 87 | C95: Delivery requirements (kana) | D95: character | E95: 44 | G95: Unused | H95: △*44 | L95: mixed string
B96: =B95+1 -> 88 | C96: Delivery requirements (Kanji) | D96: character | E96: 44 | G96: Unused | H96: □*22 | L96: Kanji
B97: =B96+1 -> 89 | C97: Payment amount | D97: Unpacking Numbers | E97: 13 | F97: 0 | G97: any | H97: "EDI_Current payment amount" | L97: real number | M97: EDI_There is a payment amount this time, so set
B98: =B97+1 -> 90 | C98: Payment reference number | D98: character | E98: 12 | G98: any | H98: △*12 | L98: mixed string | M98: Since this is a number that links payment data and payment details data, is it unnecessary if there is only payment details?
B99: =B98+1 -> 91 | C99: Bill number (check number) | D99: character | E99: 12 | G99: any | H99: △*12 | L99: mixed string | M99: No source of setting
B100: =B99+1 -> 92 | C100: Issuing bank (code) | D100: character | E100: 7 | G100: any | H100: △*7 | L100: mixed string | M100: No source of setting
B101: =B100+1 -> 93 | C101: Issuing bank (name) | D101: character | E101: 30 | G101: any | H101: △*30 | L101: mixed string
B102: =B101+1 -> 94 | C102: Transfer bank (code) | D102: character | E102: 7 | G102: any | H102: "Bank Code" + "Branch Code" - Fill in the end with △ | L102: mixed string
B103: =B102+1 -> 95 | C103: Transfer bank (name) | D103: character | E103: 30 | G103: any | H103: Right trim of "Bank name (kana)" + △ + "Branch name (kana)" with the last △ padded to the top 30 digits | L103: mixed string
B104: =B103+1 -> 96 | C104: Account number | D104: character | E104: 7 | G104: any | H104: Fill in the "Transfer Account No." with △ at the end | L104: mixed string
B105: =B104+1 -> 97 | C105: Payment Requirements | D105: character | E105: 10 | G105: any | H105: △*10 | L105: mixed string | M105: No source of setting
...
