Workbook

Sheet 発注_送信ファイル
A1: 発注_送信ファイル出力確認
B3: No. | C3: テストNo | D3: 共通フォーマットデータ
C4: 【テスト結果】 | D4: TUGA0501を以下に貼り付ける
B5: =B4+1 -> 1 | C5: NO.32,33,39 | D5: JPCA0102S151010191300011050483200000115101250730120609 0369B 0369B 870089 000000B00344A2011105061029 0000000000000000 XX XX IG98D ■■モ■■穂■■第■■場 0Y349333 000000000000 000000 0.000 0.000 0 0.000 0VM77A ■■ノ■■㈱■■橋■■ ■■県■■市■■相■■９■ 11111 1131121161 1105160000 000000 0 0000000 25.000 1.000KG 0.000 0.00011 25.000 0 0 0 0 1 0000000000 1
B6: =B5+1 -> 2 | D6: JPCA0102S151010191300011050483200000115101250730120609 0369B 0369B 815791 000000B0034455011105060937 午前着希望 0000000000000000 XXNXX XX-XX CI94A ■■化■■業■ 8359C ■■井■■ 000000000000 000000 0.000 0.000 0 0.000 09773A ■■化■■ ■■井■■ ■■県■■井■■幸■■－■■２■ 11611 1161111121 1105110000 000000 0 0000000 300.000 12.000KG 0.000 0.00011 25.000 0 0 0 0 1 0000000000 1
B7: =B6+1 -> 3 | D7: JPCA0102S151010191300011050483200000115101250730120609 0369B 0369B 815791 000000B0034459011105060939 午前着希望 0000000000000000 XXNXX XX-XX CI94A ■■化■■業■ 8359C ■■井■■ 000000000000 000000 0.000 0.000 0 0.000 0AUJ1A ■■化■■業■ ■■県■■市■■２■■－■ 11411 1161141131 1105110000 000000 0 0000000 300.000 12.000KG 0.000 0.00011 25.000 0 0 0 0 1 0000000000 1
B8: =B7+1 -> 4 | D8: JPCA0102S151010191300011050483200000115101250730120609 0369A 0369A 905100 000000B00344AE011105061037 0000000000000000 XXSXX5XX0XX1 8878A ■■ザ■■工 2258338 2627C ■■商■■大■■店 000000000000 000000 0.000 0.000 0 0.000 08878A ■■ザ■■工 ■■県■■部■■輪■■８■■ 11211 1161111121 1105230000 000000 0 0000000 800.000 32.000KG 0.000 0.00011 25.000 0 0 0 0 1 0000000000 1
B9: =B8+1 -> 5 | D9: JPCA0102S151010191300011050483200000115101250730120609 0369C 0369C 606430 000000B00344D4011105061057 0000000000000000 XXSXX3X DY86A ■■化■■業■ IS0501 000000000000 000000 0.000 0.000 0 0.000 0LJ32A ■■化■■ ■■県■■山■■石■■今■■１■■ 11911 1131131151 1105120000 000000 0 0000000 600.000 24.000KG 0.000 0.00011 25.000 0 0 0 0 1 0000000000 1
B10: =B9+1 -> 6 | D10: JPCA0102S151010191300011050483200000115101250730120609 0369B 0369B 837647 000000B003445C011105060940 0000000000000000 XXXXX5XX XX CI94A ■■化■■業■ 8359C ■■井■■ 000000000000 000000 0.000 0.000 0 0.000 0AUJ1A ■■化■■業■ ■■県■■市■■２■■－■ 11411 1161141131 1105130000 000000 0 0000000 450.000 18.000KG 0.000 0.00011 25.000 0 0 0 0 1 0000000000 1
B11: =B10+1 -> 7
B12: =B11+1 -> 8
B13: =B12+1 -> 9
B14: =B13+1 -> 10
B15: =B14+1 -> 11
B16: =B15+1 -> 12
B17: =B16+1 -> 13
B18: =B17+1 -> 14
B19: =B18+1 -> 15
B20: =B19+1 -> 16
B21: =B20+1 -> 17
B22: =B21+1 -> 18
... B46: =B45+1 -> 42

Sheet 発注_送信ファイル_項目分割
A1: 項目分割
C3: 開始位置 | D3: 1 | E3: 2 | F3: 10 | G3: 11 | H3: 15 | I3: 27 | J3: 39 | K3: 43 | L3: 44 | M3: 50 | N3: 56 | O3: 57 | P3: 63 | Q3: 69 | R3: 75 | S3: 81 | T3: 87 | U3: 93 | V3: 99 | W3: 105 | X3: 111 | Y3: 117 | Z3: 127 | AA3: 133 | AB3: 143 | AC3: 149 | AD3: 153 | AE3: 154 | AF3: 155 | AG3: 156 | AH3: 200 | AI3: 244 | AJ3: 254 | AK3: 260 | AL3: 264 | AM3: 270 | AN3: 271 | AO3: 272 | AP3: 277 | AQ3: 347 | AR3: 417 | AS3: 418 | AT3: 428 | AU3: 434 | AV3: 440 | AW3: 480 | AX3: 520 | AY3: 530 | AZ3: 536 | BA3: 542 | BB3: 582 | BC3: 622 | BD3: 628 | BE3: 634 | BF3: 674 | BG3: 714 | BH3: 720 | BI3: 726 | BJ3: 727 | BK3: 733 | BL3: 734 | BM3: 749 | BN3: 750 | BO3: 763 | BP3: 766 | BQ3: 767 | BR3: 768 | BS3: 781 | BT3: 794 | BU3: 795 | BV3: 808 | BW3: 821 | BX3: 827 | BY3: 833 | BZ3: 873 | CA3: 913 | CB3: 915 | CC3: 989 | CD3: 1063 | CE3: 1074 | CF3: 1081 | CG3: 1093 | CH3: 1105 | CI3: 1111 | CJ3: 1115 | CK3: 1125 | CL3: 1131 | CM3: 1175 | CN3: 1219 | CO3: 1232 | CP3: 1244 | CQ3: 1256 | CR3: 1263 | CS3: 1293 | CT3: 1300 | CU3: 1330 | CV3: 1337 | CW3: 1347 | CX3: 1360 | CY3: 1373 | CZ3: 1376 | DA3: 1389 | DB3: 1402 | DC3: 1412 | DD3: 1425 | DE3: 1438 | DF3: 1451 | DG3: 1464 | DH3: 1477 | DI3: 1478 | DJ3: 1479 | DK3: 1480 | DL3: 1481 | DM3: 1483 | DN3: 1484 | DO3: 1488 | DP3: 1494 | DQ3: 1519 | DR3: 1529 | DS3: 1534 | DT3: 1578 | DU3: 1622 | DV3: 1624 | DW3: 1634 | DX3: 1654 | DY3: 1674 | DZ3: 1675 | EA3: 1685 | EB3: 1729 | EC3: 1773 | ED3: 1774 | EE3: 1804 | EF3: 1834
C4: 桁数 | D4: 1 | E4: 8 | F4: 1 | G4: 4 | H4: 12 | I4: 12 | J4: 4 | K4: 1 | L4: 6 | M4: 6 | N4: 1 | O4: 6 | P4: 6 | Q4: 6 | R4: 6 | S4: 6 | T4: 6 | U4: 6 | V4: 6 | W4: 6 | X4: 6 | Y4: 10 | Z4: 6 | AA4: 10 | AB4: 6 | AC4: 4 | AD4: 1 | AE4: 1 | AF4: 1 | AG4: 44 | AH4: 44 | AI4: 10 | AJ4: 6 | AK4: 4 | AL4: 6 | AM4: 1 | AN4: 1 | AO4: 5 | AP4: 70 | AQ4: 70 | AR4: 1 | AS4: 10 | AT4: 6 | AU4: 6 | AV4: 40 | AW4: 40 | AX4: 10 | AY4: 6 | AZ4: 6 | BA4: 40 | BB4: 40 | BC4: 6 | BD4: 6 | BE4: 40 | BF4: 40 | BG4: 6 | BH4: 6 | BI4: 1 | BJ4: 6 | BK4: 1 | BL4: 15 | BM4: 1 | BN4: 13 | BO4: 3 | BP4: 1 | BQ4: 1 | BR4: 13 | BS4: 13 | BT4: 1 | BU4: 13 | BV4: 13 | BW4: 6 | BX4: 6 | BY4: 40 | BZ4: 40 | CA4: 2 | CB4: 74 | CC4: 74 | CD4: 11 | CE4: 7 | CF4: 12 | CG4: 12 | CH4: 6 | CI4: 4 | CJ4: 10 | CK4: 6 | CL4: 44 | CM4: 44 | CN4: 13 | CO4: 12 | CP4: 12 | CQ4: 7 | CR4: 30 | CS4: 7 | CT4: 30 | CU4: 7 | CV4: 10 | CW4: 13 | CX4: 13 | CY4: 3 | CZ4: 13 | DA4: 13 | DB4: 10 | DC4: 13 | DD4: 13 | DE4: 13 | DF4: 13 | DG4: 13 | DH4: 1 | DI4: 1 | DJ4: 1 | DK4: 1 | DL4: 2 | DM4: 1 | DN4: 4 | DO4: 6 | DP4: 25 | DQ4: 10 | DR4: 5 | DS4: 44 | DT4: 44 | DU4: 2 | DV4: 10 | DW4: 20 | DX4: 20 | DY4: 1 | DZ4: 10 | EA4: 44 | EB4: 44 | EC4: 1 | ED4: 30 | EE4: 30 | EF4: 67
B5: No. | C5: テストNo | D5: リザーブ | E5: BPID | F5: 送受信 | G5: 情報区分 | H5: 自社コード | I5: 相手先コード | J5: データ種別 | K5: 処理区分 | L5: 処理年月日 | M5: 処理時刻 | N5: 赤黒区分 | O5: 発注者企業コード | P5: 発注者部門コード | Q5: 新発注者企業コード | R5: 新発注者部門コード | S5: 受注者企業コード | T5: 受注者部門コード | U5: 請求者企業コード | V5: 請求者部門コード | W5: 支払者企業コード | X5: 支払者部門コード | Y5: 契約番号 | Z5: 実施年月日 | AA5: 注文番号 | AB5: 発注者・注文日 | AC5: 発注者・注文時刻 | AD5: オーダー区分 | AE5: 連絡要否区分 | AF5: 数量指定区分 | AG5: 発注コメント（カナ） | AH5: 発注コメント（漢字） | AI5: 受注番号 | AJ5: 受注者注文受付日付 | AK5: 受注者注文受付時刻 | AL5: 受注者注文確定日 | AM5: 分納区分 | AN5: 受注者処理区分 | AO5: 品名グループ | AP5: 品名（カナ） | AQ5: 品名（漢字） | AR5: ロット番号指定区分 | AS5: ロット番号 | AT5: 需要家企業コード | AU5: 需要家部門コード | AV5: 需要家名称（カナ） | AW5: 需要家名称（漢字） | AX5: 需要家注文番号 | AY5: ２次店企業コード | AZ5: ２次店部門コード | BA5: ２次店名称（カナ） | BB5: ２次店名称（漢字） | BC5: ３次店企業コード | BD5: ３次店部門コード | BE5: ３次店名称（カナ） | BF5: ３次店名称（漢字） | BG5: 決済条件締切日 | BH5: 決済条件起算日 | BI5: 決済条件手段 | BJ5: 決済条件満期日 | BK5: 決済条件基準 | BL5: 決済条件 | BM5: 数量確定区分 | BN5: 販売単価 | BO5: 単価単位 | BP5: 単価区分 | BQ5: 口銭区分 | BR5: 口銭単価 | BS5: 口銭 | BT5: ２次店口銭区分 | BU5: ２次店口銭単価 | BV5: ２次店口銭 | BW5: 納入先企業コード | BX5: 納入先部門コード | BY5: 納入先名称（カナ） | BZ5: 納入先名称（漢字） | CA5: 受渡条件 | CB5: 受渡場所住所（カナ） | CC5: 受渡場所住所（漢字） | CD5: 地区コード | CE5: 郵便番号 | CF5: 電話番号 | CG5: FAX電話番号 | CH5: 希望納入年月日 | CI5: 希望納入時刻 | CJ5: 希望納入コメント | CK5: 納入年月日（予定） | CL5: 納入要件（カナ） | CM5: 納入要件（漢字） | CN5: 支払金額 | CO5: 支払整理番号 | CP5: 手形番号（小切手番号） | CQ5: 振出銀行（コード） | CR5: 振出銀行（名称） | CS5: 振込銀行（コード） | CT5: 振込銀行（名称） | CU5: 口座番号 | CV5: 支払要件 | CW5: 注文数量 | CX5: 注文・販売個数 | CY5: 注文数量単位 | CZ5: 販売数量 | DA5: 金額算出数量 | DB5: 荷姿 | DC5: 容量 | DD5: 販売金額 | DE5: 請求金額 | DF5: 消費税額 | DG5: 税込請求額 | DH5: 単価金額区分 | DI5: 取引区分 | DJ5: 遡及区分 | DK5: 出荷請求区分 | DL5: 課税区分 | DM5: バックオーダー区分 | DN5: 計上年月 | DO5: 出荷年月日（予定） | DP5: 出荷報告番号 | DQ5: 出荷請求番号 | DR5: 出荷場所 | DS5: 出荷指図コメント（カナ） | DT5: 出荷指図コメント（漢字） | DU5: 輸送手段 | DV5: 輸送車種 | DW5: 発注者情報 | DX5: 受注者情報 | DY5: 国内輸出区分 | DZ5: エラー理由 | EA5: エラーコメント（カナ） | EB5: エラーコメント（漢字） | EC5: 請求確認区分 | ED5: 予備欄（カナ） | EE5: 予備欄（漢字） | EF5: FILLER
C6: =IF(発注_送信ファイル!C4="","",発注_送信ファイル!C4) -> 【テスト結果】 | D6: TUGA0501を以下に貼り付ける
B7: =ROW()-6 -> 1 | C7: =IF(発注_送信ファイル!C5="","",発注_送信ファイル!C5) -> NO.32,33,39 | D7: =IF(発注_送信ファイル!$D5="","",MIDB(発注_送信ファイル!$D5,発注_送信ファイル_項目分割!D$3,発注_送信ファイル_項目分割!D$4)) | E7: =IF(発注_送信ファイル!$D5="","",MIDB(発注_送信ファイル!$D5,発注_送信ファイル_項目分割!E$3,発注_送信ファイル_項目分割!E$4)) -> JPCA0102 | F7: =IF(発注_送信ファイル!$D5="","",MIDB(発注_送信ファイル!$D5,発注_送信ファイル_項目分割!F$3,発注_送信ファイル_項目分割!F$4)) -> S | G7: =IF(発注_送信ファイル!$D5="","",MIDB(発注_送信ファイル!$D5,発注_送信ファイル_項目分割!G$3,発注_送信ファイル_項目分割!G$4)) -> 1510 | H7: =IF(発注_送信ファイル!$D5="","",MIDB(発注_送信ファイル!$D5,発注_送信ファイル_項目分割!H$3,発注_送信ファイル_項目分割!H$4)) -> 101913000110 | I7: =IF(発注_送信ファイル!$D5="","",MIDB(発注_送信ファイル!$D5,発注_送信ファイル_項目分割!I$3,発注_送信ファイル_項目分割!I$4)) -> 504832000001 | J7: =IF(発注_送信ファイル!$D5="","",MIDB(発注_送信ファイル!$D5,発注_送信ファイル_項目分割!J$3,発注_送信ファイル_項目分割!J$4)) -> 1510 | K7: =IF(発注_送信ファイル!$D5="","",MIDB(発注_送信ファイル!$D5,発注_送信ファイル_項目分割!K$3,発注_送信ファイル_項目分割!K$4)) -> 1 | ... EF7: =IF(発注_送信ファイル!$D5="","",MIDB(発注_送信ファイル!$D5,発注_送信ファイル_項目分割!EF$3,発注_送信ファイル_項目分割!EF$4))
B8: =ROW()-6 -> 2 | C8: =IF(発注_送信ファイル!C6="","",発注_送信ファイル!C6) | D8: =IF(発注_送信ファイル!$D6="","",MIDB(発注_送信ファイル!$D6,発注_送信ファイル_項目分割!D$3,発注_送信ファイル_項目分割!D$4)) | E8: =IF(発注_送信ファイル!$D6="","",MIDB(発注_送信ファイル!$D6,発注_送信ファイル_項目分割!E$3,発注_送信ファイル_項目分割!E$4)) -> JPCA0102 | F8: =IF(発注_送信ファイル!$D6="","",MIDB(発注_送信ファイル!$D6,発注_送信ファイル_項目分割!F$3,発注_送信ファイル_項目分割!F$4)) -> S | G8: =IF(発注_送信ファイル!$D6="","",MIDB(発注_送信ファイル!$D6,発注_送信ファイル_項目分割!G$3,発注_送信ファイル_項目分割!G$4)) -> 1510 | H8: =IF(発注_送信ファイル!$D6="","",MIDB(発注_送信ファイル!$D6,発注_送信ファイル_項目分割!H$3,発注_送信ファイル_項目分割!H$4)) -> 101913000110 | I8: =IF(発注_送信ファイル!$D6="","",MIDB(発注_送信ファイル!$D6,発注_送信ファイル_項目分割!I$3,発注_送信ファイル_項目分割!I$4)) -> 504832000001 | J8: =IF(発注_送信ファイル!$D6="","",MIDB(発注_送信ファイル!$D6,発注_送信ファイル_項目分割!J$3,発注_送信ファイル_項目分割!J$4)) -> 1510 | K8: =IF(発注_送信ファイル!$D6="","",MIDB(発注_送信ファイル!$D6,発注_送信ファイル_項目分割!K$3,発注_送信ファイル_項目分割!K$4)) -> 1 | ... EF8: =IF(発注_送信ファイル!$D6="","",MIDB(発注_送信ファイル!$D6,発注_送信ファイル_項目分割!EF$3,発注_送信ファイル_項目分割!EF$4))
B9: =ROW()-6 -> 3 | C9: =IF(発注_送信ファイル!C7="","",発注_送信ファイル!C7) | D9: =IF(発注_送信ファイル!$D7="","",MIDB(発注_送信ファイル!$D7,発注_送信ファイル_項目分割!D$3,発注_送信ファイル_項目分割!D$4)) | E9: =IF(発注_送信ファイル!$D7="","",MIDB(発注_送信ファイル!$D7,発注_送信ファイル_項目分割!E$3,発注_送信ファイル_項目分割!E$4)) -> JPCA0102 | F9: =IF(発注_送信ファイル!$D7="","",MIDB(発注_送信ファイル!$D7,発注_送信ファイル_項目分割!F$3,発注_送信ファイル_項目分割!F$4)) -> S | G9: =IF(発注_送信ファイル!$D7="","",MIDB(発注_送信ファイル!$D7,発注_送信ファイル_項目分割!G$3,発注_送信ファイル_項目分割!G$4)) -> 1510 | H9: =IF(発注_送信ファイル!$D7="","",MIDB(発注_送信ファイル!$D7,発注_送信ファイル_項目分割!H$3,発注_送信ファイル_項目分割!H$4)) -> 101913000110 | I9: =IF(発注_送信ファイル!$D7="","",MIDB(発注_送信ファイル!$D7,発注_送信ファイル_項目分割!I$3,発注_送信ファイル_項目分割!I$4)) -> 504832000001 | J9: =IF(発注_送信ファイル!$D7="","",MIDB(発注_送信ファイル!$D7,発注_送信ファイル_項目分割!J$3,発注_送信ファイル_項目分割!J$4)) -> 1510 | K9: =IF(発注_送信ファイル!$D7="","",MIDB(発注_送信ファイル!$D7,発注_送信ファイル_項目分割!K$3,発注_送信ファイル_項目分割!K$4)) -> 1 | ... EF9: =IF(発注_送信ファイル!$D7="","",MIDB(発注_送信ファイル!$D7,発注_送信ファイル_項目分割!EF$3,発注_送信ファイル_項目分割!EF$4))
B10: =ROW()-6 -> 4 | C10: =IF(発注_送信ファイル!C8="","",発注_送信ファイル!C8) | D10: =IF(発注_送信ファイル!$D8="","",MIDB(発注_送信ファイル!$D8,発注_送信ファイル_項目分割!D$3,発注_送信ファイル_項目分割!D$4)) | E10: =IF(発注_送信ファイル!$D8="","",MIDB(発注_送信ファイル!$D8,発注_送信ファイル_項目分割!E$3,発注_送信ファイル_項目分割!E$4)) -> JPCA0102 | F10: =IF(発注_送信ファイル!$D8="","",MIDB(発注_送信ファイル!$D8,発注_送信ファイル_項目分割!F$3,発注_送信ファイル_項目分割!F$4)) -> S | G10: =IF(発注_送信ファイル!$D8="","",MIDB(発注_送信ファイル!$D8,発注_送信ファイル_項目分割!G$3,発注_送信ファイル_項目分割!G$4)) -> 1510 | H10: =IF(発注_送信ファイル!$D8="","",MIDB(発注_送信ファイル!$D8,発注_送信ファイル_項目分割!H$3,発注_送信ファイル_項目分割!H$4)) -> 101913000110 | I10: =IF(発注_送信ファイル!$D8="","",MIDB(発注_送信ファイル!$D8,発注_送信ファイル_項目分割!I$3,発注_送信ファイル_項目分割!I$4)) -> 504832000001 | J10: =IF(発注_送信ファイル!$D8="","",MIDB(発注_送信ファイル!$D8,発注_送信ファイル_項目分割!J$3,発注_送信ファイル_項目分割!J$4)) -> 1510 | K10: =IF(発注_送信ファイル!$D8="","",MIDB(発注_送信ファイル!$D8,発注_送信ファイル_項目分割!K$3,発注_送信ファイル_項目分割!K$4)) -> 1 | ... EF10: =IF(発注_送信ファイル!$D8="","",MIDB(発注_送信ファイル!$D8,発注_送信ファイル_項目分割!EF$3,発注_送信ファイル_項目分割!EF$4))
B11: =ROW()-6 -> 5 | C11: =IF(発注_送信ファイル!C9="","",発注_送信ファイル!C9) | D11: =IF(発注_送信ファイル!$D9="","",MIDB(発注_送信ファイル!$D9,発注_送信ファイル_項目分割!D$3,発注_送信ファイル_項目分割!D$4)) | E11: =IF(発注_送信ファイル!$D9="","",MIDB(発注_送信ファイル!$D9,発注_送信ファイル_項目分割!E$3,発注_送信ファイル_項目分割!E$4)) -> JPCA0102 | F11: =IF(発注_送信ファイル!$D9="","",MIDB(発注_送信ファイル!$D9,発注_送信ファイル_項目分割!F$3,発注_送信ファイル_項目分割!F$4)) -> S | G11: =IF(発注_送信ファイル!$D9="","",MIDB(発注_送信ファイル!$D9,発注_送信ファイル_項目分割!G$3,発注_送信ファイル_項目分割!G$4)) -> 1510 | H11: =IF(発注_送信ファイル!$D9="","",MIDB(発注_送信ファイル!$D9,発注_送信ファイル_項目分割!H$3,発注_送信ファイル_項目分割!H$4)) -> 101913000110 | I11: =IF(発注_送信ファイル!$D9="","",MIDB(発注_送信ファイル!$D9,発注_送信ファイル_項目分割!I$3,発注_送信ファイル_項目分割!I$4)) -> 504832000001 | J11: =IF(発注_送信ファイル!$D9="","",MIDB(発注_送信ファイル!$D9,発注_送信ファイル_項目分割!J$3,発注_送信ファイル_項目分割!J$4)) -> 1510 | K11: =IF(発注_送信ファイル!$D9="","",MIDB(発注_送信ファイル!$D9,発注_送信ファイル_項目分割!K$3,発注_送信ファイル_項目分割!K$4)) -> 1 | ... EF11: =IF(発注_送信ファイル!$D9="","",MIDB(発注_送信ファイル!$D9,発注_送信ファイル_項目分割!EF$3,発注_送信ファイル_項目分割!EF$4))
B12: =ROW()-6 -> 6 | C12: =IF(発注_送信ファイル!C10="","",発注_送信ファイル!C10) | D12: =IF(発注_送信ファイル!$D10="","",MIDB(発注_送信ファイル!$D10,発注_送信ファイル_項目分割!D$3,発注_送信ファイル_項目分割!D$4)) | E12: =IF(発注_送信ファイル!$D10="","",MIDB(発注_送信ファイル!$D10,発注_送信ファイル_項目分割!E$3,発注_送信ファイル_項目分割!E$4)) -> JPCA0102 | F12: =IF(発注_送信ファイル!$D10="","",MIDB(発注_送信ファイル!$D10,発注_送信ファイル_項目分割!F$3,発注_送信ファイル_項目分割!F$4)) -> S | G12: =IF(発注_送信ファイル!$D10="","",MIDB(発注_送信ファイル!$D10,発注_送信ファイル_項目分割!G$3,発注_送信ファイル_項目分割!G$4)) -> 1510 | H12: =IF(発注_送信ファイル!$D10="","",MIDB(発注_送信ファイル!$D10,発注_送信ファイル_項目分割!H$3,発注_送信ファイル_項目分割!H$4)) -> 101913000110 | I12: =IF(発注_送信ファイル!$D10="","",MIDB(発注_送信ファイル!$D10,発注_送信ファイル_項目分割!I$3,発注_送信ファイル_項目分割!I$4)) -> 504832000001 | J12: =IF(発注_送信ファイル!$D10="","",MIDB(発注_送信ファイル!$D10,発注_送信ファイル_項目分割!J$3,発注_送信ファイル_項目分割!J$4)) -> 1510 | K12: =IF(発注_送信ファイル!$D10="","",MIDB(発注_送信ファイル!$D10,発注_送信ファイル_項目分割!K$3,発注_送信ファイル_項目分割!K$4)) -> 1 | ... EF12: =IF(発注_送信ファイル!$D10="","",MIDB(発注_送信ファイル!$D10,発注_送信ファイル_項目分割!EF$3,発注_送信ファイル_項目分割!EF$4))
B13: =ROW()-6 -> 7 | C13: =IF(発注_送信ファイル!C11="","",発注_送信ファイル!C11) | D13: =IF(発注_送信ファイル!$D11="","",MIDB(発注_送信ファイル!$D11,発注_送信ファイル_項目分割!D$3,発注_送信ファイル_項目分割!D$4)) | E13: =IF(発注_送信ファイル!$D11="","",MIDB(発注_送信ファイル!$D11,発注_送信ファイル_項目分割!E$3,発注_送信ファイル_項目分割!E$4)) | F13: =IF(発注_送信ファイル!$D11="","",MIDB(発注_送信ファイル!$D11,発注_送信ファイル_項目分割!F$3,発注_送信ファイル_項目分割!F$4)) | G13: =IF(発注_送信ファイル!$D11="","",MIDB(発注_送信ファイル!$D11,発注_送信ファイル_項目分割!G$3,発注_送信ファイル_項目分割!G$4)) | H13: =IF(発注_送信ファイル!$D11="","",MIDB(発注_送信ファイル!$D11,発注_送信ファイル_項目分割!H$3,発注_送信ファイル_項目分割!H$4)) | I13: =IF(発注_送信ファイル!$D11="","",MIDB(発注_送信ファイル!$D11,発注_送信ファイル_項目分割!I$3,発注_送信ファイル_項目分割!I$4)) | J13: =IF(発注_送信ファイル!$D11="","",MIDB(発注_送信ファイル!$D11,発注_送信ファイル_項目分割!J$3,発注_送信ファイル_項目分割!J$4)) | K13: =IF(発注_送信ファイル!$D11="","",MIDB(発注_送信ファイル!$D11,発注_送信ファイル_項目分割!K$3,発注_送信ファイル_項目分割!K$4)) | ... EF13: =IF(発注_送信ファイル!$D11="","",MIDB(発注_送信ファイル!$D11,発注_送信ファイル_項目分割!EF$3,発注_送信ファイル_項目分割!EF$4))
B14: =ROW()-6 -> 8 | C14: =IF(発注_送信ファイル!C12="","",発注_送信ファイル!C12) | D14: =IF(発注_送信ファイル!$D12="","",MIDB(発注_送信ファイル!$D12,発注_送信ファイル_項目分割!D$3,発注_送信ファイル_項目分割!D$4)) | E14: =IF(発注_送信ファイル!$D12="","",MIDB(発注_送信ファイル!$D12,発注_送信ファイル_項目分割!E$3,発注_送信ファイル_項目分割!E$4)) | F14: =IF(発注_送信ファイル!$D12="","",MIDB(発注_送信ファイル!$D12,発注_送信ファイル_項目分割!F$3,発注_送信ファイル_項目分割!F$4)) | G14: =IF(発注_送信ファイル!$D12="","",MIDB(発注_送信ファイル!$D12,発注_送信ファイル_項目分割!G$3,発注_送信ファイル_項目分割!G$4)) | H14: =IF(発注_送信ファイル!$D12="","",MIDB(発注_送信ファイル!$D12,発注_送信ファイル_項目分割!H$3,発注_送信ファイル_項目分割!H$4)) | I14: =IF(発注_送信ファイル!$D12="","",MIDB(発注_送信ファイル!$D12,発注_送信ファイル_項目分割!I$3,発注_送信ファイル_項目分割!I$4)) | J14: =IF(発注_送信ファイル!$D12="","",MIDB(発注_送信ファイル!$D12,発注_送信ファイル_項目分割!J$3,発注_送信ファイル_項目分割!J$4)) | K14: =IF(発注_送信ファイル!$D12="","",MIDB(発注_送信ファイル!$D12,発注_送信ファイル_項目分割!K$3,発注_送信ファイル_項目分割!K$4)) | ... EF14: =IF(発注_送信ファイル!$D12="","",MIDB(発注_送信ファイル!$D12,発注_送信ファイル_項目分割!EF$3,発注_送信ファイル_項目分割!EF$4))
B15: =ROW()-6 -> 9 | C15: =IF(発注_送信ファイル!C13="","",発注_送信ファイル!C13) | D15: =IF(発注_送信ファイル!$D13="","",MIDB(発注_送信ファイル!$D13,発注_送信ファイル_項目分割!D$3,発注_送信ファイル_項目分割!D$4)) | E15: =IF(発注_送信ファイル!$D13="","",MIDB(発注_送信ファイル!$D13,発注_送信ファイル_項目分割!E$3,発注_送信ファイル_項目分割!E$4)) | F15: =IF(発注_送信ファイル!$D13="","",MIDB(発注_送信ファイル!$D13,発注_送信ファイル_項目分割!F$3,発注_送信ファイル_項目分割!F$4)) | G15: =IF(発注_送信ファイル!$D13="","",MIDB(発注_送信ファイル!$D13,発注_送信ファイル_項目分割!G$3,発注_送信ファイル_項目分割!G$4)) | H15: =IF(発注_送信ファイル!$D13="","",MIDB(発注_送信ファイル!$D13,発注_送信ファイル_項目分割!H$3,発注_送信ファイル_項目分割!H$4)) | I15: =IF(発注_送信ファイル!$D13="","",MIDB(発注_送信ファイル!$D13,発注_送信ファイル_項目分割!I$3,発注_送信ファイル_項目分割!I$4)) | J15: =IF(発注_送信ファイル!$D13="","",MIDB(発注_送信ファイル!$D13,発注_送信ファイル_項目分割!J$3,発注_送信ファイル_項目分割!J$4)) | K15: =IF(発注_送信ファイル!$D13="","",MIDB(発注_送信ファイル!$D13,発注_送信ファイル_項目分割!K$3,発注_送信ファイル_項目分割!K$4)) | ... EF15: =IF(発注_送信ファイル!$D13="","",MIDB(発注_送信ファイル!$D13,発注_送信ファイル_項目分割!EF$3,発注_送信ファイル_項目分割!EF$4))
B16: =ROW()-6 -> 10 | C16: =IF(発注_送信ファイル!C14="","",発注_送信ファイル!C14) | D16: =IF(発注_送信ファイル!$D14="","",MIDB(発注_送信ファイル!$D14,発注_送信ファイル_項目分割!D$3,発注_送信ファイル_項目分割!D$4)) | E16: =IF(発注_送信ファイル!$D14="","",MIDB(発注_送信ファイル!$D14,発注_送信ファイル_項目分割!E$3,発注_送信ファイル_項目分割!E$4)) | F16: =IF(発注_送信ファイル!$D14="","",MIDB(発注_送信ファイル!$D14,発注_送信ファイル_項目分割!F$3,発注_送信ファイル_項目分割!F$4)) | G16: =IF(発注_送信ファイル!$D14="","",MIDB(発注_送信ファイル!$D14,発注_送信ファイル_項目分割!G$3,発注_送信ファイル_項目分割!G$4)) | H16: =IF(発注_送信ファイル!$D14="","",MIDB(発注_送信ファイル!$D14,発注_送信ファイル_項目分割!H$3,発注_送信ファイル_項目分割!H$4)) | I16: =IF(発注_送信ファイル!$D14="","",MIDB(発注_送信ファイル!$D14,発注_送信ファイル_項目分割!I$3,発注_送信ファイル_項目分割!I$4)) | J16: =IF(発注_送信ファイル!$D14="","",MIDB(発注_送信ファイル!$D14,発注_送信ファイル_項目分割!J$3,発注_送信ファイル_項目分割!J$4)) | K16: =IF(発注_送信ファイル!$D14="","",MIDB(発注_送信ファイル!$D14,発注_送信ファイル_項目分割!K$3,発注_送信ファイル_項目分割!K$4)) | ... EF16: =IF(発注_送信ファイル!$D14="","",MIDB(発注_送信ファイル!$D14,発注_送信ファイル_項目分割!EF$3,発注_送信ファイル_項目分割!EF$4))
B17: =ROW()-6 -> 11 | C17: =IF(発注_送信ファイル!C15="","",発注_送信ファイル!C15) | F17: =IF(発注_送信ファイル!$D15="","",MIDB(発注_送信ファイル!$D15,発注_送信ファイル_項目分割!F$3,発注_送信ファイル_項目分割!F$4)) | G17: =IF(発注_送信ファイル!$D15="","",MIDB(発注_送信ファイル!$D15,発注_送信ファイル_項目分割!G$3,発注_送信ファイル_項目分割!G$4)) | H17: =IF(発注_送信ファイル!$D15="","",MIDB(発注_送信ファイル!$D15,発注_送信ファイル_項目分割!H$3,発注_送信ファイル_項目分割!H$4)) | I17: =IF(発注_送信ファイル!$D15="","",MIDB(発注_送信ファイル!$D15,発注_送信ファイル_項目分割!I$3,発注_送信ファイル_項目分割!I$4)) | J17: =IF(発注_送信ファイル!$D15="","",MIDB(発注_送信ファイル!$D15,発注_送信ファイル_項目分割!J$3,発注_送信ファイル_項目分割!J$4)) | K17: =IF(発注_送信ファイル!$D15="","",MIDB(発注_送信ファイル!$D15,発注_送信ファイル_項目分割!K$3,発注_送信ファイル_項目分割!K$4)) | L17: =IF(発注_送信ファイル!$D15="","",MIDB(発注_送信ファイル!$D15,発注_送信ファイル_項目分割!L$3,発注_送信ファイル_項目分割!L$4)) | M17: =IF(発注_送信ファイル!$D15="","",MIDB(発注_送信ファイル!$D15,発注_送信ファイル_項目分割!M$3,発注_送信ファイル_項目分割!M$4)) | ... EF17: =IF(発注_送信ファイル!$D15="","",MIDB(発注_送信ファイル!$D15,発注_送信ファイル_項目分割!EF$3,発注_送信ファイル_項目分割!EF$4))
B18: =ROW()-6 -> 12 | C18: =IF(発注_送信ファイル!C16="","",発注_送信ファイル!C16) | D18: =IF(発注_送信ファイル!$D16="","",MIDB(発注_送信ファイル!$D16,発注_送信ファイル_項目分割!D$3,発注_送信ファイル_項目分割!D$4)) | E18: =IF(発注_送信ファイル!$D16="","",MIDB(発注_送信ファイル!$D16,発注_送信ファイル_項目分割!E$3,発注_送信ファイル_項目分割!E$4)) | F18: =IF(発注_送信ファイル!$D16="","",MIDB(発注_送信ファイル!$D16,発注_送信ファイル_項目分割!F$3,発注_送信ファイル_項目分割!F$4)) | G18: =IF(発注_送信ファイル!$D16="","",MIDB(発注_送信ファイル!$D16,発注_送信ファイル_項目分割!G$3,発注_送信ファイル_項目分割!G$4)) | H18: =IF(発注_送信ファイル!$D16="","",MIDB(発注_送信ファイル!$D16,発注_送信ファイル_項目分割!H$3,発注_送信ファイル_項目分割!H$4)) | I18: =IF(発注_送信ファイル!$D16="","",MIDB(発注_送信ファイル!$D16,発注_送信ファイル_項目分割!I$3,発注_送信ファイル_項目分割!I$4)) | J18: =IF(発注_送信ファイル!$D16="","",MIDB(発注_送信ファイル!$D16,発注_送信ファイル_項目分割!J$3,発注_送信ファイル_項目分割!J$4)) | K18: =IF(発注_送信ファイル!$D16="","",MIDB(発注_送信ファイル!$D16,発注_送信ファイル_項目分割!K$3,発注_送信ファイル_項目分割!K$4)) | ... EF18: =IF(発注_送信ファイル!$D16="","",MIDB(発注_送信ファイル!$D16,発注_送信ファイル_項目分割!EF$3,発注_送信ファイル_項目分割!EF$4))
B19: =ROW()-6 -> 13 | C19: =IF(発注_送信ファイル!C17="","",発注_送信ファイル!C17) | D19: =IF(発注_送信ファイル!$D17="","",MIDB(発注_送信ファイル!$D17,発注_送信ファイル_項目分割!D$3,発注_送信ファイル_項目分割!D$4)) | E19: =IF(発注_送信ファイル!$D17="","",MIDB(発注_送信ファイル!$D17,発注_送信ファイル_項目分割!E$3,発注_送信ファイル_項目分割!E$4)) | F19: =IF(発注_送信ファイル!$D17="","",MIDB(発注_送信ファイル!$D17,発注_送信ファイル_項目分割!F$3,発注_送信ファイル_項目分割!F$4)) | G19: =IF(発注_送信ファイル!$D17="","",MIDB(発注_送信ファイル!$D17,発注_送信ファイル_項目分割!G$3,発注_送信ファイル_項目分割!G$4)) | H19: =IF(発注_送信ファイル!$D17="","",MIDB(発注_送信ファイル!$D17,発注_送信ファイル_項目分割!H$3,発注_送信ファイル_項目分割!H$4)) | I19: =IF(発注_送信ファイル!$D17="","",MIDB(発注_送信ファイル!$D17,発注_送信ファイル_項目分割!I$3,発注_送信ファイル_項目分割!I$4)) | J19: =IF(発注_送信ファイル!$D17="","",MIDB(発注_送信ファイル!$D17,発注_送信ファイル_項目分割!J$3,発注_送信ファイル_項目分割!J$4)) | K19: =IF(発注_送信ファイル!$D17="","",MIDB(発注_送信ファイル!$D17,発注_送信ファイル_項目分割!K$3,発注_送信ファイル_項目分割!K$4)) | ... EF19: =IF(発注_送信ファイル!$D17="","",MIDB(発注_送信ファイル!$D17,発注_送信ファイル_項目分割!EF$3,発注_送信ファイル_項目分割!EF$4))
B20: =ROW()-6 -> 14 | C20: =IF(発注_送信ファイル!C18="","",発注_送信ファイル!C18) | D20: =IF(発注_送信ファイル!$D18="","",MIDB(発注_送信ファイル!$D18,発注_送信ファイル_項目分割!D$3,発注_送信ファイル_項目分割!D$4)) | E20: =IF(発注_送信ファイル!$D18="","",MIDB(発注_送信ファイル!$D18,発注_送信ファイル_項目分割!E$3,発注_送信ファイル_項目分割!E$4)) | F20: =IF(発注_送信ファイル!$D18="","",MIDB(発注_送信ファイル!$D18,発注_送信ファイル_項目分割!F$3,発注_送信ファイル_項目分割!F$4)) | G20: =IF(発注_送信ファイル!$D18="","",MIDB(発注_送信ファイル!$D18,発注_送信ファイル_項目分割!G$3,発注_送信ファイル_項目分割!G$4)) | H20: =IF(発注_送信ファイル!$D18="","",MIDB(発注_送信ファイル!$D18,発注_送信ファイル_項目分割!H$3,発注_送信ファイル_項目分割!H$4)) | I20: =IF(発注_送信ファイル!$D18="","",MIDB(発注_送信ファイル!$D18,発注_送信ファイル_項目分割!I$3,発注_送信ファイル_項目分割!I$4)) | J20: =IF(発注_送信ファイル!$D18="","",MIDB(発注_送信ファイル!$D18,発注_送信ファイル_項目分割!J$3,発注_送信ファイル_項目分割!J$4)) | K20: =IF(発注_送信ファイル!$D18="","",MIDB(発注_送信ファイル!$D18,発注_送信ファイル_項目分割!K$3,発注_送信ファイル_項目分割!K$4)) | ... EF20: =IF(発注_送信ファイル!$D18="","",MIDB(発注_送信ファイル!$D18,発注_送信ファイル_項目分割!EF$3,発注_送信ファイル_項目分割!EF$4))
B21: =ROW()-6 -> 15 | C21: =IF(発注_送信ファイル!C19="","",発注_送信ファイル!C19) | D21: =IF(発注_送信ファイル!$D19="","",MIDB(発注_送信ファイル!$D19,発注_送信ファイル_項目分割!D$3,発注_送信ファイル_項目分割!D$4)) | E21: =IF(発注_送信ファイル!$D19="","",MIDB(発注_送信ファイル!$D19,発注_送信ファイル_項目分割!E$3,発注_送信ファイル_項目分割!E$4)) | F21: =IF(発注_送信ファイル!$D19="","",MIDB(発注_送信ファイル!$D19,発注_送信ファイル_項目分割!F$3,発注_送信ファイル_項目分割!F$4)) | G21: =IF(発注_送信ファイル!$D19="","",MIDB(発注_送信ファイル!$D19,発注_送信ファイル_項目分割!G$3,発注_送信ファイル_項目分割!G$4)) | H21: =IF(発注_送信ファイル!$D19="","",MIDB(発注_送信ファイル!$D19,発注_送信ファイル_項目分割!H$3,発注_送信ファイル_項目分割!H$4)) | I21: =IF(発注_送信ファイル!$D19="","",MIDB(発注_送信ファイル!$D19,発注_送信ファイル_項目分割!I$3,発注_送信ファイル_項目分割!I$4)) | J21: =IF(発注_送信ファイル!$D19="","",MIDB(発注_送信ファイル!$D19,発注_送信ファイル_項目分割!J$3,発注_送信ファイル_項目分割!J$4)) | K21: =IF(発注_送信ファイル!$D19="","",MIDB(発注_送信ファイル!$D19,発注_送信ファイル_項目分割!K$3,発注_送信ファイル_項目分割!K$4)) | ... EF21: =IF(発注_送信ファイル!$D19="","",MIDB(発注_送信ファイル!$D19,発注_送信ファイル_項目分割!EF$3,発注_送信ファイル_項目分割!EF$4))
B22: =ROW()-6 -> 16 | C22: =IF(発注_送信ファイル!C20="","",発注_送信ファイル!C20) | D22: =IF(発注_送信ファイル!$D20="","",MIDB(発注_送信ファイル!$D20,発注_送信ファイル_項目分割!D$3,発注_送信ファイル_項目分割!D$4)) | E22: =IF(発注_送信ファイル!$D20="","",MIDB(発注_送信ファイル!$D20,発注_送信ファイル_項目分割!E$3,発注_送信ファイル_項目分割!E$4)) | F22: =IF(発注_送信ファイル!$D20="","",MIDB(発注_送信ファイル!$D20,発注_送信ファイル_項目分割!F$3,発注_送信ファイル_項目分割!F$4)) | G22: =IF(発注_送信ファイル!$D20="","",MIDB(発注_送信ファイル!$D20,発注_送信ファイル_項目分割!G$3,発注_送信ファイル_項目分割!G$4)) | H22: =IF(発注_送信ファイル!$D20="","",MIDB(発注_送信ファイル!$D20,発注_送信ファイル_項目分割!H$3,発注_送信ファイル_項目分割!H$4)) | I22: =IF(発注_送信ファイル!$D20="","",MIDB(発注_送信ファイル!$D20,発注_送信ファイル_項目分割!I$3,発注_送信ファイル_項目分割!I$4)) | J22: =IF(発注_送信ファイル!$D20="","",MIDB(発注_送信ファイル!$D20,発注_送信ファイル_項目分割!J$3,発注_送信ファイル_項目分割!J$4)) | K22: =IF(発注_送信ファイル!$D20="","",MIDB(発注_送信ファイル!$D20,発注_送信ファイル_項目分割!K$3,発注_送信ファイル_項目分割!K$4)) | ... EF22: =IF(発注_送信ファイル!$D20="","",MIDB(発注_送信ファイル!$D20,発注_送信ファイル_項目分割!EF$3,発注_送信ファイル_項目分割!EF$4))
B23: =ROW()-6 -> 17 | C23: =IF(発注_送信ファイル!C21="","",発注_送信ファイル!C21) | D23: =IF(発注_送信ファイル!$D21="","",MIDB(発注_送信ファイル!$D21,発注_送信ファイル_項目分割!D$3,発注_送信ファイル_項目分割!D$4)) | E23: =IF(発注_送信ファイル!$D21="","",MIDB(発注_送信ファイル!$D21,発注_送信ファイル_項目分割!E$3,発注_送信ファイル_項目分割!E$4)) | F23: =IF(発注_送信ファイル!$D21="","",MIDB(発注_送信ファイル!$D21,発注_送信ファイル_項目分割!F$3,発注_送信ファイル_項目分割!F$4)) | G23: =IF(発注_送信ファイル!$D21="","",MIDB(発注_送信ファイル!$D21,発注_送信ファイル_項目分割!G$3,発注_送信ファイル_項目分割!G$4)) | H23: =IF(発注_送信ファイル!$D21="","",MIDB(発注_送信ファイル!$D21,発注_送信ファイル_項目分割!H$3,発注_送信ファイル_項目分割!H$4)) | I23: =IF(発注_送信ファイル!$D21="","",MIDB(発注_送信ファイル!$D21,発注_送信ファイル_項目分割!I$3,発注_送信ファイル_項目分割!I$4)) | J23: =IF(発注_送信ファイル!$D21="","",MIDB(発注_送信ファイル!$D21,発注_送信ファイル_項目分割!J$3,発注_送信ファイル_項目分割!J$4)) | K23: =IF(発注_送信ファイル!$D21="","",MIDB(発注_送信ファイル!$D21,発注_送信ファイル_項目分割!K$3,発注_送信ファイル_項目分割!K$4)) | ... EF23: =IF(発注_送信ファイル!$D21="","",MIDB(発注_送信ファイル!$D21,発注_送信ファイル_項目分割!EF$3,発注_送信ファイル_項目分割!EF$4))
B24: =ROW()-6 -> 18 | C24: =IF(発注_送信ファイル!C22="","",発注_送信ファイル!C22) | D24: =IF(発注_送信ファイル!$D22="","",MIDB(発注_送信ファイル!$D22,発注_送信ファイル_項目分割!D$3,発注_送信ファイル_項目分割!D$4)) | E24: =IF(発注_送信ファイル!$D22="","",MIDB(発注_送信ファイル!$D22,発注_送信ファイル_項目分割!E$3,発注_送信ファイル_項目分割!E$4)) | F24: =IF(発注_送信ファイル!$D22="","",MIDB(発注_送信ファイル!$D22,発注_送信ファイル_項目分割!F$3,発注_送信ファイル_項目分割!F$4)) | G24: =IF(発注_送信ファイル!$D22="","",MIDB(発注_送信ファイル!$D22,発注_送信ファイル_項目分割!G$3,発注_送信ファイル_項目分割!G$4)) | H24: =IF(発注_送信ファイル!$D22="","",MIDB(発注_送信ファイル!$D22,発注_送信ファイル_項目分割!H$3,発注_送信ファイル_項目分割!H$4)) | I24: =IF(発注_送信ファイル!$D22="","",MIDB(発注_送信ファイル!$D22,発注_送信ファイル_項目分割!I$3,発注_送信ファイル_項目分割!I$4)) | J24: =IF(発注_送信ファイル!$D22="","",MIDB(発注_送信ファイル!$D22,発注_送信ファイル_項目分割!J$3,発注_送信ファイル_項目分割!J$4)) | K24: =IF(発注_送信ファイル!$D22="","",MIDB(発注_送信ファイル!$D22,発注_送信ファイル_項目分割!K$3,発注_送信ファイル_項目分割!K$4)) | ... EF24: =IF(発注_送信ファイル!$D22="","",MIDB(発注_送信ファイル!$D22,発注_送信ファイル_項目分割!EF$3,発注_送信ファイル_項目分割!EF$4))
B25: =ROW()-6 -> 19 | C25: =IF(発注_送信ファイル!C23="","",発注_送信ファイル!C23) | D25: =IF(発注_送信ファイル!$D23="","",MIDB(発注_送信ファイル!$D23,発注_送信ファイル_項目分割!D$3,発注_送信ファイル_項目分割!D$4)) | E25: =IF(発注_送信ファイル!$D23="","",MIDB(発注_送信ファイル!$D23,発注_送信ファイル_項目分割!E$3,発注_送信ファイル_項目分割!E$4)) | F25: =IF(発注_送信ファイル!$D23="","",MIDB(発注_送信ファイル!$D23,発注_送信ファイル_項目分割!F$3,発注_送信ファイル_項目分割!F$4)) | G25: =IF(発注_送信ファイル!$D23="","",MIDB(発注_送信ファイル!$D23,発注_送信ファイル_項目分割!G$3,発注_送信ファイル_項目分割!G$4)) | H25: =IF(発注_送信ファイル!$D23="","",MIDB(発注_送信ファイル!$D23,発注_送信ファイル_項目分割!H$3,発注_送信ファイル_項目分割!H$4)) | I25: =IF(発注_送信ファイル!$D23="","",MIDB(発注_送信ファイル!$D23,発注_送信ファイル_項目分割!I$3,発注_送信ファイル_項目分割!I$4)) | J25: =IF(発注_送信ファイル!$D23="","",MIDB(発注_送信ファイル!$D23,発注_送信ファイル_項目分割!J$3,発注_送信ファイル_項目分割!J$4)) | K25: =IF(発注_送信ファイル!$D23="","",MIDB(発注_送信ファイル!$D23,発注_送信ファイル_項目分割!K$3,発注_送信ファイル_項目分割!K$4)) | ... EF25: =IF(発注_送信ファイル!$D23="","",MIDB(発注_送信ファイル!$D23,発注_送信ファイル_項目分割!EF$3,発注_送信ファイル_項目分割!EF$4))
B26: =ROW()-6 -> 20 | C26: =IF(発注_送信ファイル!C24="","",発注_送信ファイル!C24) | D26: =IF(発注_送信ファイル!$D24="","",MIDB(発注_送信ファイル!$D24,発注_送信ファイル_項目分割!D$3,発注_送信ファイル_項目分割!D$4)) | E26: =IF(発注_送信ファイル!$D24="","",MIDB(発注_送信ファイル!$D24,発注_送信ファイル_項目分割!E$3,発注_送信ファイル_項目分割!E$4)) | F26: =IF(発注_送信ファイル!$D24="","",MIDB(発注_送信ファイル!$D24,発注_送信ファイル_項目分割!F$3,発注_送信ファイル_項目分割!F$4)) | G26: =IF(発注_送信ファイル!$D24="","",MIDB(発注_送信ファイル!$D24,発注_送信ファイル_項目分割!G$3,発注_送信ファイル_項目分割!G$4)) | H26: =IF(発注_送信ファイル!$D24="","",MIDB(発注_送信ファイル!$D24,発注_送信ファイル_項目分割!H$3,発注_送信ファイル_項目分割!H$4)) | I26: =IF(発注_送信ファイル!$D24="","",MIDB(発注_送信ファイル!$D24,発注_送信ファイル_項目分割!I$3,発注_送信ファイル_項目分割!I$4)) | J26: =IF(発注_送信ファイル!$D24="","",MIDB(発注_送信ファイル!$D24,発注_送信ファイル_項目分割!J$3,発注_送信ファイル_項目分割!J$4)) | K26: =IF(発注_送信ファイル!$D24="","",MIDB(発注_送信ファイル!$D24,発注_送信ファイル_項目分割!K$3,発注_送信ファイル_項目分割!K$4)) | ... EF26: =IF(発注_送信ファイル!$D24="","",MIDB(発注_送信ファイル!$D24,発注_送信ファイル_項目分割!EF$3,発注_送信ファイル_項目分割!EF$4))
B27: =ROW()-6 -> 21 | C27: =IF(発注_送信ファイル!C25="","",発注_送信ファイル!C25) | D27: =IF(発注_送信ファイル!$D25="","",MIDB(発注_送信ファイル!$D25,発注_送信ファイル_項目分割!D$3,発注_送信ファイル_項目分割!D$4)) | E27: =IF(発注_送信ファイル!$D25="","",MIDB(発注_送信ファイル!$D25,発注_送信ファイル_項目分割!E$3,発注_送信ファイル_項目分割!E$4)) | F27: =IF(発注_送信ファイル!$D25="","",MIDB(発注_送信ファイル!$D25,発注_送信ファイル_項目分割!F$3,発注_送信ファイル_項目分割!F$4)) | G27: =IF(発注_送信ファイル!$D25="","",MIDB(発注_送信ファイル!$D25,発注_送信ファイル_項目分割!G$3,発注_送信ファイル_項目分割!G$4)) | H27: =IF(発注_送信ファイル!$D25="","",MIDB(発注_送信ファイル!$D25,発注_送信ファイル_項目分割!H$3,発注_送信ファイル_項目分割!H$4)) | I27: =IF(発注_送信ファイル!$D25="","",MIDB(発注_送信ファイル!$D25,発注_送信ファイル_項目分割!I$3,発注_送信ファイル_項目分割!I$4)) | J27: =IF(発注_送信ファイル!$D25="","",MIDB(発注_送信ファイル!$D25,発注_送信ファイル_項目分割!J$3,発注_送信ファイル_項目分割!J$4)) | K27: =IF(発注_送信ファイル!$D25="","",MIDB(発注_送信ファイル!$D25,発注_送信ファイル_項目分割!K$3,発注_送信ファイル_項目分割!K$4)) | ... EF27: =IF(発注_送信ファイル!$D25="","",MIDB(発注_送信ファイル!$D25,発注_送信ファイル_項目分割!EF$3,発注_送信ファイル_項目分割!EF$4))
B28: =ROW()-6 -> 22 | C28: =IF(発注_送信ファイル!C26="","",発注_送信ファイル!C26) | D28: =IF(発注_送信ファイル!$D26="","",MIDB(発注_送信ファイル!$D26,発注_送信ファイル_項目分割!D$3,発注_送信ファイル_項目分割!D$4)) | E28: =IF(発注_送信ファイル!$D26="","",MIDB(発注_送信ファイル!$D26,発注_送信ファイル_項目分割!E$3,発注_送信ファイル_項目分割!E$4)) | F28: =IF(発注_送信ファイル!$D26="","",MIDB(発注_送信ファイル!$D26,発注_送信ファイル_項目分割!F$3,発注_送信ファイル_項目分割!F$4)) | G28: =IF(発注_送信ファイル!$D26="","",MIDB(発注_送信ファイル!$D26,発注_送信ファイル_項目分割!G$3,発注_送信ファイル_項目分割!G$4)) | H28: =IF(発注_送信ファイル!$D26="","",MIDB(発注_送信ファイル!$D26,発注_送信ファイル_項目分割!H$3,発注_送信ファイル_項目分割!H$4)) | I28: =IF(発注_送信ファイル!$D26="","",MIDB(発注_送信ファイル!$D26,発注_送信ファイル_項目分割!I$3,発注_送信ファイル_項目分割!I$4)) | J28: =IF(発注_送信ファイル!$D26="","",MIDB(発注_送信ファイル!$D26,発注_送信ファイル_項目分割!J$3,発注_送信ファイル_項目分割!J$4)) | K28: =IF(発注_送信ファイル!$D26="","",MIDB(発注_送信ファイル!$D26,発注_送信ファイル_項目分割!K$3,発注_送信ファイル_項目分割!K$4)) | ... EF28: =IF(発注_送信ファイル!$D26="","",MIDB(発注_送信ファイル!$D26,発注_送信ファイル_項目分割!EF$3,発注_送信ファイル_項目分割!EF$4))
B29: =ROW()-6 -> 23 | C29: =IF(発注_送信ファイル!C27="","",発注_送信ファイル!C27) | D29: =IF(発注_送信ファイル!$D27="","",MIDB(発注_送信ファイル!$D27,発注_送信ファイル_項目分割!D$3,発注_送信ファイル_項目分割!D$4)) | E29: =IF(発注_送信ファイル!$D27="","",MIDB(発注_送信ファイル!$D27,発注_送信ファイル_項目分割!E$3,発注_送信ファイル_項目分割!E$4)) | F29: =IF(発注_送信ファイル!$D27="","",MIDB(発注_送信ファイル!$D27,発注_送信ファイル_項目分割!F$3,発注_送信ファイル_項目分割!F$4)) | G29: =IF(発注_送信ファイル!$D27="","",MIDB(発注_送信ファイル!$D27,発注_送信ファイル_項目分割!G$3,発注_送信ファイル_項目分割!G$4)) | H29: =IF(発注_送信ファイル!$D27="","",MIDB(発注_送信ファイル!$D27,発注_送信ファイル_項目分割!H$3,発注_送信ファイル_項目分割!H$4)) | I29: =IF(発注_送信ファイル!$D27="","",MIDB(発注_送信ファイル!$D27,発注_送信ファイル_項目分割!I$3,発注_送信ファイル_項目分割!I$4)) | J29: =IF(発注_送信ファイル!$D27="","",MIDB(発注_送信ファイル!$D27,発注_送信ファイル_項目分割!J$3,発注_送信ファイル_項目分割!J$4)) | K29: =IF(発注_送信ファイル!$D27="","",MIDB(発注_送信ファイル!$D27,発注_送信ファイル_項目分割!K$3,発注_送信ファイル_項目分割!K$4)) | ... EF29: =IF(発注_送信ファイル!$D27="","",MIDB(発注_送信ファイル!$D27,発注_送信ファイル_項目分割!EF$3,発注_送信ファイル_項目分割!EF$4))
... B48: =ROW()-6 -> 42 | C48: =IF(発注_送信ファイル!C46="","",発注_送信ファイル!C46) | D48: =IF(発注_送信ファイル!$D46="","",MIDB(発注_送信ファイル!$D46,発注_送信ファイル_項目分割!D$3,発注_送信ファイル_項目分割!D$4)) | E48: =IF(発注_送信ファイル!$D46="","",MIDB(発注_送信ファイル!$D46,発注_送信ファイル_項目分割!E$3,発注_送信ファイル_項目分割!E$4)) | F48: =IF(発注_送信ファイル!$D46="","",MIDB(発注_送信ファイル!$D46,発注_送信ファイル_項目分割!F$3,発注_送信ファイル_項目分割!F$4)) | G48: =IF(発注_送信ファイル!$D46="","",MIDB(発注_送信ファイル!$D46,発注_送信ファイル_項目分割!G$3,発注_送信ファイル_項目分割!G$4)) | H48: =IF(発注_送信ファイル!$D46="","",MIDB(発注_送信ファイル!$D46,発注_送信ファイル_項目分割!H$3,発注_送信ファイル_項目分割!H$4)) | I48: =IF(発注_送信ファイル!$D46="","",MIDB(発注_送信ファイル!$D46,発注_送信ファイル_項目分割!I$3,発注_送信ファイル_項目分割!I$4)) | J48: =IF(発注_送信ファイル!$D46="","",MIDB(発注_送信ファイル!$D46,発注_送信ファイル_項目分割!J$3,発注_送信ファイル_項目分割!J$4)) | K48: =IF(発注_送信ファイル!$D46="","",MIDB(発注_送信ファイル!$D46,発注_送信ファイル_項目分割!K$3,発注_送信ファイル_項目分割!K$4)) | ... EF48: =IF(発注_送信ファイル!$D46="","",MIDB(発注_送信ファイル!$D46,発注_送信ファイル_項目分割!EF$3,発注_送信ファイル_項目分割!EF$4))
