Workbook

Sheet 発注_連携ファイル
A1: 発注_連携ファイル出力確認
B3: No. | C3: テストNo | D3: 共通フォーマットデータ
C4: 【テスト結果】 | D4: TUGA050S02001を以下に貼り付ける
B5: =B4+1 -> 1 | C5: No34,35,39 | D5: S1000537160000861410308024 1870089 870089 20110401 0369B 0369B ﾁ7ｻ B00344A21 0Y349333 IG98D IG98D ■■モ■■穂■■第■■場 VM77A ■■ノ■■㈱■■橋■■ ■■県■■市■■相■■９■ 11111 1131121161 2011051625.0000 352.0000 8800.000 1.0000 KG 0.000 XT01CP XX XX 920100 25.000 2 キログラム 2 11 1 N 1 20110506 102943 0631209
B6: =B5+1 -> 2 | C6: No34,35,39 | D6: S1000536800000861410308024 1815791 815791 20110322 0369B 0369B ﾁ7ｻ B00344551 CI94A CI94A ■■化■■業■ 8359C 8359C ■■井■■ 9773A ■■化■■ ■■井■■ ■■県■■井■■幸■■－■■２■ 11611 1161111121 20110511300.0000 349.0000 104700.000 12.0000 KG 0.000 SANC-I-D XXNXX XX-XX 52485Z 25.000 2 キログラム 2 11 午前着希望 1 N 1 20110506 093746 0631209
B7: =B6+1 -> 3 | C7: No34,35,39 | D7: S1000536830000861410308024 1815791 815791 20110322 0369B 0369B ﾁ7ｻ B00344591 CI94A CI94A ■■化■■業■ 8359C 8359C ■■井■■ AUJ1A ■■化■■業■ ■■県■■市■■２■■－■ 11411 1161141131 20110511300.0000 349.0000 104700.000 12.0000 KG 0.000 SANC-I-D XXNXX XX-XX 52485Z 25.000 2 キログラム 2 11 午前着希望 1 N 1 20110506 093918 0631209
B8: =B7+1 -> 4 | C8: No34,35,39 | D8: S10005372000008614102920270525713911 1905100 905100 20110201 0369A 0369A ﾁ7ｻ B00344AE1 2258338 8878A 8878A ■■ザ■■工 2627C 2627C ■■商■■大■■店 8878A ■■ザ■■工 ■■県■■部■■輪■■８■■ 11211 1161111121 20110523800.0000 510.0000 408000.000 32.0000 KG 0.000 F5350D1N XXSXX5XX0XX1 25.000 2 キログラム 2 11 1 N 1 20110506 103739 0631209
B9: =B8+1 -> 5 | C9: No34,35,39 | D9: S1000537330000861430104010 1606430 606430 20110310 0369C 0369C ﾁ6ｻ B00344D41 IS0501 DY86A DY86A ■■化■■業■ LJ32A ■■化■■ ■■県■■山■■石■■今■■１■■ 11911 1131131151 20110512600.0000 444.0000 266400.000 24.0000 KG 0.000 330 XXSXX3X STD 25.000 2 キログラム 2 11 1 N 1 20110506 105700 0631209
B10: =B9+1 -> 6 | C10: No34,35,39 | D10: S1000536840000861410308024 1837647 837647 20110322 0369B 0369B ﾁ7ｻ B003445C1 CI94A CI94A ■■化■■業■ 8359C 8359C ■■井■■ AUJ1A ■■化■■業■ ■■県■■市■■２■■－■ 11411 1161141131 20110513450.0000 418.0000 188100.000 18.0000 KG 0.000 V1-250E-3 XXXXX5XX XX 10802Z 25.000 2 キログラム 2 11 1 N 1 20110506 094028 0631209
B11: =B10+1 -> 7 | C11: No34,35,39
B12: =B11+1 -> 8 | C12: No34,35,39
B13: =B12+1 -> 9 | C13: No34,35,39
B14: =B13+1 -> 10 | C14: No34,35,39
B15: =B14+1 -> 11
B16: =B15+1 -> 12
B17: =B16+1 -> 13
B18: =B17+1 -> 14
B19: =B18+1 -> 15
B20: =B19+1 -> 16
B21: =B20+1 -> 17
B22: =B21+1 -> 18
B23: =B22+1 -> 19
B24: =B23+1 -> 20
B25: =B24+1 -> 21
B26: =B25+1 -> 22
... B46: =B45+1 -> 42

Sheet 発注_連携ファイル_項目分割
A1: 項目分割
C3: 開始位置 | D3: 1 | E3: 11 | F3: 17 | G3: 22 | H3: 27 | I3: 42 | J3: 43 | K3: 58 | L3: 68 | M3: 76 | N3: 77 | O3: 89 | P3: 101 | Q3: 113 | R3: 143 | S3: 151 | T3: 153 | U3: 173 | V3: 196 | W3: 199 | X3: 214 | Y3: 229 | Z3: 269 | AA3: 309 | AB3: 343 | AC3: 358 | AD3: 373 | AE3: 413 | AF3: 453 | AG3: 493 | AH3: 508 | AI3: 523 | AJ3: 563 | AK3: 613 | AL3: 713 | AM3: 813 | AN3: 863 | AO3: 871 | AP3: 921 | AQ3: 971 | AR3: 978 | AS3: 993 | AT3: 1008 | AU3: 1019 | AV3: 1027 | AW3: 1039 | AX3: 1056 | AY3: 1072 | AZ3: 1086 | BA3: 1089 | BB3: 1090 | BC3: 1103 | BD3: 1133 | BE3: 1233 | BF3: 1333 | BG3: 1353 | BH3: 1364 | BI3: 1369 | BJ3: 1409 | BK3: 1414 | BL3: 1454 | BM3: 1459 | BN3: 1499 | BO3: 1509 | BP3: 1553 | BQ3: 1585 | BR3: 1605 | BS3: 1645 | BT3: 1675 | BU3: 1719 | BV3: 1739 | BW3: 1744 | BX3: 1759 | BY3: 1760 | BZ3: 1772 | CA3: 1782 | CB3: 1802 | CC3: 1803 | CD3: 1804 | CE3: 1805 | CF3: 1820 | CG3: 1821 | CH3: 1822 | CI3: 1823 | CJ3: 1825 | CK3: 1826 | CL3: 1856 | CM3: 1886 | CN3: 2086 | CO3: 2094 | CP3: 2102 | CQ3: 2108 | CR3: 2114 | CS3: 2115 | CT3: 2125
C4: 桁数 | D4: 10 | E4: 6 | F4: 5 | G4: 5 | H4: 15 | I4: 1 | J4: 15 | K4: 10 | L4: 8 | M4: 1 | N4: 12 | O4: 12 | P4: 12 | Q4: 30 | R4: 8 | S4: 2 | T4: 20 | U4: 23 | V4: 3 | W4: 15 | X4: 15 | Y4: 40 | Z4: 40 | AA4: 34 | AB4: 15 | AC4: 15 | AD4: 40 | AE4: 40 | AF4: 40 | AG4: 15 | AH4: 15 | AI4: 40 | AJ4: 50 | AK4: 100 | AL4: 100 | AM4: 50 | AN4: 8 | AO4: 50 | AP4: 50 | AQ4: 7 | AR4: 15 | AS4: 15 | AT4: 11 | AU4: 8 | AV4: 12 | AW4: 17 | AX4: 16 | AY4: 14 | AZ4: 3 | BA4: 1 | BB4: 13 | BC4: 30 | BD4: 100 | BE4: 100 | BF4: 20 | BG4: 11 | BH4: 5 | BI4: 40 | BJ4: 5 | BK4: 40 | BL4: 5 | BM4: 40 | BN4: 10 | BO4: 44 | BP4: 32 | BQ4: 20 | BR4: 40 | BS4: 30 | BT4: 44 | BU4: 20 | BV4: 5 | BW4: 15 | BX4: 1 | BY4: 12 | BZ4: 10 | CA4: 20 | CB4: 1 | CC4: 1 | CD4: 1 | CE4: 15 | CF4: 1 | CG4: 1 | CH4: 1 | CI4: 2 | CJ4: 1 | CK4: 30 | CL4: 30 | CM4: 200 | CN4: 8 | CO4: 8 | CP4: 6 | CQ4: 6 | CR4: 1 | CS4: 10 | CT4: 2
B5: No. | C5: テストNo | D5: 送信シーケンスNO | E5: データ交換ID | F5: 仕入先組織コード | G5: 発注入力担当者コード | H5: 発注担当者FAX番号 | I5: 発注処理種別 | J5: EDI_取引条件番号 | K5: EDI_契約番号 | L5: EDI_適用開始年月日 | M5: EDI_メーカ取引区分 | N5: EDI_メーカ発注者コード（送信用） | O5: EDI_メーカ受注者コード（送信用） | P5: EDI_メーカ支払者コード（送信用） | Q5: EDI_メーカ組織コード | R5: 発注番号 | S5: 発注行番号 | T5: EDI_メーカ受注番号 | U5: EDI_販売先注文番号 | V5: EDI_メーカ扱店コード | W5: EDI_メーカ需要家コード（送信用） | X5: EDI_メーカ需要家コード | Y5: EDI_メーカ需要家名(カナ) | Z5: EDI_メーカ需要家名(漢字) | AA5: EDI_メーカ需要家支店名(漢字) | AB5: EDI_メーカ２次店コード（送信用） | AC5: EDI_メーカ２次店コード | AD5: EDI_メーカ２次店名(カナ) | AE5: EDI_メーカ２次店名(漢字) | AF5: EDI_メーカ３次店名(漢字) | AG5: EDI_メーカ納入先コード（送信用） | AH5: EDI_メーカ納入先コード | AI5: EDI_メーカ納入先名(カナ) | AJ5: EDI_メーカ納入先名(漢字) | AK5: EDI_メーカ納入先住所(カナ) | AL5: EDI_メーカ納入先住所(漢字) | AM5: EDI_メーカ納入先支社名(漢字) | AN5: EDI_メーカ納入先都道府県 | AO5: EDI_メーカ納入先住所1 | AP5: EDI_メーカ納入先住所2 | AQ5: EDI_メーカ納入先郵便番号 | AR5: EDI_メーカ納入先電話番号 | AS5: EDI_メーカ納入先FAX番号 | AT5: EDI_メーカ納入先地区コード | AU5: 希望納期 | AV5: 発注数量 | AW5: 発注単価 | AX5: 発注金額 | AY5: EDI_個数 | AZ5: 仕入単位コード | BA5: EDI_口銭区分 | BB5: EDI_口銭単価 | BC5: EDI_メーカ商品コード | BD5: EDI_メーカ商品名(カナ) | BE5: EDI_メーカ商品名(漢字) | BF5: EDI_グレード | BG5: EDI_容量 | BH5: EDI_メーカ数量単位コード | BI5: EDI_メーカ数量単位名 | BJ5: EDI_メーカ単価単位コード | BK5: EDI_メーカ単価単位名 | BL5: EDI_メーカ荷姿コード | BM5: EDI_メーカ荷姿名(カナ) | BN5: EDI_納入コメント | BO5: EDI_発注コメント | BP5: EDI_納品コメント | BQ5: EDI_備考 | BR5: EDI_特記事項 | BS5: EDI_配送指示 | BT5: EDI_納入要件 | BU5: EDI_メーカ受注者情報 | BV5: EDI_メーカ受渡条件コード | BW5: EDI_決済条件 | BX5: EDI_緊急オーダーコード | BY5: EDI_輸送便コード | BZ5: EDI_納入希望時刻コード | CA5: EDI_納入希望時刻名称 | CB5: EDI_納入希望時刻条件コード | CC5: EDI_LOT NO条件コード | CD5: EDI_ロット区分 | CE5: EDI_ロット番号 | CF5: EDI_メーカ国内・輸出区分 | CG5: EDI_数量確定区分 | CH5: EDI_単価区分 | CI5: EDI_課税区分 | CJ5: EDI_オーダ区分 | CK5: EDI_予備欄 | CL5: EDI_予備欄(漢字) | CM5: IK自由使用欄1 | CN5: 登録年月日 | CO5: 修正年月日 | CP5: 発注入力時刻 | CQ5: 発注修正時刻 | CR5: 削除区分 | CS5: 処理受付番号 | CT5: FILLER
C6: =IF(発注_連携ファイル!C4="","",発注_連携ファイル!C4) -> 【テスト結果】 | D6: TUGA050S02001を以下に貼り付ける
B7: =ROW()-6 -> 1 | C7: =IF(発注_連携ファイル!C5="","",発注_連携ファイル!C5) -> No34,35,39 | D7: =IF(発注_連携ファイル!$D5="","",MIDB(発注_連携ファイル!$D5,発注_連携ファイル_項目分割!D$3,発注_連携ファイル_項目分割!D$4)) -> S100053716 | E7: =IF(発注_連携ファイル!$D5="","",MIDB(発注_連携ファイル!$D5,発注_連携ファイル_項目分割!E$3,発注_連携ファイル_項目分割!E$4)) -> 000086 | F7: =IF(発注_連携ファイル!$D5="","",MIDB(発注_連携ファイル!$D5,発注_連携ファイル_項目分割!F$3,発注_連携ファイル_項目分割!F$4)) -> 14103 | G7: =IF(発注_連携ファイル!$D5="","",MIDB(発注_連携ファイル!$D5,発注_連携ファイル_項目分割!G$3,発注_連携ファイル_項目分割!G$4)) -> 08024 | H7: =IF(発注_連携ファイル!$D5="","",MIDB(発注_連携ファイル!$D5,発注_連携ファイル_項目分割!H$3,発注_連携ファイル_項目分割!H$4)) | I7: =IF(発注_連携ファイル!$D5="","",MIDB(発注_連携ファイル!$D5,発注_連携ファイル_項目分割!I$3,発注_連携ファイル_項目分割!I$4)) -> 1 | J7: =IF(発注_連携ファイル!$D5="","",MIDB(発注_連携ファイル!$D5,発注_連携ファイル_項目分割!J$3,発注_連携ファイル_項目分割!J$4)) -> 870089 | K7: =IF(発注_連携ファイル!$D5="","",MIDB(発注_連携ファイル!$D5,発注_連携ファイル_項目分割!K$3,発注_連携ファイル_項目分割!K$4)) -> 870089 | ... CT7: =IF(発注_連携ファイル!$D5="","",MIDB(発注_連携ファイル!$D5,発注_連携ファイル_項目分割!CT$3,発注_連携ファイル_項目分割!CT$4))
B8: =ROW()-6 -> 2 | C8: =IF(発注_連携ファイル!C6="","",発注_連携ファイル!C6) -> No34,35,39 | D8: =IF(発注_連携ファイル!$D6="","",MIDB(発注_連携ファイル!$D6,発注_連携ファイル_項目分割!D$3,発注_連携ファイル_項目分割!D$4)) -> S100053680 | E8: =IF(発注_連携ファイル!$D6="","",MIDB(発注_連携ファイル!$D6,発注_連携ファイル_項目分割!E$3,発注_連携ファイル_項目分割!E$4)) -> 000086 | F8: =IF(発注_連携ファイル!$D6="","",MIDB(発注_連携ファイル!$D6,発注_連携ファイル_項目分割!F$3,発注_連携ファイル_項目分割!F$4)) -> 14103 | G8: =IF(発注_連携ファイル!$D6="","",MIDB(発注_連携ファイル!$D6,発注_連携ファイル_項目分割!G$3,発注_連携ファイル_項目分割!G$4)) -> 08024 | H8: =IF(発注_連携ファイル!$D6="","",MIDB(発注_連携ファイル!$D6,発注_連携ファイル_項目分割!H$3,発注_連携ファイル_項目分割!H$4)) | I8: =IF(発注_連携ファイル!$D6="","",MIDB(発注_連携ファイル!$D6,発注_連携ファイル_項目分割!I$3,発注_連携ファイル_項目分割!I$4)) -> 1 | J8: =IF(発注_連携ファイル!$D6="","",MIDB(発注_連携ファイル!$D6,発注_連携ファイル_項目分割!J$3,発注_連携ファイル_項目分割!J$4)) -> 815791 | K8: =IF(発注_連携ファイル!$D6="","",MIDB(発注_連携ファイル!$D6,発注_連携ファイル_項目分割!K$3,発注_連携ファイル_項目分割!K$4)) -> 815791 | ... CT8: =IF(発注_連携ファイル!$D6="","",MIDB(発注_連携ファイル!$D6,発注_連携ファイル_項目分割!CT$3,発注_連携ファイル_項目分割!CT$4))
B9: =ROW()-6 -> 3 | C9: =IF(発注_連携ファイル!C7="","",発注_連携ファイル!C7) -> No34,35,39 | D9: =IF(発注_連携ファイル!$D7="","",MIDB(発注_連携ファイル!$D7,発注_連携ファイル_項目分割!D$3,発注_連携ファイル_項目分割!D$4)) -> S100053683 | E9: =IF(発注_連携ファイル!$D7="","",MIDB(発注_連携ファイル!$D7,発注_連携ファイル_項目分割!E$3,発注_連携ファイル_項目分割!E$4)) -> 000086 | F9: =IF(発注_連携ファイル!$D7="","",MIDB(発注_連携ファイル!$D7,発注_連携ファイル_項目分割!F$3,発注_連携ファイル_項目分割!F$4)) -> 14103 | G9: =IF(発注_連携ファイル!$D7="","",MIDB(発注_連携ファイル!$D7,発注_連携ファイル_項目分割!G$3,発注_連携ファイル_項目分割!G$4)) -> 08024 | H9: =IF(発注_連携ファイル!$D7="","",MIDB(発注_連携ファイル!$D7,発注_連携ファイル_項目分割!H$3,発注_連携ファイル_項目分割!H$4)) | I9: =IF(発注_連携ファイル!$D7="","",MIDB(発注_連携ファイル!$D7,発注_連携ファイル_項目分割!I$3,発注_連携ファイル_項目分割!I$4)) -> 1 | J9: =IF(発注_連携ファイル!$D7="","",MIDB(発注_連携ファイル!$D7,発注_連携ファイル_項目分割!J$3,発注_連携ファイル_項目分割!J$4)) -> 815791 | K9: =IF(発注_連携ファイル!$D7="","",MIDB(発注_連携ファイル!$D7,発注_連携ファイル_項目分割!K$3,発注_連携ファイル_項目分割!K$4)) -> 815791 | ... CT9: =IF(発注_連携ファイル!$D7="","",MIDB(発注_連携ファイル!$D7,発注_連携ファイル_項目分割!CT$3,発注_連携ファイル_項目分割!CT$4))
B10: =ROW()-6 -> 4 | C10: =IF(発注_連携ファイル!C8="","",発注_連携ファイル!C8) -> No34,35,39 | D10: =IF(発注_連携ファイル!$D8="","",MIDB(発注_連携ファイル!$D8,発注_連携ファイル_項目分割!D$3,発注_連携ファイル_項目分割!D$4)) -> S100053720 | E10: =IF(発注_連携ファイル!$D8="","",MIDB(発注_連携ファイル!$D8,発注_連携ファイル_項目分割!E$3,発注_連携ファイル_項目分割!E$4)) -> 000086 | F10: =IF(発注_連携ファイル!$D8="","",MIDB(発注_連携ファイル!$D8,発注_連携ファイル_項目分割!F$3,発注_連携ファイル_項目分割!F$4)) -> 14102 | G10: =IF(発注_連携ファイル!$D8="","",MIDB(発注_連携ファイル!$D8,発注_連携ファイル_項目分割!G$3,発注_連携ファイル_項目分割!G$4)) -> 92027 | H10: =IF(発注_連携ファイル!$D8="","",MIDB(発注_連携ファイル!$D8,発注_連携ファイル_項目分割!H$3,発注_連携ファイル_項目分割!H$4)) -> 0525713911 | I10: =IF(発注_連携ファイル!$D8="","",MIDB(発注_連携ファイル!$D8,発注_連携ファイル_項目分割!I$3,発注_連携ファイル_項目分割!I$4)) -> 1 | J10: =IF(発注_連携ファイル!$D8="","",MIDB(発注_連携ファイル!$D8,発注_連携ファイル_項目分割!J$3,発注_連携ファイル_項目分割!J$4)) -> 905100 | K10: =IF(発注_連携ファイル!$D8="","",MIDB(発注_連携ファイル!$D8,発注_連携ファイル_項目分割!K$3,発注_連携ファイル_項目分割!K$4)) -> 905100 | ... CT10: =IF(発注_連携ファイル!$D8="","",MIDB(発注_連携ファイル!$D8,発注_連携ファイル_項目分割!CT$3,発注_連携ファイル_項目分割!CT$4))
B11: =ROW()-6 -> 5 | C11: =IF(発注_連携ファイル!C9="","",発注_連携ファイル!C9) -> No34,35,39 | D11: =IF(発注_連携ファイル!$D9="","",MIDB(発注_連携ファイル!$D9,発注_連携ファイル_項目分割!D$3,発注_連携ファイル_項目分割!D$4)) -> S100053733 | E11: =IF(発注_連携ファイル!$D9="","",MIDB(発注_連携ファイル!$D9,発注_連携ファイル_項目分割!E$3,発注_連携ファイル_項目分割!E$4)) -> 000086 | F11: =IF(発注_連携ファイル!$D9="","",MIDB(発注_連携ファイル!$D9,発注_連携ファイル_項目分割!F$3,発注_連携ファイル_項目分割!F$4)) -> 14301 | G11: =IF(発注_連携ファイル!$D9="","",MIDB(発注_連携ファイル!$D9,発注_連携ファイル_項目分割!G$3,発注_連携ファイル_項目分割!G$4)) -> 04010 | H11: =IF(発注_連携ファイル!$D9="","",MIDB(発注_連携ファイル!$D9,発注_連携ファイル_項目分割!H$3,発注_連携ファイル_項目分割!H$4)) | I11: =IF(発注_連携ファイル!$D9="","",MIDB(発注_連携ファイル!$D9,発注_連携ファイル_項目分割!I$3,発注_連携ファイル_項目分割!I$4)) -> 1 | J11: =IF(発注_連携ファイル!$D9="","",MIDB(発注_連携ファイル!$D9,発注_連携ファイル_項目分割!J$3,発注_連携ファイル_項目分割!J$4)) -> 606430 | K11: =IF(発注_連携ファイル!$D9="","",MIDB(発注_連携ファイル!$D9,発注_連携ファイル_項目分割!K$3,発注_連携ファイル_項目分割!K$4)) -> 606430 | ... CT11: =IF(発注_連携ファイル!$D9="","",MIDB(発注_連携ファイル!$D9,発注_連携ファイル_項目分割!CT$3,発注_連携ファイル_項目分割!CT$4))
B12: =ROW()-6 -> 6 | C12: =IF(発注_連携ファイル!C10="","",発注_連携ファイル!C10) -> No34,35,39 | D12: =IF(発注_連携ファイル!$D10="","",MIDB(発注_連携ファイル!$D10,発注_連携ファイル_項目分割!D$3,発注_連携ファイル_項目分割!D$4)) -> S100053684 | E12: =IF(発注_連携ファイル!$D10="","",MIDB(発注_連携ファイル!$D10,発注_連携ファイル_項目分割!E$3,発注_連携ファイル_項目分割!E$4)) -> 000086 | F12: =IF(発注_連携ファイル!$D10="","",MIDB(発注_連携ファイル!$D10,発注_連携ファイル_項目分割!F$3,発注_連携ファイル_項目分割!F$4)) -> 14103 | G12: =IF(発注_連携ファイル!$D10="","",MIDB(発注_連携ファイル!$D10,発注_連携ファイル_項目分割!G$3,発注_連携ファイル_項目分割!G$4)) -> 08024 | H12: =IF(発注_連携ファイル!$D10="","",MIDB(発注_連携ファイル!$D10,発注_連携ファイル_項目分割!H$3,発注_連携ファイル_項目分割!H$4)) | I12: =IF(発注_連携ファイル!$D10="","",MIDB(発注_連携ファイル!$D10,発注_連携ファイル_項目分割!I$3,発注_連携ファイル_項目分割!I$4)) -> 1 | J12: =IF(発注_連携ファイル!$D10="","",MIDB(発注_連携ファイル!$D10,発注_連携ファイル_項目分割!J$3,発注_連携ファイル_項目分割!J$4)) -> 837647 | K12: =IF(発注_連携ファイル!$D10="","",MIDB(発注_連携ファイル!$D10,発注_連携ファイル_項目分割!K$3,発注_連携ファイル_項目分割!K$4)) -> 837647 | ... CT12: =IF(発注_連携ファイル!$D10="","",MIDB(発注_連携ファイル!$D10,発注_連携ファイル_項目分割!CT$3,発注_連携ファイル_項目分割!CT$4))
B13: =ROW()-6 -> 7 | C13: =IF(発注_連携ファイル!C11="","",発注_連携ファイル!C11) -> No34,35,39 | D13: =IF(発注_連携ファイル!$D11="","",MIDB(発注_連携ファイル!$D11,発注_連携ファイル_項目分割!D$3,発注_連携ファイル_項目分割!D$4)) | E13: =IF(発注_連携ファイル!$D11="","",MIDB(発注_連携ファイル!$D11,発注_連携ファイル_項目分割!E$3,発注_連携ファイル_項目分割!E$4)) | F13: =IF(発注_連携ファイル!$D11="","",MIDB(発注_連携ファイル!$D11,発注_連携ファイル_項目分割!F$3,発注_連携ファイル_項目分割!F$4)) | G13: =IF(発注_連携ファイル!$D11="","",MIDB(発注_連携ファイル!$D11,発注_連携ファイル_項目分割!G$3,発注_連携ファイル_項目分割!G$4)) | H13: =IF(発注_連携ファイル!$D11="","",MIDB(発注_連携ファイル!$D11,発注_連携ファイル_項目分割!H$3,発注_連携ファイル_項目分割!H$4)) | I13: =IF(発注_連携ファイル!$D11="","",MIDB(発注_連携ファイル!$D11,発注_連携ファイル_項目分割!I$3,発注_連携ファイル_項目分割!I$4)) | J13: =IF(発注_連携ファイル!$D11="","",MIDB(発注_連携ファイル!$D11,発注_連携ファイル_項目分割!J$3,発注_連携ファイル_項目分割!J$4)) | K13: =IF(発注_連携ファイル!$D11="","",MIDB(発注_連携ファイル!$D11,発注_連携ファイル_項目分割!K$3,発注_連携ファイル_項目分割!K$4)) | ... CT13: =IF(発注_連携ファイル!$D11="","",MIDB(発注_連携ファイル!$D11,発注_連携ファイル_項目分割!CT$3,発注_連携ファイル_項目分割!CT$4))
B14: =ROW()-6 -> 8 | C14: =IF(発注_連携ファイル!C12="","",発注_連携ファイル!C12) -> No34,35,39 | D14: =IF(発注_連携ファイル!$D12="","",MIDB(発注_連携ファイル!$D12,発注_連携ファイル_項目分割!D$3,発注_連携ファイル_項目分割!D$4)) | E14: =IF(発注_連携ファイル!$D12="","",MIDB(発注_連携ファイル!$D12,発注_連携ファイル_項目分割!E$3,発注_連携ファイル_項目分割!E$4)) | F14: =IF(発注_連携ファイル!$D12="","",MIDB(発注_連携ファイル!$D12,発注_連携ファイル_項目分割!F$3,発注_連携ファイル_項目分割!F$4)) | G14: =IF(発注_連携ファイル!$D12="","",MIDB(発注_連携ファイル!$D12,発注_連携ファイル_項目分割!G$3,発注_連携ファイル_項目分割!G$4)) | H14: =IF(発注_連携ファイル!$D12="","",MIDB(発注_連携ファイル!$D12,発注_連携ファイル_項目分割!H$3,発注_連携ファイル_項目分割!H$4)) | I14: =IF(発注_連携ファイル!$D12="","",MIDB(発注_連携ファイル!$D12,発注_連携ファイル_項目分割!I$3,発注_連携ファイル_項目分割!I$4)) | J14: =IF(発注_連携ファイル!$D12="","",MIDB(発注_連携ファイル!$D12,発注_連携ファイル_項目分割!J$3,発注_連携ファイル_項目分割!J$4)) | K14: =IF(発注_連携ファイル!$D12="","",MIDB(発注_連携ファイル!$D12,発注_連携ファイル_項目分割!K$3,発注_連携ファイル_項目分割!K$4)) | ... CT14: =IF(発注_連携ファイル!$D12="","",MIDB(発注_連携ファイル!$D12,発注_連携ファイル_項目分割!CT$3,発注_連携ファイル_項目分割!CT$4))
B15: =ROW()-6 -> 9 | C15: =IF(発注_連携ファイル!C13="","",発注_連携ファイル!C13) -> No34,35,39 | D15: =IF(発注_連携ファイル!$D13="","",MIDB(発注_連携ファイル!$D13,発注_連携ファイル_項目分割!D$3,発注_連携ファイル_項目分割!D$4)) | E15: =IF(発注_連携ファイル!$D13="","",MIDB(発注_連携ファイル!$D13,発注_連携ファイル_項目分割!E$3,発注_連携ファイル_項目分割!E$4)) | F15: =IF(発注_連携ファイル!$D13="","",MIDB(発注_連携ファイル!$D13,発注_連携ファイル_項目分割!F$3,発注_連携ファイル_項目分割!F$4)) | G15: =IF(発注_連携ファイル!$D13="","",MIDB(発注_連携ファイル!$D13,発注_連携ファイル_項目分割!G$3,発注_連携ファイル_項目分割!G$4)) | H15: =IF(発注_連携ファイル!$D13="","",MIDB(発注_連携ファイル!$D13,発注_連携ファイル_項目分割!H$3,発注_連携ファイル_項目分割!H$4)) | I15: =IF(発注_連携ファイル!$D13="","",MIDB(発注_連携ファイル!$D13,発注_連携ファイル_項目分割!I$3,発注_連携ファイル_項目分割!I$4)) | J15: =IF(発注_連携ファイル!$D13="","",MIDB(発注_連携ファイル!$D13,発注_連携ファイル_項目分割!J$3,発注_連携ファイル_項目分割!J$4)) | K15: =IF(発注_連携ファイル!$D13="","",MIDB(発注_連携ファイル!$D13,発注_連携ファイル_項目分割!K$3,発注_連携ファイル_項目分割!K$4)) | ... CT15: =IF(発注_連携ファイル!$D13="","",MIDB(発注_連携ファイル!$D13,発注_連携ファイル_項目分割!CT$3,発注_連携ファイル_項目分割!CT$4))
B16: =ROW()-6 -> 10 | C16: =IF(発注_連携ファイル!C14="","",発注_連携ファイル!C14) -> No34,35,39 | D16: =IF(発注_連携ファイル!$D14="","",MIDB(発注_連携ファイル!$D14,発注_連携ファイル_項目分割!D$3,発注_連携ファイル_項目分割!D$4)) | E16: =IF(発注_連携ファイル!$D14="","",MIDB(発注_連携ファイル!$D14,発注_連携ファイル_項目分割!E$3,発注_連携ファイル_項目分割!E$4)) | F16: =IF(発注_連携ファイル!$D14="","",MIDB(発注_連携ファイル!$D14,発注_連携ファイル_項目分割!F$3,発注_連携ファイル_項目分割!F$4)) | G16: =IF(発注_連携ファイル!$D14="","",MIDB(発注_連携ファイル!$D14,発注_連携ファイル_項目分割!G$3,発注_連携ファイル_項目分割!G$4)) | H16: =IF(発注_連携ファイル!$D14="","",MIDB(発注_連携ファイル!$D14,発注_連携ファイル_項目分割!H$3,発注_連携ファイル_項目分割!H$4)) | I16: =IF(発注_連携ファイル!$D14="","",MIDB(発注_連携ファイル!$D14,発注_連携ファイル_項目分割!I$3,発注_連携ファイル_項目分割!I$4)) | J16: =IF(発注_連携ファイル!$D14="","",MIDB(発注_連携ファイル!$D14,発注_連携ファイル_項目分割!J$3,発注_連携ファイル_項目分割!J$4)) | K16: =IF(発注_連携ファイル!$D14="","",MIDB(発注_連携ファイル!$D14,発注_連携ファイル_項目分割!K$3,発注_連携ファイル_項目分割!K$4)) | ... CT16: =IF(発注_連携ファイル!$D14="","",MIDB(発注_連携ファイル!$D14,発注_連携ファイル_項目分割!CT$3,発注_連携ファイル_項目分割!CT$4))
B17: =ROW()-6 -> 11 | C17: =IF(発注_連携ファイル!C15="","",発注_連携ファイル!C15) | D17: =IF(発注_連携ファイル!$D15="","",MIDB(発注_連携ファイル!$D15,発注_連携ファイル_項目分割!D$3,発注_連携ファイル_項目分割!D$4)) | E17: =IF(発注_連携ファイル!$D15="","",MIDB(発注_連携ファイル!$D15,発注_連携ファイル_項目分割!E$3,発注_連携ファイル_項目分割!E$4)) | F17: =IF(発注_連携ファイル!$D15="","",MIDB(発注_連携ファイル!$D15,発注_連携ファイル_項目分割!F$3,発注_連携ファイル_項目分割!F$4)) | G17: =IF(発注_連携ファイル!$D15="","",MIDB(発注_連携ファイル!$D15,発注_連携ファイル_項目分割!G$3,発注_連携ファイル_項目分割!G$4)) | H17: =IF(発注_連携ファイル!$D15="","",MIDB(発注_連携ファイル!$D15,発注_連携ファイル_項目分割!H$3,発注_連携ファイル_項目分割!H$4)) | I17: =IF(発注_連携ファイル!$D15="","",MIDB(発注_連携ファイル!$D15,発注_連携ファイル_項目分割!I$3,発注_連携ファイル_項目分割!I$4)) | J17: =IF(発注_連携ファイル!$D15="","",MIDB(発注_連携ファイル!$D15,発注_連携ファイル_項目分割!J$3,発注_連携ファイル_項目分割!J$4)) | K17: =IF(発注_連携ファイル!$D15="","",MIDB(発注_連携ファイル!$D15,発注_連携ファイル_項目分割!K$3,発注_連携ファイル_項目分割!K$4)) | ... CT17: =IF(発注_連携ファイル!$D15="","",MIDB(発注_連携ファイル!$D15,発注_連携ファイル_項目分割!CT$3,発注_連携ファイル_項目分割!CT$4))
B18: =ROW()-6 -> 12 | C18: =IF(発注_連携ファイル!C16="","",発注_連携ファイル!C16) | D18: =IF(発注_連携ファイル!$D16="","",MIDB(発注_連携ファイル!$D16,発注_連携ファイル_項目分割!D$3,発注_連携ファイル_項目分割!D$4)) | E18: =IF(発注_連携ファイル!$D16="","",MIDB(発注_連携ファイル!$D16,発注_連携ファイル_項目分割!E$3,発注_連携ファイル_項目分割!E$4)) | F18: =IF(発注_連携ファイル!$D16="","",MIDB(発注_連携ファイル!$D16,発注_連携ファイル_項目分割!F$3,発注_連携ファイル_項目分割!F$4)) | G18: =IF(発注_連携ファイル!$D16="","",MIDB(発注_連携ファイル!$D16,発注_連携ファイル_項目分割!G$3,発注_連携ファイル_項目分割!G$4)) | H18: =IF(発注_連携ファイル!$D16="","",MIDB(発注_連携ファイル!$D16,発注_連携ファイル_項目分割!H$3,発注_連携ファイル_項目分割!H$4)) | I18: =IF(発注_連携ファイル!$D16="","",MIDB(発注_連携ファイル!$D16,発注_連携ファイル_項目分割!I$3,発注_連携ファイル_項目分割!I$4)) | J18: =IF(発注_連携ファイル!$D16="","",MIDB(発注_連携ファイル!$D16,発注_連携ファイル_項目分割!J$3,発注_連携ファイル_項目分割!J$4)) | K18: =IF(発注_連携ファイル!$D16="","",MIDB(発注_連携ファイル!$D16,発注_連携ファイル_項目分割!K$3,発注_連携ファイル_項目分割!K$4)) | ... CT18: =IF(発注_連携ファイル!$D16="","",MIDB(発注_連携ファイル!$D16,発注_連携ファイル_項目分割!CT$3,発注_連携ファイル_項目分割!CT$4))
... B48: =ROW()-6 -> 42 | C48: =IF(発注_連携ファイル!C46="","",発注_連携ファイル!C46) | D48: =IF(発注_連携ファイル!$D46="","",MIDB(発注_連携ファイル!$D46,発注_連携ファイル_項目分割!D$3,発注_連携ファイル_項目分割!D$4)) | E48: =IF(発注_連携ファイル!$D46="","",MIDB(発注_連携ファイル!$D46,発注_連携ファイル_項目分割!E$3,発注_連携ファイル_項目分割!E$4)) | F48: =IF(発注_連携ファイル!$D46="","",MIDB(発注_連携ファイル!$D46,発注_連携ファイル_項目分割!F$3,発注_連携ファイル_項目分割!F$4)) | G48: =IF(発注_連携ファイル!$D46="","",MIDB(発注_連携ファイル!$D46,発注_連携ファイル_項目分割!G$3,発注_連携ファイル_項目分割!G$4)) | H48: =IF(発注_連携ファイル!$D46="","",MIDB(発注_連携ファイル!$D46,発注_連携ファイル_項目分割!H$3,発注_連携ファイル_項目分割!H$4)) | I48: =IF(発注_連携ファイル!$D46="","",MIDB(発注_連携ファイル!$D46,発注_連携ファイル_項目分割!I$3,発注_連携ファイル_項目分割!I$4)) | J48: =IF(発注_連携ファイル!$D46="","",MIDB(発注_連携ファイル!$D46,発注_連携ファイル_項目分割!J$3,発注_連携ファイル_項目分割!J$4)) | K48: =IF(発注_連携ファイル!$D46="","",MIDB(発注_連携ファイル!$D46,発注_連携ファイル_項目分割!K$3,発注_連携ファイル_項目分割!K$4)) | ... CT48: =IF(発注_連携ファイル!$D46="","",MIDB(発注_連携ファイル!$D46,発注_連携ファイル_項目分割!CT$3,発注_連携ファイル_項目分割!CT$4))
