Workbook
Name _1枚目: #REF!
Name _2枚目: #REF!
Name _3枚目: #REF!
Name _4枚目: #REF!
Name a: #REF!
Name AA: #REF!
Name b: #REF!
Name B_下: #REF!
Name B_下: #REF!
Name B_上: #REF!
Name B_上: #REF!
Name CSV項目編集仕様: #REF!
Name dd: #REF!
Name DS_下: #REF!
Name DS_下: #REF!
Name DS_上: #REF!
Name DS_上: #REF!
Name ＤＳ担当: #REF!
Name ＤＳ担当: #REF!
Name GUI名称: #REF!
Name ＩＤ: #REF!
Name ＩＤ: #REF!
Name IO: #REF!
Name IT項目: #REF!
Name kkk: #REF!
Name NULL: #REF!
Name NULL: #REF!
Name ON: #REF!
Name PCL_下: #REF!
Name PCL_下: #REF!
Name PCL_上: #REF!
Name PCL_上: #REF!
Name ＰＧ担当: #REF!
Name ＰＧ担当: #REF!
Name PT項目: #REF!
Name RI: #REF!
Name RI: #REF!
Name riyu: #REF!
Name riyu: #REF!
Name RYZ: #REF!
Name RYZ: #REF!
Name STEP_下: #REF!
Name STEP_下: #REF!
Name STEP_上: #REF!
Name STEP_上: #REF!
Name UD: #REF!
Name UD: #REF!
Name x: '８．【参考】日本触媒 OUTPUTファイルレイアウト'!x
Name x: [0]!x
Name カーソルキー移動↑↓←: #REF!
Name カテゴリ一覧: #REF!
Name カテゴリ一覧: #REF!
Name クラス名: #REF!
Name サブシステム名: #REF!
Name システム名: #REF!
Name セパレータ: #REF!
Name タイトル: #REF!
Name チェック: #REF!
Name チェック: #REF!
Name チェック実行アプリ: #REF!

Sheet 表紙
C2: 稲畑産業株式会社様
A8: EDIシステム
A10: バッチ処理設計書
A13: 日本触媒_請求確認
A17: - Ver.2.00 -
A22: 45769
A24: 富士通株式会社
V28: 承認 | AA28: 作成
AA29: 45769
AA30: FJ松枝

Sheet 変更履歴
A1: 稲畑産業 株式会社 | F1: バッチ処理設計書 | T1: 取引先名 | AH1: 取引先略称ID | AS1: カテゴリ名 | BB1: 作成者 | BF1: 作成日 | BJ1: 更新者 | BN1: 更新日
T3: 日本触媒 | AH3: NSB | AS3: 請求確認 | BB3: FJ松枝 | BF3: 45769
B7: № | D7: バージョン | H7: 変更日付 | L7: 変更者 | O7: 区分 | Q7: 変更管理番号 | U7: 変更箇所 | AF7: 変更内容 | AY7: 備考
B8: =ROW()-7 -> 1 | D8: 2.00 | H8: 45769 | L8: FJ松枝 | O8: 新規 | Q8: R60795 | AF8: 新規作成 | AY8: EDIミドル移行対応
B9: =ROW()-7 -> 2
B10: =ROW()-7 -> 3
B11: =ROW()-7 -> 4
B12: =ROW()-7 -> 5
B13: =ROW()-7 -> 6
B14: =ROW()-7 -> 7
B15: =ROW()-7 -> 8
B16: =ROW()-7 -> 9
B17: =ROW()-7 -> 10
B18: =ROW()-7 -> 11
B19: =ROW()-7 -> 12
B20: =ROW()-7 -> 13
... B52: =ROW()-7 -> 45

Sheet １．送受信情報
A1: 稲畑産業 株式会社 | E1: バッチ処理設計書 | O1: 取引先名 | X1: 取引先略称ID | AC1: カテゴリ名 | AG1: 作成者 | AJ1: 作成日 | AM1: 更新者 | AP1: 更新日
O3: =変更履歴!T3 -> 日本触媒 | X3: =変更履歴!AH3 -> NSB | AC3: =変更履歴!AS3 -> 請求確認 | AG3: =変更履歴!BB3 -> FJ松枝 | AJ3: =変更履歴!BF3 -> 45769
B6: ①送受信ファイル一覧
K7: S：スタート、H：ヘッダ、B：ボディ、T：トレーラ、E：エンド
C8: № | D8: フォーマット種類 | K8: ファイル構成 | P8: 0件データ伝送有無
C9: 1 | D9: JPCA | K9: H1+H2+B+T | P9: 無
B11: ②データの見方
C12: 発注データ | V12: H：ヘッダ | AD12: ※
C13: H：ヘッダ | V13: H：ヘッダ
C14: B：ボディ | V14: B：ボディ
C15: B：ボディ | V15: B：ボディ
C16: B：ボディ | V16: B：ボディ
V17: T：トレーラ | AD17: ※
Q19: ファイル構成 | V19: １レコード目：ヘッダ、ボディ、最終レコード：トレーラ
B20: ③抽出条件 | V20: （※NTS処理で付与）
C22: シート「２.機能」 ④機能詳細 (1) 送信対象データ作成 を参照。
B25: ④ヘッダ・トレーラ編集
C27: CII変換時にバッチでヘッダを付与。
B29: ⑤0件データ伝送仕様
C31: なし。

Sheet ２．機能
A1: 稲畑産業 株式会社 | E1: バッチ処理設計書 | O1: 取引先名 | X1: 取引先略称ID | AC1: カテゴリ名 | AG1: 作成者 | AJ1: 作成日 | AM1: 更新者 | AP1: 更新日
O3: =変更履歴!T3 -> 日本触媒 | X3: =変更履歴!AH3 -> NSB | AC3: =変更履歴!AS3 -> 請求確認 | AG3: =変更履歴!BB3 -> FJ松枝 | AJ3: =変更履歴!BF3 -> 45769
B6: ①目的
C8: ・共通処理_EDI送信_請求確認_データ抽出 にて、連携ファイル（NSBA130S02001）を取り込み、日本触媒向けの請求確認ファイルを作成する。
B10: ②機能概要
C12: ・連携ファイルを取り込み、送信対象データを抽出して、件数を確認する。
C13: ・送信対象データの件数 が0件ではない場合、取引先への送信ファイルを作成する。
C14: ・mplt_CMN_EDI送信DB_請求確認更新２を呼び出し、EDI送信DB_請求確認のEDI送信状況種別と処理受付番号、EDI受信DB_仕入先の請求確認作成種別を更新する。
B17: ③入出力情報
C19: [入力]
C20: テーブル名orファイル名 | M20: 抽出条件 | AE20: 使用目的
C21: 連携ファイル | M21: EDIサーバ：/PRD/Temp/NSBA130S02001（共通処理で作成） | AE21: 送信対象データの抽出
C23: 中間データ | M23: 以下の抽出条件を基に作成。 | AE23: 更新対象レコードのロック
M24: EDI送信DB_請求確認.ﾃﾞｰﾀ交換ID="001440"（日本触媒） | AE24: 送信シーケンスNOの抽出
M25: EDI送信DB_請求確認.EDI機能カテゴリ種別 = 'A130'（請求確認） | AE25: 受信シーケンスNOの抽出
M26: EDI送信DB_請求確認.EDI送信状況種別="1"（処理中）
M27: EDI送信DB_請求確認.削除区分＝"0"（有効）
M28: EDI送信DB_請求確認.送信データ削除区分＝"0"（送信対象）
M29: EDI送信DB_請求確認.受信SEQ番号 = EDI受信DB_仕入先.受信SEQ番号
C32: [出力]
C33: テーブル名orファイル名 | M33: 更新条件 | AE33: 使用目的
C34: 送信ファイル | M34: 以下の抽出条件を基に作成。 | AE34: 取引先への送信ファイル作成
M35: 連携ファイル.削除区分 = "0"（有効） かつ
M36: 連携ファイル.送信データ削除区分 = "0"（送信対象） かつ
M37: 連携ファイル.計上状況種別 = '0' ,'1' ,'2' ,'3' ,'4' ,'5'（※１）
C38: EDI送信DB_請求確認 | M38: 以下の更新条件を基に更新。 | AE38: 処理済フラグを設定
M39: 送信シーケンスNO = 中間データ.送信シーケンスNO | AE39: EDI送信状況種別="3"（処理済）
AE40: 処理受付番号=連携ファイル.処理受付番号
C41: EDI受信DB_仕入先 | M41: 以下の更新条件を基に更新。 | AE41: 作成済フラグを設定
M42: 受信SEQ番号=中間データ.受信SEQ番号 | AE42: 請求確認作成種別＝"2"（作成済）
C44: ※１ 計上状況種別
D45: 計上状況種別
D46: 0 | E46: 未確認
D47: 1 | E47: 計上済
D48: 2 | E48: 否認
D49: 3 | E49: 保留
D50: 4 | E50: 相殺
D51: 5 | E51: 計上取消
B55: ④機能詳細
C57: (1) 連携ファイルの取込
D59: 共通処理で作成された連携ファイル「NSBA130S02001」を取り込む。
D60: →ファイルパス：/EDIサーバ/PRD/Temp/NSBA130S02001
C63: (2) 送信対象データ作成
D65: ①連携ファイルから、送信対象データを取得する。
D67: 抽出条件：
E68: ・連携ファイル.削除区分 = '0'（有効）
E69: ・連携ファイル.送信データ削除区分 = '0'（送信対象）
E70: ・連携ファイル.計上状況種別 = '0' ,'1' ,'2' ,'3' ,'4' ,'5'（※１）
D72: ②送信対象データが存在する場合、取引先への送信ファイルを作成する。
E74: 1 | F74: 相手先別データの編集
F75: ①より取得した連携ファイルの相手先別データを「６．１．相手先別データレイアウト」の桁数ごとに分割し、各項目にマッピングする。
E77: 2 | F77: 取引先への送信ファイルの編集
F78: 再マッピングした相手先別データと連携ファイルを元に、「７．項目転送 (請求データ送信ファイル)」に従い、送信ファイルの項目にマッピングする。
E80: 3 | F80: 取引先への送信ファイルを作成
F81: 出力フォーマットは「５．OUTPUTファイルレイアウト(B) (送信ファイル）」シートを参照。
G82: 配置箇所：EDIサーバ\PRD\Temp\
G83: ファイル名:NSBA1301
C85: (3) EDI送信DB_請求確認のステータス更新（共通処理呼び出し）
D87: mplt_CMN_EDI送信DB_請求確認更新２ を呼び出し、以下の処理を行う。
E89: ①EDI送信DB_請求確認とEDI受信DB_仕入先より対象の中間ﾃﾞｰﾀをSELECT for Updateでレコードロックする
E90: 抽出条件：
F91: ・EDI送信DB_請求確認.ﾃﾞｰﾀ交換ID="001440"（日本触媒）
F92: ・EDI送信DB_請求確認.EDI機能カテゴリ種別 = 'A130'（請求確認）
F93: ・EDI送信DB_請求確認.EDI送信状況種別="1"（処理中）
F94: ・EDI送信DB_請求確認.削除区分＝"0"（有効）
F95: ・EDI送信DB_請求確認.送信データ削除区分＝"0"（送信対象）
F96: ・EDI送信DB_請求確認.受信SEQ番号 = EDI受信DB_仕入先.受信SEQ番号
E98: ②EDI送信DB_請求確認をEDI送信状況種別="3"（処理済）、処理受付番号=連携ファイル.処理受付番号 にUPDATEする。
E99: ※送信シーケンスNO = 中間データ.送信シーケンスNO
E101: ③中間データから以下の条件の受信シーケンスNOを抽出する。
E102: 抽出条件：
F103: ・中間データ.計上状況種別＝"1"（計上済） もしくは "4"（相殺）
E105: ④EDI受信DB_仕入先を請求確認作成種別＝"2"（作成済）にUPDATEする。
E106: ※受信シーケンスNO = 中間データ.受信シーケンスNO

Sheet ３．INPUTファイルレイアウト(B)（連携ファイル）
A6: ■ | B6: INPUTファイルレイアウト | E6: レコード長 | G6: 4143 | H6: 文字コード | J6: SJIS
A7: 【ボディレコード】
B8: 項目 | H8: 小数 | I8: 小数点 | J8: PAC/ | K8: Ｓｈｉｆｔ 有無 | L8: 開始
A9: № | B9: グループ | C9: 項 目 名（和名） | D9: 項目名（英名） | E9: 文字コード | F9: 型 | G9: 桁数 | H9: 桁数 | I9: 有無 | J9: UNPAC | L9: 位置 | M9: 備 考
A10: =ROW()-9 -> 1 | C10: 送信シーケンスNO | D10: SND_SEQ_NO | F10: 文字 | G10: 10 | L10: 1
A11: =ROW()-9 -> 2 | C11: 計上状況種別 | D11: KEIJO_JOKYO_SBT | F11: 数値 | G11: 1 | L11: 11
A12: =ROW()-9 -> 3 | C12: エラーメッセージ(否認理由) | D12: ERR_MSG_HININ_RIYU | F12: 文字 | G12: 100 | L12: 12
A13: =ROW()-9 -> 4 | C13: 受信シーケンスNO_1 | D13: RCV_SEQ_NO_1 | F13: 文字 | G13: 10 | L13: 112
A14: =ROW()-9 -> 5 | C14: 送信データ削除区分 | D14: SND_DATA_DEL_KBN | F14: 数値 | G14: 1 | L14: 122
A15: =ROW()-9 -> 6 | C15: 削除区分 | D15: DEL_KBN | F15: 数値 | G15: 1 | L15: 123
A16: =ROW()-9 -> 7 | C16: 受信シーケンスNO_2 | D16: RCV_SEQ_NO_2 | F16: 文字 | G16: 10 | L16: 124
A17: =ROW()-9 -> 8 | C17: 相手先別データ | D17: AITE_SAKI_BETSU_DATA | F17: 文字 | G17: 4000 | L17: 134
A18: =ROW()-9 -> 9 | C18: 処理受付番号 | D18: FUNC_UKETSUKE_NO | F18: 数値 | G18: 10 | H18: 0 | L18: 4134

Sheet ４．OUTPUTファイルレイアウト(B) (送信ファイル）
A6: ■ | B6: OUTPUTファイルレイアウト | E6: レコード長 | G6: 812 | H6: 文字コード | J6: SJIS
A7: 【ボディレコード】
B8: 項目 | H8: 小数 | I8: 小数点 | J8: PAC/ | K8: Ｓｈｉｆｔ 有無 | L8: 開始
A9: № | B9: グループ | C9: 項 目 名（和名） | D9: 項目名（英名） | E9: 文字コード | F9: 型 | G9: 桁数 | H9: 桁数 | I9: 有無 | J9: UNPAC | L9: 位置 | M9: 備 考
A10: =ROW()-9 -> 1 | C10: リザーブ | D10: RESERVE | F10: 文字 | G10: 1 | L10: 1
A11: =ROW()-9 -> 2 | C11: BPID | D11: BPID | F11: 文字 | G11: 8 | L11: =L10+G10 -> 2
A12: =ROW()-9 -> 3 | C12: 送受信 | D12: SND_RCV | F12: 文字 | G12: 1 | L12: =L11+G11 -> 10
A13: =ROW()-9 -> 4 | C13: 情報区分 | D13: INF_KBN | F13: 文字 | G13: 4 | L13: =L12+G12 -> 11
A14: =ROW()-9 -> 5 | C14: 自社コード | D14: JISHA_CD | F14: 文字 | G14: 12 | L14: =L13+G13 -> 15
A15: =ROW()-9 -> 6 | C15: 相手先コード | D15: AITE_SAKI_CD | F15: 文字 | G15: 12 | L15: =L14+G14 -> 27
A16: =ROW()-9 -> 7 | C16: データ種別 | D16: DATA_SBT | F16: 文字 | G16: 4 | L16: =L15+G15 -> 39
A17: =ROW()-9 -> 8 | C17: 処理区分 | D17: FUNC_KBN | F17: 文字 | G17: 1 | L17: =L16+G16 -> 43
A18: =ROW()-9 -> 9 | C18: 処理年月日 | D18: FUNC_YMD | F18: 文字 | G18: 6 | L18: =L17+G17 -> 44
A19: =ROW()-9 -> 10 | C19: 処理時刻 | D19: FUNC_TM | F19: 文字 | G19: 6 | L19: =L18+G18 -> 50
A20: =ROW()-9 -> 11 | C20: 赤黒区分 | D20: AKAKURO_KBN | F20: 文字 | G20: 1 | L20: =L19+G19 -> 56
A21: =ROW()-9 -> 12 | C21: 発注者企業コード | D21: HACSHA_KIGYO_CD | F21: 文字 | G21: 6 | L21: =L20+G20 -> 57
A22: =ROW()-9 -> 13 | C22: 発注者部門コード | D22: HACSHA_BMN_CD | F22: 文字 | G22: 6 | L22: =L21+G21 -> 63
... A44: =ROW()-9 -> 35 | C44: 数量確定区分 | D44: SURYO_CONFIRM_KBN | F44: 文字 | G44: 1 | L44: =L43+G43 -> 303
A45: =ROW()-9 -> 36 | C45: 販売単価 | D45: HAN_TANK | F45: 数値 | G45: 15 | H45: 3 | I45: 有 | J45: PAC | L45: =L44+G44 -> 304
A46: =ROW()-9 -> 37 | C46: 単価単位 | D46: TANK_UNIT | F46: 文字 | G46: 3 | L46: =L45+G45 -> 319
A47: =ROW()-9 -> 38 | C47: 単価区分 | D47: TANK_KBN | F47: 文字 | G47: 1 | L47: =L46+G46 -> 322
A48: =ROW()-9 -> 39 | C48: 納入先企業コード | D48: NNY_KIGYO_CD | F48: 文字 | G48: 6 | L48: =L47+G47 -> 323
A49: =ROW()-9 -> 40 | C49: 納入先部門コード | D49: NNY_BMN_CD | F49: 文字 | G49: 6 | L49: =L48+G48 -> 329
A50: =ROW()-9 -> 41 | C50: 納入先名称 | D50: NNY_NM | F50: 文字 | G50: 40 | L50: =L49+G49 -> 335
A51: =ROW()-9 -> 42 | C51: 納入日（予定） | D51: NNY_NM_D_YOTEI | F51: 文字 | G51: 6 | L51: =L50+G50 -> 375
A52: =ROW()-9 -> 43 | C52: 販売数量 | D52: HAN_SURYO | F52: 数値 | G52: 15 | H52: 3 | I52: 有 | J52: PAC | L52: =L51+G51 -> 381
A53: =ROW()-9 -> 44 | C53: 金額算出数量 | D53: GAKU_CLC_SURYO | F53: 数値 | G53: 15 | H53: 3 | I53: 有 | J53: PAC | L53: =L52+G52 -> 396
A54: =ROW()-9 -> 45 | C54: 荷姿 | D54: NISUGATA | F54: 文字 | G54: 10 | L54: =L53+G53 -> 411
A55: =ROW()-9 -> 46 | C55: 容量 | D55: YORYO | F55: 数値 | G55: 15 | H55: 3 | I55: 有 | J55: PAC | L55: =L54+G54 -> 421
A56: =ROW()-9 -> 47 | C56: 販売金額 | D56: HAN_GAKU | F56: 数値 | G56: 14 | H56: 0 | I56: 無 | J56: PAC | L56: =L55+G55 -> 436
A57: =ROW()-9 -> 48 | C57: 消費税額 | D57: SHOHIZEI_GAKU | F57: 数値 | G57: 14 | H57: 0 | I57: 無 | J57: PAC | L57: =L56+G56 -> 450
A58: =ROW()-9 -> 49 | C58: 税込請求額 | D58: ZEIKOMI_SEIKYU_GAKU | F58: 数値 | G58: 14 | H58: 0 | I58: 無 | J58: PAC | L58: =L57+G57 -> 464
A59: =ROW()-9 -> 50 | C59: 単価金額区分 | D59: TANK_GAKU_KBN | F59: 文字 | G59: 1 | L59: =L58+G58 -> 478
A60: =ROW()-9 -> 51 | C60: 取引区分 | D60: TORIHIKI_KBN | F60: 文字 | G60: 1 | L60: =L59+G59 -> 479
A61: =ROW()-9 -> 52 | C61: 遡及区分 | D61: SOKYU_KBN | F61: 文字 | G61: 1 | L61: =L60+G60 -> 480
A62: =ROW()-9 -> 53 | C62: 出荷請求区分 | D62: SHUKKA_SEIKYU_KBN | F62: 文字 | G62: 1 | L62: =L61+G61 -> 481
A63: =ROW()-9 -> 54 | C63: 課税区分 | D63: KAZEI_KBN | F63: 文字 | G63: 2 | L63: =L62+G62 -> 482
A64: =ROW()-9 -> 55 | C64: バックオーダー区分 | D64: BACK_ORDER_KBN | F64: 文字 | G64: 1 | L64: =L63+G63 -> 484
A65: =ROW()-9 -> 56 | C65: 出荷年月日（予定） | D65: SHUKKA_YMD_YOTEI | F65: 文字 | G65: 6 | L65: =L64+G64 -> 485
A66: =ROW()-9 -> 57 | C66: 出荷報告番号 | D66: SHUKKA_HOKOKU_NO | F66: 文字 | G66: 25 | L66: =L65+G65 -> 491
A67: =ROW()-9 -> 58 | C67: 出荷請求番号 | D67: SHUKKA_SEIKYU_NO | F67: 文字 | G67: 10 | L67: =L66+G66 -> 516
A68: =ROW()-9 -> 59 | C68: 出荷指図コメント（カナ） | D68: SHUKKA_SASHIZU_COMMENT_KANA | F68: 文字 | G68: 44 | L68: =L67+G67 -> 526
A69: =ROW()-9 -> 60 | C69: 発注者情報 | D69: HACSHA_INF | F69: 文字 | G69: 20 | L69: =L68+G68 -> 570
A70: =ROW()-9 -> 61 | C70: 受注者情報 | D70: JUC_INF | F70: 文字 | G70: 20 | L70: =L69+G69 -> 590
... A75: =ROW()-9 -> 66 | C75: 予備欄（漢字） | D75: YOBI_KANJI | F75: 文字 | G75: 30 | L75: =L74+G74 -> 666
A76: =ROW()-9 -> 67 | C76: 請求金額 | D76: SEIKYU_GAKU | F76: 数値 | G76: 14 | H76: 0 | I76: 無 | J76: PAC | L76: =L75+G75 -> 696
A77: =ROW()-9 -> 68 | C77: 空白5 | D77: FILLER | F77: 文字 | G77: 103 | L77: =L76+G76 -> 710

Sheet ５．項目転送（EDI送信DB_請求確認）_更新
A6: ■ | B6: EDI送信DB_請求確認 更新
A7: EDI送信DB_請求確認フォーマットマッピング | H7: 設 定 値
A8: № | B8: 項目グループ | C8: 項 目 名（和名） | D8: 項 目 名（英名） | E8: 型 | F8: 桁数 | G8: 小数桁数 | H8: 単 純 転 送 | I8: 編 集 内 容
A9: =ROW()-8 -> 1 | C9: 送信シーケンスNO | D9: SND_SEQ_NO | E9: 半角英数字 | F9: 10
A10: =ROW()-8 -> 2 | C10: 計上状況種別 | D10: KEIJO_JOKYO_SBT | E10: 半角数字 | F10: 1
A11: =ROW()-8 -> 3 | C11: エラー種別 | D11: ERR_SBT | E11: 半角英数字 | F11: 1
A12: =ROW()-8 -> 4 | C12: サイン区分 | D12: SIGN_KBN | E12: 半角英数字 | F12: 1
A13: =ROW()-8 -> 5 | C13: 仕入伝票番号 | D13: SIR_DEN_NO | E13: 半角英数字 | F13: 10
A14: =ROW()-8 -> 6 | C14: データ交換ID | D14: DATA_KOKAN_ID | E14: 半角英数字 | F14: 6
A15: =ROW()-8 -> 7 | C15: EDI_機能カテゴリコード | D15: EDI_KINO_CATEGORY_CD | E15: 半角英数字 | F15: 4
A16: =ROW()-8 -> 8 | C16: エラーメッセージ(否認理由) | D16: ERR_MSG_HININ_RIYU | E16: 全半角混在文字 | F16: 100
A17: =ROW()-8 -> 9 | C17: 組織コード | D17: SOSHIKI_CD | E17: 半角英数字 | F17: 5
A18: =ROW()-8 -> 10 | C18: 担当者 | D18: TANTO | E18: 半角英数字 | F18: 5
A19: =ROW()-8 -> 11 | C19: 登録年月日 | D19: REG_YMD | E19: 日付(年月日) | F19: 8
A20: =ROW()-8 -> 12 | C20: 計上年月日 | D20: KEIJO_YMD | E20: 日付(年月日) | F20: 8
... A22: =ROW()-8 -> 14 | C22: 受信シーケンスNO | D22: RCV_SEQ_NO | E22: 半角英数字 | F22: 10
A23: =ROW()-8 -> 15 | C23: EDI_送信状況種別 | D23: EDI_SND_JOKYO_SBT | E23: 半角英数字 | F23: 1 | I23: "3"（処理済）
A24: =ROW()-8 -> 16 | C24: 送信日時 | D24: SND_DT | E24: 全半角混在文字 | F24: 19
A25: =ROW()-8 -> 17 | C25: 送信データ削除区分 | D25: SND_DATA_DEL_KBN | E25: 半角数字 | F25: 1
A26: =ROW()-8 -> 18 | C26: 出荷報告番号 | D26: SHUKKA_HOKOKU_NO | E26: 半角文字 | F26: 25
A27: =ROW()-8 -> 19 | C27: 商品コード | D27: ITEM_CD | E27: 半角数字 | F27: 10
A28: =ROW()-8 -> 20 | C28: EDI_照合キー | D28: EDI_SHOGO_KEY | E28: 半角文字 | F28: 30
A29: =ROW()-8 -> 21 | C29: 販売先注文番号 | D29: HAN_CHUMON_NO | E29: 半角文字 | F29: 23
A30: =ROW()-8 -> 22 | C30: 処理受付番号 | D30: FUNC_UKETSUKE_NO | E30: 小数付き数値 | F30: 10 | G30: 0 | H30: 【処理受付番号】
A31: =ROW()-8 -> 23 | C31: 削除区分 | D31: DEL_KBN | E31: 半角数字 | F31: 1
A32: =ROW()-8 -> 24 | C32: 作成日時 | D32: CREATE_DT | E32: 全半角混在文字 | F32: 19
A33: =ROW()-8 -> 25 | C33: 作成ユーザ | D33: CREATE_USR | E33: 半角英数記号 | F33: 20
A34: =ROW()-8 -> 26 | C34: 作成処理 | D34: CREATE_FUNC | E34: 全半角混在文字 | F34: 64
A35: =ROW()-8 -> 27 | C35: 最新更新日時 | D35: NEW_UPDATE_DT | E35: 全半角混在文字 | F35: 19 | I35: システム日時(YYYY/MM/DD HH:MI:SS)
A36: =ROW()-8 -> 28 | C36: 最新更新ユーザ | D36: NEW_UPDATE_USR | E36: 半角英数記号 | F36: 20 | I36: "EDI"
A37: =ROW()-8 -> 29 | C37: 最新更新処理 | D37: NEW_UPDATE_FUNC | E37: 全半角混在文字 | F37: 64 | I37: "m_NSB_請求確認_データ編集_010"
A38: =ROW()-8 -> 30 | C38: 更新回数 | D38: UPDATE_CNT | E38: 小数付き数値 | F38: 9 | G38: 0 | I38: 【更新回数】＋1

Sheet ６．項目転送（ EDI受信DB_仕入先）_更新
A6: ■ | B6: EDI受信DB_仕入先 更新
A7: EDI採番マスタマッピング | H7: 設 定 値
A8: № | B8: 項目グループ | C8: 項 目 名（和名） | D8: 項 目 名（英名） | E8: 型 | F8: 桁数 | G8: 小数桁数 | H8: 単 純 転 送 | I8: 編 集 内 容
A9: =ROW()-8 -> 1 | C9: 受信シーケンスNO | D9: RCV_SEQ_NO | E9: 半角英数字 | F9: 10
A10: =ROW()-8 -> 2 | C10: データ交換ID | D10: DATA_KOKAN_ID | E10: 半角英数字 | F10: 6
A11: =ROW()-8 -> 3 | C11: EDI_機能カテゴリコード | D11: EDI_KINO_CATEGORY_CD | E11: 半角英数字 | F11: 4
A12: =ROW()-8 -> 4 | C12: 販売先不明区分 | D12: HAN_FUMEI_KBN | E12: 半角数字 | F12: 1
A13: =ROW()-8 -> 5 | C13: 販売先コード | D13: HAN_CD | E13: 半角数字 | F13: 10
A14: =ROW()-8 -> 6 | C14: 販売先コード(確定) | D14: HAN_CD_KAKUTEI | E14: 半角数字 | F14: 10
A15: =ROW()-8 -> 7 | C15: 受信時組織コード | D15: RCV_SOSHIKI_CD | E15: 半角英数字 | F15: 5
A16: =ROW()-8 -> 8 | C16: 受信時組織コード(確定) | D16: RCV_SOSHIKI_CD_KAKUTEI | E16: 半角英数字 | F16: 5
A17: =ROW()-8 -> 9 | C17: 確定仕入責任組織コード(旧) | D17: CONFIRM_SIR_SKNIN_SSHK_CD_OLD | E17: 半角英数字 | F17: 5
A18: =ROW()-8 -> 10 | C18: 確定仕入責任組織コード(新) | D18: CONFIRM_SIR_SKNIN_SSHK_CD_NEW | E18: 半角英数字 | F18: 5
A19: =ROW()-8 -> 11 | C19: 仕入先不明区分 | D19: SUP_FUMEI_KBN | E19: 半角数字 | F19: 1
A20: =ROW()-8 -> 12 | C20: 仕入先コード | D20: SUP_CD | E20: 半角数字 | F20: 10
... A38: =ROW()-8 -> 30 | C38: EDI_照合キー | D38: EDI_SHOGO_KEY | E38: 半角文字 | F38: 30
A39: =ROW()-8 -> 31 | C39: 処理受付番号 | D39: FUNC_UKETSUKE_NO | E39: 小数付き数値 | F39: 10 | G39: 0
A40: =ROW()-8 -> 32 | C40: 受信年月日 | D40: RCV_YMD | E40: 日付(年月日) | F40: 8
A41: =ROW()-8 -> 33 | C41: 受信時刻 | D41: RCV_TM | E41: 半角数字 | F41: 6
A42: =ROW()-8 -> 34 | C42: 受信処理結果通知 | D42: RCV_FUNC_KEKKA_TSUCHI | E42: 全半角混在文字 | F42: 120
A43: =ROW()-8 -> 35 | C43: エラーメッセージ(否認理由) | D43: ERR_MSG_HININ_RIYU | E43: 全半角混在文字 | F43: 100
A44: =ROW()-8 -> 36 | C44: IK自由使用欄1 | D44: IK_FREE_SPACE1 | E44: 全半角混在文字 | F44: 200
A45: =ROW()-8 -> 37 | C45: IK自由使用欄2 | D45: IK_FREE_SPACE2 | E45: 全半角混在文字 | F45: 200
A46: =ROW()-8 -> 38 | C46: IK自由使用欄3 | D46: IK_FREE_SPACE3 | E46: 全半角混在文字 | F46: 200
A47: =ROW()-8 -> 39 | C47: IK自由使用欄4 | D47: IK_FREE_SPACE4 | E47: 全半角混在文字 | F47: 200
A48: =ROW()-8 -> 40 | C48: IK自由使用欄5 | D48: IK_FREE_SPACE5 | E48: 全半角混在文字 | F48: 200
A49: =ROW()-8 -> 41 | C49: IK自由使用欄6 | D49: IK_FREE_SPACE6 | E49: 全半角混在文字 | F49: 200
A50: =ROW()-8 -> 42 | C50: IK自由使用欄7 | D50: IK_FREE_SPACE7 | E50: 全半角混在文字 | F50: 200
A51: =ROW()-8 -> 43 | C51: IK自由使用欄8 | D51: IK_FREE_SPACE8 | E51: 全半角混在文字 | F51: 200
... A54: =ROW()-8 -> 46 | C54: 商品名追記 | D54: ITEM_NM_TSUIKI | E54: 全半角混在文字 | F54: 100
A55: =ROW()-8 -> 47 | C55: 売上単価 | D55: URI_TANK | E55: 小数付き数値 | F55: 17 | G55: 4
A56: =ROW()-8 -> 48 | C56: 売上金額本体 | D56: URI_GAKU_HONTAI | E56: 小数付き数値 | F56: 13 | G56: 0
A57: =ROW()-8 -> 49 | C57: EDI_請求金額(確定) | D57: EDI_SEIKYU_GAKU_KAKUTEI | E57: 小数付き数値 | F57: 13 | G57: 0
A58: =ROW()-8 -> 50 | C58: EDI_消費税額(確定) | D58: EDI_SHOHIZEI_GAKU_KAKUTEI | E58: 小数付き数値 | F58: 10 | G58: 0
A59: =ROW()-8 -> 51 | C59: 税込請求額(確定) | D59: ZEIKOMI_SEIKYU_GAKU_KAKUTEI | E59: 小数付き数値 | F59: 13 | G59: 0
A60: =ROW()-8 -> 52 | C60: 仕入先計上年月日 | D60: SUP_KEIJO_YMD | E60: 日付(年月日) | F60: 8
A61: =ROW()-8 -> 53 | C61: 計上年月日 | D61: KEIJO_YMD | E61: 日付(年月日) | F61: 8
A62: =ROW()-8 -> 54 | C62: 仕入先売上NO | D62: SUP_URI_NO | E62: 半角文字 | F62: 10
A63: =ROW()-8 -> 55 | C63: 重量 | D63: JURYO | E63: 小数付き数値 | F63: 12 | G63: 4
A64: =ROW()-8 -> 56 | C64: EDI_支払サイト | D64: EDI_PAY_SIGHT | E64: 半角英数字 | F64: 3
A65: =ROW()-8 -> 57 | C65: メモ | D65: MEMO | E65: 全半角混在文字 | F65: 20
A66: =ROW()-8 -> 58 | C66: 訂正時の相手照合NO | D66: TEISEI_H_AITE_SHOGO_NO | E66: 半角文字 | F66: 30
A67: =ROW()-8 -> 59 | C67: メーカ事業所 | D67: MK_JIGYOSHO | E67: 半角文字 | F67: 7
A68: =ROW()-8 -> 60 | C68: メーカ商品コード(FULL) | D68: MK_ITEM_CD_FULL | E68: 半角文字 | F68: 50
A69: =ROW()-8 -> 61 | C69: 出荷場所名(漢字) | D69: SHUKKA_BASHO_NM | E69: 全角文字 | F69: 20
A70: =ROW()-8 -> 62 | C70: EDI_メーカ荷姿名(漢字) | D70: EDI_MK_NISUGATA_NM | E70: 全角文字 | F70: 20
A71: =ROW()-8 -> 63 | C71: 工場名 | D71: KOJO_NM | E71: 全半角混在文字 | F71: 20
A72: =ROW()-8 -> 64 | C72: 現場名 | D72: GEMBA_NM | E72: 全半角混在文字 | F72: 50
A73: =ROW()-8 -> 65 | C73: 販売区域 | D73: HAN_ARER | E73: 半角英数字 | F73: 2
A74: =ROW()-8 -> 66 | C74: 担当課コード | D74: TANTOKA_CD | E74: 半角英数字 | F74: 4
A75: =ROW()-8 -> 67 | C75: 漢字備考種別 | D75: KANJI_NOTE_SBT | E75: 半角英数字 | F75: 1
... A77: =ROW()-8 -> 69 | C77: グレード/カラーNO | D77: GRADE_COLOR_NO | E77: 半角文字 | F77: 20
A78: =ROW()-8 -> 70 | C78: EDI_商品巾 | D78: EDI_ITEM_WIDTH | E78: 小数付き数値 | F78: 9 | G78: 1
A79: =ROW()-8 -> 71 | C79: EDI_商品長さ | D79: EDI_ITEM_LENGTH | E79: 小数付き数値 | F79: 9 | G79: 1
A80: =ROW()-8 -> 72 | C80: EDI_商品厚み | D80: EDI_ITEM_THICK | E80: 小数付き数値 | F80: 8 | G80: 0
A81: =ROW()-8 -> 73 | C81: EDI_商品代替品巾 | D81: EDI_ITEM_DAITAIHIN_WIDTH | E81: 小数付き数値 | F81: 8 | G81: 0
A82: =ROW()-8 -> 74 | C82: 販売先品番 | D82: HAN_HIMBAN | E82: 半角文字 | F82: 20
A83: =ROW()-8 -> 75 | C83: リスト出力用エラー内容 | D83: LIST_OUT_YO_ERR_NAIYO | E83: 全半角混在文字 | F83: 100
A84: =ROW()-8 -> 76 | C84: 仕入伝票番号 | D84: SIR_DEN_NO | E84: 半角英数字 | F84: 10
A85: =ROW()-8 -> 77 | C85: 売上伝票番号 | D85: URI_DEN_NO | E85: 半角英数字 | F85: 10
A86: =ROW()-8 -> 78 | C86: 相殺先受信シーケンスNO | D86: SOSAI_RCV_SEQ_NO | E86: 半角英数字 | F86: 10
A87: =ROW()-8 -> 79 | C87: EDI_支払締切年月日 | D87: EDI_PAY_SHIMEKIRI_YMD | E87: 日付(年月日) | F87: 8
A88: =ROW()-8 -> 80 | C88: 変更後期日年月日 | D88: HENKOGO_KIJITSU_YMD | E88: 日付(年月日) | F88: 8
A89: =ROW()-8 -> 81 | C89: 支払照合番号 | D89: PAY_SHOGO_NO | E89: 半角英数字 | F89: 10
A90: =ROW()-8 -> 82 | C90: 出荷請求確認番号(債務) | D90: SHUKKA_SEIKYU_CHK_NO_SAIMU | E90: 半角英数字 | F90: 10
A91: =ROW()-8 -> 83 | C91: 計上状況種別(仮締め) | D91: KEIJO_JOKYO_SBT_KARISHIME | E91: 半角数字 | F91: 1
A92: =ROW()-8 -> 84 | C92: EDI_支払締め種別 | D92: EDI_PAY_SHIME_SBT | E92: 半角数字 | F92: 1
A93: =ROW()-8 -> 85 | C93: EDI_支払種別 | D93: EDI_PAY_SBT | E93: 半角数字 | F93: 1
... A118: =ROW()-8 -> 110 | C118: ユーザ発注処理種別 | D118: USR_HAC_FUNC_SBT | E118: 半角英数字 | F118: 1
A119: =ROW()-8 -> 111 | C119: 請求確認作成種別 | D119: SEIKYU_CHK_CREATE_SBT | E119: 半角数字 | F119: 1 | I119: "2"（作成済）
A120: =ROW()-8 -> 112 | C120: 確認種別 | D120: CHK_SBT | E120: 半角英数字 | F120: 1
A121: =ROW()-8 -> 113 | C121: EDI_計上種別 | D121: EDI_KEIJO_SBT | E121: 半角英数字 | F121: 2
A122: =ROW()-8 -> 114 | C122: EDI_計上種別(確定) | D122: EDI_KEIJO_SBT_KAKUTEI | E122: 半角英数字 | F122: 2
A123: =ROW()-8 -> 115 | C123: 計上状況種別 | D123: KEIJO_JOKYO_SBT | E123: 半角数字 | F123: 1
A124: =ROW()-8 -> 116 | C124: 自動取消実施状況種別 | D124: AUTO_DEL_JISSHI_JOKYO_SBT | E124: 半角数字 | F124: 1
A125: =ROW()-8 -> 117 | C125: 業務エラーコード | D125: ACT_ERR_CD | E125: 半角英数字 | F125: 12
A126: =ROW()-8 -> 118 | C126: EDI_請求データ区分 | D126: EDI_SEIKYU_DATA_KBN | E126: 半角数字 | F126: 1
A127: =ROW()-8 -> 119 | C127: JPCA_リザーブ | D127: JPCA_RESERVE | E127: 半角英数字 | F127: 1
A128: =ROW()-8 -> 120 | C128: JPCA_BPID | D128: JPCA_BPID | E128: 半角英数字 | F128: 8
A129: =ROW()-8 -> 121 | C129: JPCA_送受信 | D129: JPCA_SND_RCV | E129: 半角英数字 | F129: 1
A130: =ROW()-8 -> 122 | C130: JPCA_情報区分 | D130: JPCA_INF_KBN | E130: 半角英数字 | F130: 4
A131: =ROW()-8 -> 123 | C131: JPCA_自社コード | D131: JPCA_JISHA_CD | E131: 半角文字 | F131: 12
... A188: =ROW()-8 -> 180 | C188: JPCA_数量確定区分 | D188: JPCA_SU_KAKUTEI_KBN | E188: 半角英数字 | F188: 1
A189: =ROW()-8 -> 181 | C189: JPCA_販売単価 | D189: JPCA_HAN_TANK | E189: 小数付き数値 | F189: 13 | G189: 3
A190: =ROW()-8 -> 182 | C190: JPCA_単価単位 | D190: JPCA_TANK_UNIT | E190: 半角文字 | F190: 3
A191: =ROW()-8 -> 183 | C191: JPCA_単価区分 | D191: JPCA_TANK_KBN | E191: 半角英数字 | F191: 1
A192: =ROW()-8 -> 184 | C192: JPCA_口銭区分 | D192: JPCA_KOSEN_KBN | E192: 半角英数字 | F192: 1
A193: =ROW()-8 -> 185 | C193: JPCA_口銭単価 | D193: JPCA_KOSEN_TANK | E193: 小数付き数値 | F193: 13 | G193: 3
A194: =ROW()-8 -> 186 | C194: JPCA_口銭 | D194: JPCA_KOSEN | E194: 小数付き数値 | F194: 16 | G194: 0
A195: =ROW()-8 -> 187 | C195: JPCA_2次店口銭区分 | D195: JPCA_NIJITEN_KOSEN_KBN | E195: 半角英数字 | F195: 1
A196: =ROW()-8 -> 188 | C196: JPCA_2次店口銭単価 | D196: JPCA_NIJITEN_KOSEN_TANK | E196: 小数付き数値 | F196: 13 | G196: 3
A197: =ROW()-8 -> 189 | C197: JPCA_2次店口銭 | D197: JPCA_NIJITEN_KOSEN | E197: 小数付き数値 | F197: 16 | G197: 0
A198: =ROW()-8 -> 190 | C198: JPCA_納入先企業コード | D198: JPCA_NNY_KIGYO_CD | E198: 半角文字 | F198: 6
A199: =ROW()-8 -> 191 | C199: JPCA_納入先部門コード | D199: JPCA_NNY_BMN_CD | E199: 半角文字 | F199: 6
A200: =ROW()-8 -> 192 | C200: JPCA_納入先名称(カナ) | D200: JPCA_NNY_NMK | E200: 半角文字 | F200: 40
A201: =ROW()-8 -> 193 | C201: JPCA_納入先名称(漢字) | D201: JPCA_NNY_NM_KANJI | E201: 全角文字 | F201: 50
A202: =ROW()-8 -> 194 | C202: JPCA_EDI受渡条件 | D202: JPCA_EDI_UKEWATASHI_JOKEN | E202: 半角文字 | F202: 2
A203: =ROW()-8 -> 195 | C203: JPCA_受渡場所住所(カナ) | D203: JPCA_UKEWATASHI_BASHO_ADDRK | E203: 半角文字 | F203: 74
A204: =ROW()-8 -> 196 | C204: JPCA_受渡場所住所(漢字) | D204: JPCA_UKEWATASHI_BASHO_ADDR | E204: 全角文字 | F204: 80
A205: =ROW()-8 -> 197 | C205: JPCA_地区コード | D205: JPCA_CHIKU_CD | E205: 半角文字 | F205: 11
...

Sheet ６．１．相手先別データレイアウト
E6: レコード長 | F6: =SUM(G10:G141) -> 4000
A7: ■ | B7: 相手先別データレイアウト
B8: 変更 | C8: 項目 | H8: 小数 | I8: 小数点 | J8: 開始
A9: № | B9: 箇所 | C9: グループ | D9: 項 目 名（和名） | E9: 項目名（英名） | F9: 型 | G9: 桁数 | H9: 桁数 | I9: 有無 | J9: 位置 | K9: 備 考
A10: =ROW()-9 -> 1 | D10: リザーブ | E10: RESERVE | F10: 文字 | G10: 1 | J10: 1
A11: =ROW()-9 -> 2 | D11: BPID | E11: BPID | F11: 文字 | G11: 8 | J11: =J10+G10 -> 2
A12: =ROW()-9 -> 3 | D12: 送受信 | E12: SND_RCV | F12: 文字 | G12: 1 | J12: =J11+G11 -> 10
A13: =ROW()-9 -> 4 | D13: 情報区分 | E13: INF_KBN | F13: 文字 | G13: 4 | J13: =J12+G12 -> 11
A14: =ROW()-9 -> 5 | D14: 自社コード | E14: JISHA_CD | F14: 文字 | G14: 12 | J14: =J13+G13 -> 15
A15: =ROW()-9 -> 6 | D15: 相手先企業コード | E15: AITE_SAKI_KIGYO_CD | F15: 文字 | G15: 6 | J15: =J14+G14 -> 27
A16: =ROW()-9 -> 7 | D16: 相手先部門コード | E16: AITE_SAKI_BMN_CD | F16: 文字 | G16: 6 | J16: =J15+G15 -> 33
A17: =ROW()-9 -> 8 | D17: データ種別 | E17: DATA_SBT | F17: 文字 | G17: 4 | J17: =J16+G16 -> 39
A18: =ROW()-9 -> 9 | D18: 処理区分 | E18: FUNC_KBN | F18: 文字 | G18: 1 | J18: =J17+G17 -> 43
A19: =ROW()-9 -> 10 | D19: 処理年月日 | E19: FUNC_YMD | F19: 文字 | G19: 6 | J19: =J18+G18 -> 44
A20: =ROW()-9 -> 11 | D20: 処理時刻 | E20: FUNC_TM | F20: 文字 | G20: 6 | J20: =J19+G19 -> 50
A21: =ROW()-9 -> 12 | D21: 赤黒区分 | E21: AKAKURO_KBN | F21: 文字 | G21: 1 | J21: =J20+G20 -> 56
A22: =ROW()-9 -> 13 | D22: 発注者企業コード | E22: HACSHA_KIGYO_CD | F22: 文字 | G22: 6 | J22: =J21+G21 -> 57
... A71: =ROW()-9 -> 62 | D71: 数量確定区分 | E71: SURYO_CONFIRM_KBN | F71: 文字 | G71: 1 | J71: =J70+G70 -> 749
A72: =ROW()-9 -> 63 | B72: ● | D72: 販売単価 | E72: HAN_TANK | F72: 数値 | G72: 13 | H72: 3 | I72: 無 | J72: =J71+G71 -> 750 | K72: アンパック数値文字列を数値に変換し使用
A73: =ROW()-9 -> 64 | D73: 単価単位 | E73: TANK_UNIT | F73: 文字 | G73: 3 | J73: =J72+G72 -> 763
A74: =ROW()-9 -> 65 | D74: 単価区分 | E74: TANK_KBN | F74: 文字 | G74: 1 | J74: =J73+G73 -> 766
A75: =ROW()-9 -> 66 | D75: 口銭区分 | E75: KOSEN_KBN | F75: 文字 | G75: 1 | J75: =J74+G74 -> 767
A76: =ROW()-9 -> 67 | B76: ● | D76: 口銭単価 | E76: KOSEN_TANK | F76: 数値 | G76: 13 | H76: 3 | I76: 無 | J76: =J75+G75 -> 768 | K76: アンパック数値文字列を数値に変換し使用
A77: =ROW()-9 -> 68 | B77: ● | D77: 口銭金額 | E77: KOSEN_GAKU | F77: 数値 | G77: 13 | H77: 0 | J77: =J76+G76 -> 781 | K77: アンパック数値文字列を数値に変換し使用
A78: =ROW()-9 -> 69 | D78: 2次店口銭区分 | E78: NIJITEN_KOSEN_KBN | F78: 文字 | G78: 1 | J78: =J77+G77 -> 794
A79: =ROW()-9 -> 70 | B79: ● | D79: 2次店口銭単価 | E79: NIJITEN_KOSEN_TANK | F79: 数値 | G79: 13 | H79: 3 | I79: 無 | J79: =J78+G78 -> 795 | K79: アンパック数値文字列を数値に変換し使用
A80: =ROW()-9 -> 71 | B80: ● | D80: 2次店口銭金額 | E80: NIJITEN_KOSEN_GAKU | F80: 数値 | G80: 13 | H80: 0 | J80: =J79+G79 -> 808 | K80: アンパック数値文字列を数値に変換し使用
A81: =ROW()-9 -> 72 | D81: 納入先企業コード | E81: NNY_KIGYO_CD | F81: 文字 | G81: 6 | J81: =J80+G80 -> 821
A82: =ROW()-9 -> 73 | D82: 納入先部門コード | E82: NNY_BMN_CD | F82: 文字 | G82: 6 | J82: =J81+G81 -> 827
A83: =ROW()-9 -> 74 | D83: 納入先名称（カナ） | E83: NNY_NM_KANA | F83: 文字 | G83: 40 | J83: =J82+G82 -> 833
A84: =ROW()-9 -> 75 | D84: 納入先名称（漢字） | E84: NNY_NM_KANJI | F84: 文字 | G84: 40 | J84: =J83+G83 -> 873
A85: =ROW()-9 -> 76 | D85: 受渡条件 | E85: UKEWATASHI_JOKEN | F85: 文字 | G85: 2 | J85: =J84+G84 -> 913
A86: =ROW()-9 -> 77 | D86: 受渡場所住所（カナ） | E86: UKEWATASHI_BASHO_ADDRK | F86: 文字 | G86: 74 | J86: =J85+G85 -> 915
A87: =ROW()-9 -> 78 | D87: 受渡場所住所（漢字） | E87: UKEWATASHI_BASHO_ADDR | F87: 文字 | G87: 74 | J87: =J86+G86 -> 989
A88: =ROW()-9 -> 79 | D88: 地区コード | E88: CHIKU_CD | F88: 文字 | G88: 11 | J88: =J87+G87 -> 1063
A89: =ROW()-9 -> 80 | D89: 郵便番号 | E89: ZIP | F89: 文字 | G89: 7 | J89: =J88+G88 -> 1074
A90: =ROW()-9 -> 81 | D90: 電話番号 | E90: TEL | F90: 文字 | G90: 12 | J90: =J89+G89 -> 1081
A91: =ROW()-9 -> 82 | D91: FAX番号 | E91: FAX | F91: 文字 | G91: 12 | J91: =J90+G90 -> 1093
A92: =ROW()-9 -> 83 | D92: 希望納入日 | E92: KIBO_NONYU_D | F92: 文字 | G92: 6 | J92: =J91+G91 -> 1105
... A97: =ROW()-9 -> 88 | D97: 納入要件（漢字） | E97: NONYU_YOKEN_KANJI | F97: 文字 | G97: 44 | J97: =J96+G96 -> 1175
A98: =ROW()-9 -> 89 | B98: ● | D98: 支払金額 | E98: PAY_GAKU | F98: 数値 | G98: 13 | H98: 0 | J98: =J97+G97 -> 1219 | K98: アンパック数値文字列を数値に変換し使用
A99: =ROW()-9 -> 90 | D99: 支払整理番号 | E99: PAY_SEIRI_NO | F99: 文字 | G99: 12 | J99: =J98+G98 -> 1232
A100: =ROW()-9 -> 91 | D100: 銀行情報 | E100: BANK_INF | F100: 文字 | G100: 103 | J100: =J99+G99 -> 1244
A101: =ROW()-9 -> 92 | B101: ● | D101: 注文数量 | E101: CHUMON_SURYO | F101: 数値 | G101: 13 | H101: 3 | I101: 無 | J101: =J100+G100 -> 1347 | K101: アンパック数値文字列を数値に変換し使用
A102: =ROW()-9 -> 93 | B102: ● | D102: 注文･販売個数 | E102: CHUMON_HAN_KOSU | F102: 数値 | G102: 13 | H102: 3 | I102: 無 | J102: =J101+G101 -> 1360 | K102: アンパック数値文字列を数値に変換し使用
A103: =ROW()-9 -> 94 | D103: 注文数量単位 | E103: CHUMON_SURYO_UNIT | F103: 文字 | G103: 3 | J103: =J102+G102 -> 1373
A104: =ROW()-9 -> 95 | B104: ● | D104: 販売個数 | E104: HAN_KOSU | F104: 数値 | G104: 13 | H104: 3 | I104: 無 | J104: =J103+G103 -> 1376 | K104: アンパック数値文字列を数値に変換し使用
A105: =ROW()-9 -> 96 | B105: ● | D105: 金額算出数量 | E105: GAKU_CLC_SURYO | F105: 数値 | G105: 13 | H105: 3 | I105: 無 | J105: =J104+G104 -> 1389 | K105: アンパック数値文字列を数値に変換し使用
A106: =ROW()-9 -> 97 | D106: 荷姿コード | E106: NISUGATA_CD | F106: 文字 | G106: 3 | J106: =J105+G105 -> 1402
A107: =ROW()-9 -> 98 | D107: 荷姿名 | E107: NISUGATA_NM | F107: 文字 | G107: 7 | J107: =J106+G106 -> 1405
A108: =ROW()-9 -> 99 | B108: ● | D108: 容量 | E108: YORYO | F108: 数値 | G108: 13 | H108: 3 | I108: 無 | J108: =J107+G107 -> 1412 | K108: アンパック数値文字列を数値に変換し使用
A109: =ROW()-9 -> 100 | B109: ● | D109: 販売金額 | E109: HAN_GAKU | F109: 数値 | G109: 13 | H109: 0 | J109: =J108+G108 -> 1425 | K109: アンパック数値文字列を数値に変換し使用
A110: =ROW()-9 -> 101 | B110: ● | D110: 請求金額 | E110: SEIKYU_GAKU | F110: 数値 | G110: 13 | H110: 0 | J110: =J109+G109 -> 1438 | K110: アンパック数値文字列を数値に変換し使用
A111: =ROW()-9 -> 102 | B111: ● | D111: 消費税額 | E111: SHOHIZEI_GAKU | F111: 数値 | G111: 13 | H111: 0 | J111: =J110+G110 -> 1451 | K111: アンパック数値文字列を数値に変換し使用
A112: =ROW()-9 -> 103 | B112: ● | D112: 税込請求額 | E112: ZEIKOMI_SEIKYU_GAKU | F112: 数値 | G112: 13 | H112: 0 | J112: =J111+G111 -> 1464 | K112: アンパック数値文字列を数値に変換し使用
A113: =ROW()-9 -> 104 | D113: 単価･金額区分 | E113: TANK_GAKU_KBN | F113: 文字 | G113: 1 | J113: =J112+G112 -> 1477
A114: =ROW()-9 -> 105 | D114: 取引区分 | E114: TORIHIKI_KBN | F114: 文字 | G114: 1 | J114: =J113+G113 -> 1478
A115: =ROW()-9 -> 106 | D115: 遡及区分 | E115: SOKYU_KBN | F115: 文字 | G115: 1 | J115: =J114+G114 -> 1479
A116: =ROW()-9 -> 107 | D116: 出荷請求区分 | E116: SHUKKA_SEIKYU_KBN | F116: 文字 | G116: 1 | J116: =J115+G115 -> 1480
A117: =ROW()-9 -> 108 | D117: 課税区分 | E117: KAZEI_KBN | F117: 文字 | G117: 2 | J117: =J116+G116 -> 1481
A118: =ROW()-9 -> 109 | D118: バックオーダー区分 | E118: BACK_ORDER_KBN | F118: 文字 | G118: 1 | J118: =J117+G117 -> 1483
A119: =ROW()-9 -> 110 | D119: 計上年月日 | E119: KEIJO_YMD | F119: 文字 | G119: 4 | J119: =J118+G118 -> 1484
A120: =ROW()-9 -> 111 | B120: ● | D120: 適用税率 | E120: TEKIYO_TAX_RATE | F120: 数値 | G120: 4 | H120: 2 | I120: 無 | J120: =J119+G119 -> 1488 | K120: アンパック数値文字列を数値に変換し使用
A121: =ROW()-9 -> 112 | D121: 請求者登録番号 | E121: SHUKKA_SEIKYU_REG_NO | F121: 文字 | G121: 14 | J121: =J120+G120 -> 1492
A122: =ROW()-9 -> 113 | D122: 返品資産の基譲渡日 | E122: HEMPIN_SHISAN_MOTO_JOTO_KEIJO_D | F122: 文字 | G122: 6 | J122: =J121+G121 -> 1506
A123: =ROW()-9 -> 114 | D123: 出荷請求年月日(予定) | E123: SHUKKA_SEIKYU_YMD_YOTEI | F123: 文字 | G123: 6 | J123: =J122+G122 -> 1512
A124: =ROW()-9 -> 115 | D124: 出荷報告番号 | E124: SHUKKA_HOKOKU_NO | F124: 文字 | G124: 25 | J124: =J123+G123 -> 1518
A125: =ROW()-9 -> 116 | D125: 出荷請求番号 | E125: SHUKKA_SEIKYU_NO | F125: 文字 | G125: 10 | J125: =J124+G124 -> 1543
A126: =ROW()-9 -> 117 | D126: 出荷場所 | E126: SHUKKA_BASHO | F126: 文字 | G126: 5 | J126: =J125+G125 -> 1553
A127: =ROW()-9 -> 118 | D127: 出荷指図コメント（カナ） | E127: SHUKKA_SASHIZU_COMMENT_KANA | F127: 文字 | G127: 44 | J127: =J126+G126 -> 1558
A128: =ROW()-9 -> 119 | D128: 出荷指図コメント（漢字） | E128: SHUKKA_SASHIZU_COMMENT_KANJI | F128: 文字 | G128: 44 | J128: =J127+G127 -> 1602
A129: =ROW()-9 -> 120 | D129: 輸送手段 | E129: YUSO_SHUDAN | F129: 文字 | G129: 2 | J129: =J128+G128 -> 1646
A130: =ROW()-9 -> 121 | D130: 輸送車種 | E130: YUSO_SHASHU | F130: 文字 | G130: 10 | J130: =J129+G129 -> 1648
A131: =ROW()-9 -> 122 | D131: 発注者情報 | E131: HACSHA_INF | F131: 文字 | G131: 20 | J131: =J130+G130 -> 1658
A132: =ROW()-9 -> 123 | D132: 受注者情報 | E132: JUC_INF | F132: 文字 | G132: 20 | J132: =J131+G131 -> 1678
... A141: =ROW()-9 -> 132 | D141: カラム1 | E141: COLUMN_1 | F141: 文字 | G141: 2100 | J141: =J140+G140 -> 1901

Sheet ７．項目転送 (請求データ送信ファイル)
A6: ■ | B6: 請求確認データ送信ファイルマッピング仕様 | D6: ［ ］：６．１．相手先別データレイアウト | E6: △：半角空白、□：全角空白
A7: 請求確認データ送信ファイルマッピング | D7: 設 定 値
A8: № | B8: 項 目 名（和名） | C8: 項 目 名（英名） | D8: 単 純 転 送 | E8: 編 集 内 容
A9: 1 | B9: リザーブ | C9: RESERVE | E9: "△"
A10: 2 | B10: BPID | C10: BPID | E10: "JPCA0102"
A11: 3 | B11: 送受信 | C11: SND_RCV | E11: "S"
A12: 4 | B12: 情報区分 | C12: INF_KBN | E12: "1720"
A13: 5 | B13: 自社コード | C13: JISHA_CD | E13: "101913000010"
A14: 6 | B14: 相手先コード | C14: AITE_SAKI_CD | E14: "506040999995"
A15: 7 | B15: データ種別 | C15: DATA_SBT | E15: "1720"
A16: 8 | B16: 処理区分 | C16: FUNC_KBN | D16: [処理区分]
A17: 9 | B17: 処理年月日 | C17: FUNC_YMD | E17: yymmdd(システム日付）
A18: 10 | B18: 処理時刻 | C18: FUNC_TM | E18: HHMMSS(システム時刻)
A19: 11 | B19: 赤黒区分 | C19: AKAKURO_KBN | D19: [赤黒区分]
A20: 12 | B20: 発注者企業コード | C20: HACSHA_KIGYO_CD | D20: [発注者企業コード]
A21: 13 | B21: 発注者部門コード | C21: HACSHA_BMN_CD | D21: [発注者部門コード]
A22: 14 | B22: 受注者企業コード | C22: JUC_KIGYO_CD | D22: [受注者企業コード]
A23: 15 | B23: 受注者部門コード | C23: JUC_BMN_CD | D23: [受注者部門コード]
A24: 16 | B24: 請求者企業コード | C24: SEIKYU_KIGYO_CD | D24: [請求者企業コード]
A25: 17 | B25: 請求者部門コード | C25: SEIKYU_BMN_CD | D25: [請求者部門コード]
A26: 18 | B26: 支払者企業コード | C26: PAY_KIGYO_CD | D26: [支払者企業コード]
A27: 19 | B27: 支払先部門コード | C27: PAY_BMN_CD | D27: [支払者部門コード]
A28: 20 | B28: 契約番号 | C28: KEIYAKU_NO | D28: [契約番号]
A29: 21 | B29: 注文番号 | C29: CHUMON_NO | D29: [注文番号]
A30: 22 | B30: 受注番号 | C30: JUC_NO | D30: [受注番号]
... A52: 44 | B52: 金額算出数量 | C52: GAKU_CLC_SURYO | D52: [金額算出数量]
A53: 45 | B53: 荷姿 | C53: NISUGATA | E53: 結合文字（[荷姿ｺｰﾄﾞ]、[荷姿名]）
A54: 46 | B54: 容量 | C54: YORYO | D54: [容量]
A55: 47 | B55: 販売金額 | C55: HAN_GAKU | D55: [販売金額]
A56: 48 | B56: 消費税額 | C56: SHOHIZEI_GAKU | D56: [消費税額]
A57: 49 | B57: 税込請求額 | C57: ZEIKOMI_SEIKYU_GAKU | D57: [税込請求額]
A58: 50 | B58: 単価金額区分 | C58: TANK_GAKU_KBN | D58: [単価･金額区分]
A59: 51 | B59: 取引区分 | C59: TORIHIKI_KBN | D59: [取引区分]
A60: 52 | B60: 遡及区分 | C60: SOKYU_KBN | D60: [遡及区分]
A61: 53 | B61: 出荷請求区分 | C61: SHUKKA_SEIKYU_KBN | D61: [出荷請求区分]
A62: 54 | B62: 課税区分 | C62: KAZEI_KBN | D62: [課税区分]
A63: 55 | B63: バックオーダー区分 | C63: BACK_ORDER_KBN | D63: [バックオーダー区分]
A64: 56 | B64: 出荷年月日（予定） | C64: SHUKKA_YMD_YOTEI | D64: [出荷請求年月日(予定)]
A65: 57 | B65: 出荷報告番号 | C65: SHUKKA_HOKOKU_NO | E65: [出荷報告番号]の空白スペースをトリム
A66: 58 | B66: 出荷請求番号 | C66: SHUKKA_SEIKYU_NO | E66: [出荷請求番号]の空白スペースをトリム
A67: 59 | B67: 出荷指図コメント（カナ） | C67: SHUKKA_SASHIZU_COMMENT_KANA | E67: [出荷指図コメント（カナ）]の空白スペースをトリム
A68: 60 | B68: 発注者情報 | C68: HACSHA_INF | E68: [発注者情報]の空白スペースをトリム
A69: 61 | B69: 受注者情報 | C69: JUC_INF | E69: [発注者情報]の空白スペースをトリム
A70: 62 | B70: 国内輸出区分 | C70: DOM_EXP_KBN | D70: [国内輸出区分]
A71: =ROW()-8 -> 63 | B71: エラー理由 | C71: ERR_RIYU | E71: 連携ファイル.計上状況種別 IN ('0' ,'5')の場合
E72: ﾐｶｸﾆﾝ
E73: 連携ファイル.計上状況種別 = '2'の場合
E74: 連携ファイル.エラーメッセージ(否認理由)の先頭10バイト
E75: それ以外の場合
E76: △*10
A77: 64 | B77: エラーメッセージ | C77: ERR_MSG | E77: 連携ファイル.計上状況種別 IN ('0' ,'5')の場合
E78: ﾐｶｸﾆﾝ
E79: 連携ファイル.計上状況種別] = '2'の場合
E80: 連携ファイル.エラーメッセージ(否認理由)
E81: それ以外の場合
E82: △*44
A83: 65 | B83: 請求確認区分 | C83: SEIKYU_CHK_KBN | E83: 連携ファイル.計上状況種別 IN ('0' ,'2' ,'5')の場合
E84: 2
E85: 連携ファイル.計上状況種別 IN ('1' ,'3' ,'4')の場合
E86: 1
E87: それ以外の場合
E88: 1
A89: 66 | B89: 予備欄（漢字） | C89: YOBI_KANJI | E89: △*30
A90: 67 | B90: 請求金額 | C90: SEIKYU_GAKU | D90: [請求金額]
A91: 68 | B91: 空白5 | C91: FILLER | E91: △*103

Sheet ８．【参考】日本触媒　OUTPUTファイルレイアウト
B2: 送信はJPCAの800バイトのファイルレイアウトで行う
B3: IK
B4: № | C4: 項目名 | D4: 型 | E4: 桁数 | F4: 小数 桁数 | G4: 開始 位置 | H4: 必須/任意 | I4: 備考
B6: 1 | C6: ﾘｻﾞ-ﾌﾞ | D6: 文字 | E6: 1 | G6: 1
B7: 2 | C7: BPID | D7: 文字 | E7: 8 | G7: =E6+G6 -> 2
B8: 3 | C8: 送受信 | D8: 文字 | E8: 1 | G8: =E7+G7 -> 10
B9: 4 | C9: 情報区分 | D9: 文字 | E9: 4 | G9: =E8+G8 -> 11
B10: 5 | C10: 自社ｺ-ﾄﾞ | D10: 文字 | E10: 12 | G10: =E9+G9 -> 15
B11: 6 | C11: 相手先ｺ-ﾄﾞ | D11: 文字 | E11: 12 | G11: =E10+G10 -> 27
B12: 7 | C12: ﾃﾞｰﾀ種別 | D12: 文字 | E12: 4 | G12: =E11+G11 -> 39
B13: 8 | C13: 処理区分 | D13: 文字 | E13: 1 | G13: =E12+G12 -> 43
B14: 9 | C14: 処理年月日 | D14: 文字 | E14: 6 | G14: =E13+G13 -> 44
B15: 10 | C15: 処理時刻 | D15: 文字 | E15: 6 | G15: =E14+G14 -> 50
B16: 11 | C16: 赤黒区分 | D16: 文字 | E16: 1 | G16: =E15+G15 -> 56
B17: 12 | C17: 発注者企業ｺｰﾄﾞ | D17: 文字 | E17: 6 | G17: =E16+G16 -> 57
B18: 13 | C18: 発注者部門ｺｰﾄﾞ | D18: 文字 | E18: 6 | G18: =E17+G17 -> 63
... B40: 35 | C40: 数量確定区分 | D40: 文字 | E40: 1 | G40: =E39+G39 -> 303
B41: 36 | C41: 販売単価 | D41: 数値文字列 | E41: 15 | F41: 3 | G41: =E40+G40 -> 304
B42: 37 | C42: 単価単位 | D42: 文字 | E42: 3 | G42: =E41+G41 -> 319
B43: 38 | C43: 単価区分 | D43: 文字 | E43: 1 | G43: =E42+G42 -> 322
B44: 39 | C44: 納入先企業ｺｰﾄﾞ | D44: 文字 | E44: 6 | G44: =E43+G43 -> 323
B45: 40 | C45: 納入先部門コード | D45: 文字 | E45: 6 | G45: =E44+G44 -> 329
B46: 41 | C46: 納入先名称 | D46: 文字 | E46: 40 | G46: =E45+G45 -> 335
B47: 42 | C47: 納入日(予定) | D47: 文字 | E47: 6 | G47: =E46+G46 -> 375
B48: 43 | C48: 販売数量 | D48: 数値文字列 | E48: 15 | F48: 3 | G48: =E47+G47 -> 381
B49: 44 | C49: 金額算出数量 | D49: 数値文字列 | E49: 15 | F49: 3 | G49: =E48+G48 -> 396
B50: 45 | C50: 荷姿 | D50: 文字 | E50: 10 | G50: =E49+G49 -> 411
B51: 46 | C51: 容量 | D51: 数値文字列 | E51: 15 | F51: 3 | G51: =E50+G50 -> 421
B52: 47 | C52: 販売金額 | D52: 数値文字列 | E52: 14 | F52: 0 | G52: =E51+G51 -> 436
B53: 48 | C53: 消費税額 | D53: 数値文字列 | E53: 14 | F53: 0 | G53: =E52+G52 -> 450
B54: 49 | C54: 税込請求額 | D54: 数値文字列 | E54: 14 | F54: 0 | G54: =E53+G53 -> 464
B55: 50 | C55: 単価金額区分 | D55: 文字 | E55: 1 | G55: =E54+G54 -> 478
B56: 51 | C56: 取引区分 | D56: 文字 | E56: 1 | G56: =E55+G55 -> 479
B57: 52 | C57: 遡及区分 | D57: 文字 | E57: 1 | G57: =E56+G56 -> 480
B58: 53 | C58: 出荷請求区分 | D58: 文字 | E58: 1 | G58: =E57+G57 -> 481
B59: 54 | C59: 課税区分 | D59: 文字 | E59: 2 | G59: =E58+G58 -> 482
B60: 55 | C60: ﾊﾞﾂｸｵ-ﾀﾞ- 区分 | D60: 文字 | E60: 1 | G60: =E59+G59 -> 484
B61: 56 | C61: 出荷年月日(予定) | D61: 文字 | E61: 6 | G61: =E60+G60 -> 485
B62: 57 | C62: 出荷報告番号 | D62: 文字 | E62: 25 | G62: =E61+G61 -> 491
B63: 58 | C63: 出荷請求番号 | D63: 文字 | E63: 10 | G63: =E62+G62 -> 516
B64: 59 | C64: 出荷指図ｺﾒﾝﾄ(ｶﾅ) | D64: 文字 | E64: 44 | G64: =E63+G63 -> 526
B65: 60 | C65: 発注者情報 | D65: 文字 | E65: 20 | G65: =E64+G64 -> 570
B66: 61 | C66: 受注者情報 | D66: 文字 | E66: 20 | G66: =E65+G65 -> 590
... B71: 66 | C71: 予備欄(漢字) | D71: 文字 | E71: 30 | G71: =E70+G70 -> 666
B72: 67 | C72: 請求金額 | D72: 数値文字列 | E72: 14 | F72: 0 | G72: =E71+G71 -> 696
B73: 68 | C73: 空白5 | D73: 文字 | E73: 103 | G73: =E72+G72 -> 710
